{"count": 49, "c": 47, "f": 0, "o": 3, "n": 0, "photos": [{"read_count": 91, "image": {"large": {"url": "https://img9.doubanio.com/view/photo/l/public/p2427457769.webp", "width": 1600, "height": 900, "size": 0}, "raw": null, "small": {"url": "https://img9.doubanio.com/view/photo/s/public/p2427457769.webp", "width": 600, "height": 337, "size": 0}, "is_animated": false, "normal": {"url": "https://img9.doubanio.com/view/photo/m/public/p2427457769.webp", "width": 600, "height": 337, "size": 0}}, "create_time": "2017-02-11 18:54:16", "collections_count": 2, "reshares_count": 0, "id": "2427457769", "author": {"loc": null, "kind": "user", "name": "\u85fb\u6d77\u65e0\u8fb9", "url": "https://www.douban.com/people/35756167/", "reg_time": "2010-02-23 09:08:39", "uri": "douban://douban.com/user/35756167", "avatar_side_icon_id": "", "avatar": "https://img9.doubanio.com/icon/up35756167-31.jpg", "id": "35756167", "type": "user", "avatar_side_icon": "", "uid": "35756167"}, "is_collected": false, "subtype": "photo", "type": "photo", "owner_uri": "douban://douban.com/movie/1301998", "status": null, "reaction_type": 0, "description": "", "sharing_url": "https://www.douban.com/doubanapp/dispatch?uri=/photo/2427457769/", "url": "https://movie.douban.com/photos/photo/2427457769/", "reply_limit": "A", "uri": "douban://douban.com/photo/2427457769", "likers_count": 0, "reactions_count": 0, "comments_count": 0, "position": 44}, {"read_count": 39, "image": {"large": {"url": "https://img9.doubanio.com/view/photo/l/public/p2427457748.webp", "width": 1280, "height": 720, "size": 0}, "raw": null, "small": {"url": "https://img9.doubanio.com/view/photo/s/public/p2427457748.webp", "width": 600, "height": 337, "size": 0}, "is_animated": false, "normal": {"url": "https://img9.doubanio.com/view/photo/m/public/p2427457748.webp", "width": 600, "height": 337, "size": 0}}, "create_time": "2017-02-11 18:54:09", "collections_count": 0, "reshares_count": 0, "id": "2427457748", "author": {"loc": null, "kind": "user", "name": "\u85fb\u6d77\u65e0\u8fb9", "url": "https://www.douban.com/people/35756167/", "reg_time": "2010-02-23 09:08:39", "uri": "douban://douban.com/user/35756167", "avatar_side_icon_id": "", "avatar": "https://img9.doubanio.com/icon/up35756167-31.jpg", "id": "35756167", "type": "user", "avatar_side_icon": "", "uid": "35756167"}, "is_collected": false, "subtype": "photo", "type": "photo", "owner_uri": "douban://douban.com/movie/1301998", "status": null, "reaction_type": 0, "description": "", "sharing_url": "https://www.douban.com/doubanapp/dispatch?uri=/photo/2427457748/", "url": "https://movie.douban.com/photos/photo/2427457748/", "reply_limit": "A", "uri": "douban://douban.com/photo/2427457748", "likers_count": 0, "reactions_count": 0, "comments_count": 0, "position": 45}, {"read_count": 25, "image": {"large": {"url": "https://img9.doubanio.com/view/photo/l/public/p2427457743.webp", "width": 1280, "height": 720, "size": 0}, "raw": null, "small": {"url": "https://img9.doubanio.com/view/photo/s/public/p2427457743.webp", "width": 600, "height": 337, "size": 0}, "is_animated": false, "normal": {"url": "https://img9.doubanio.com/view/photo/m/public/p2427457743.webp", "width": 600, "height": 337, "size": 0}}, "create_time": "2017-02-11 18:54:07", "collections_count": 0, "reshares_count": 0, "id": "2427457743", "author": {"loc": null, "kind": "user", "name": "\u85fb\u6d77\u65e0\u8fb9", "url": "https://www.douban.com/people/35756167/", "reg_time": "2010-02-23 09:08:39", "uri": "douban://douban.com/user/35756167", "avatar_side_icon_id": "", "avatar": "https://img9.doubanio.com/icon/up35756167-31.jpg", "id": "35756167", "type": "user", "avatar_side_icon": "", "uid": "35756167"}, "is_collected": false, "subtype": "photo", "type": "photo", "owner_uri": "douban://douban.com/movie/1301998", "status": null, "reaction_type": 0, "description": "", "sharing_url": "https://www.douban.com/doubanapp/dispatch?uri=/photo/2427457743/", "url": "https://movie.douban.com/photos/photo/2427457743/", "reply_limit": "A", "uri": "douban://douban.com/photo/2427457743", "likers_count": 0, "reactions_count": 0, "comments_count": 0, "position": 46}, {"read_count": 3, "image": {"large": {"url": "https://img9.doubanio.com/view/photo/l/public/p2677935044.webp", "width": 1280, "height": 540, "size": 0}, "raw": null, "small": {"url": "https://img9.doubanio.com/view/photo/s/public/p2677935044.webp", "width": 600, "height": 253, "size": 0}, "is_animated": false, "normal": {"url": "https://img9.doubanio.com/view/photo/m/public/p2677935044.webp", "width": 600, "height": 253, "size": 0}}, "create_time": "2021-08-23 14:22:50", "collections_count": 0, "reshares_count": 0, "id": "2677935044", "author": {"loc": {"id": "108296", "name": "\u4e0a\u6d77", "uid": "shanghai"}, "kind": "user", "name": "\u5343\u5bfb\u4ebf\u9009", "url": "https://www.douban.com/people/2574034/", "reg_time": "2008-06-09 11:08:57", "uri": "douban://douban.com/user/2574034", "avatar_side_icon_id": "65", "avatar": "https://img9.doubanio.com/icon/up2574034-9.jpg", "id": "2574034", "type": "user", "avatar_side_icon": "https://img9.doubanio.com/view/files/raw/file-1662088254.png", "uid": "2574034"}, "is_collected": false, "subtype": "photo", "type": "photo", "owner_uri": "douban://douban.com/movie/1301998", "status": null, "reaction_type": 0, "description": "", "sharing_url": "https://www.douban.com/doubanapp/dispatch?uri=/photo/2677935044/", "url": "https://movie.douban.com/photos/photo/2677935044/", "reply_limit": "A", "uri": "douban://douban.com/photo/2677935044", "likers_count": 0, "reactions_count": 0, "comments_count": 0, "position": 0}, {"read_count": 1, "image": {"large": {"url": "https://img9.doubanio.com/view/photo/l/public/p2677935043.webp", "width": 1280, "height": 540, "size": 0}, "raw": null, "small": {"url": "https://img9.doubanio.com/view/photo/s/public/p2677935043.webp", "width": 600, "height": 253, "size": 0}, "is_animated": false, "normal": {"url": "https://img9.doubanio.com/view/photo/m/public/p2677935043.webp", "width": 600, "height": 253, "size": 0}}, "create_time": "2021-08-23 14:22:49", "collections_count": 0, "reshares_count": 0, "id": "2677935043", "author": {"loc": {"id": "108296", "name": "\u4e0a\u6d77", "uid": "shanghai"}, "kind": "user", "name": "\u5343\u5bfb\u4ebf\u9009", "url": "https://www.douban.com/people/2574034/", "reg_time": "2008-06-09 11:08:57", "uri": "douban://douban.com/user/2574034", "avatar_side_icon_id": "65", "avatar": "https://img9.doubanio.com/icon/up2574034-9.jpg", "id": "2574034", "type": "user", "avatar_side_icon": "https://img9.doubanio.com/view/files/raw/file-1662088254.png", "uid": "2574034"}, "is_collected": false, "subtype": "photo", "type": "photo", "owner_uri": "douban://douban.com/movie/1301998", "status": null, "reaction_type": 0, "description": "", "sharing_url": "https://www.douban.com/doubanapp/dispatch?uri=/photo/2677935043/", "url": "https://movie.douban.com/photos/photo/2677935043/", "reply_limit": "A", "uri": "douban://douban.com/photo/2677935043", "likers_count": 0, "reactions_count": 0, "comments_count": 0, "position": 1}, {"read_count": 1, "image": {"large": {"url": "https://img9.doubanio.com/view/photo/l/public/p2677935042.webp", "width": 1280, "height": 540, "size": 0}, "raw": null, "small": {"url": "https://img9.doubanio.com/view/photo/s/public/p2677935042.webp", "width": 600, "height": 253, "size": 0}, "is_animated": false, "normal": {"url": "https://img9.doubanio.com/view/photo/m/public/p2677935042.webp", "width": 600, "height": 253, "size": 0}}, "create_time": "2021-08-23 14:22:49", "collections_count": 0, "reshares_count": 0, "id": "2677935042", "author": {"loc": {"id": "108296", "name": "\u4e0a\u6d77", "uid": "shanghai"}, "kind": "user", "name": "\u5343\u5bfb\u4ebf\u9009", "url": "https://www.douban.com/people/2574034/", "reg_time": "2008-06-09 11:08:57", "uri": "douban://douban.com/user/2574034", "avatar_side_icon_id": "65", "avatar": "https://img9.doubanio.com/icon/up2574034-9.jpg", "id": "2574034", "type": "user", "avatar_side_icon": "https://img9.doubanio.com/view/files/raw/file-1662088254.png", "uid": "2574034"}, "is_collected": false, "subtype": "photo", "type": "photo", "owner_uri": "douban://douban.com/movie/1301998", "status": null, "reaction_type": 0, "description": "", "sharing_url": "https://www.douban.com/doubanapp/dispatch?uri=/photo/2677935042/", "url": "https://movie.douban.com/photos/photo/2677935042/", "reply_limit": "A", "uri": "douban://douban.com/photo/2677935042", "likers_count": 0, "reactions_count": 0, "comments_count": 0, "position": 2}, {"read_count": 1, "image": {"large": {"url": "https://img9.doubanio.com/view/photo/l/public/p2677935041.webp", "width": 1280, "height": 540, "size": 0}, "raw": null, "small": {"url": "https://img9.doubanio.com/view/photo/s/public/p2677935041.webp", "width": 600, "height": 253, "size": 0}, "is_animated": false, "normal": {"url": "https://img9.doubanio.com/view/photo/m/public/p2677935041.webp", "width": 600, "height": 253, "size": 0}}, "create_time": "2021-08-23 14:22:49", "collections_count": 0, "reshares_count": 0, "id": "2677935041", "author": {"loc": {"id": "108296", "name": "\u4e0a\u6d77", "uid": "shanghai"}, "kind": "user", "name": "\u5343\u5bfb\u4ebf\u9009", "url": "https://www.douban.com/people/2574034/", "reg_time": "2008-06-09 11:08:57", "uri": "douban://douban.com/user/2574034", "avatar_side_icon_id": "65", "avatar": "https://img9.doubanio.com/icon/up2574034-9.jpg", "id": "2574034", "type": "user", "avatar_side_icon": "https://img9.doubanio.com/view/files/raw/file-1662088254.png", "uid": "2574034"}, "is_collected": false, "subtype": "photo", "type": "photo", "owner_uri": "douban://douban.com/movie/1301998", "status": null, "reaction_type": 0, "description": "", "sharing_url": "https://www.douban.com/doubanapp/dispatch?uri=/photo/2677935041/", "url": "https://movie.douban.com/photos/photo/2677935041/", "reply_limit": "A", "uri": "douban://douban.com/photo/2677935041", "likers_count": 0, "reactions_count": 0, "comments_count": 0, "position": 3}, {"read_count": 0, "image": {"large": {"url": "https://img9.doubanio.com/view/photo/l/public/p2677935040.webp", "width": 1280, "height": 540, "size": 0}, "raw": null, "small": {"url": "https://img9.doubanio.com/view/photo/s/public/p2677935040.webp", "width": 600, "height": 253, "size": 0}, "is_animated": false, "normal": {"url": "https://img9.doubanio.com/view/photo/m/public/p2677935040.webp", "width": 600, "height": 253, "size": 0}}, "create_time": "2021-08-23 14:22:48", "collections_count": 0, "reshares_count": 0, "id": "2677935040", "author": {"loc": {"id": "108296", "name": "\u4e0a\u6d77", "uid": "shanghai"}, "kind": "user", "name": "\u5343\u5bfb\u4ebf\u9009", "url": "https://www.douban.com/people/2574034/", "reg_time": "2008-06-09 11:08:57", "uri": "douban://douban.com/user/2574034", "avatar_side_icon_id": "65", "avatar": "https://img9.doubanio.com/icon/up2574034-9.jpg", "id": "2574034", "type": "user", "avatar_side_icon": "https://img9.doubanio.com/view/files/raw/file-1662088254.png", "uid": "2574034"}, "is_collected": false, "subtype": "photo", "type": "photo", "owner_uri": "douban://douban.com/movie/1301998", "status": null, "reaction_type": 0, "description": "", "sharing_url": "https://www.douban.com/doubanapp/dispatch?uri=/photo/2677935040/", "url": "https://movie.douban.com/photos/photo/2677935040/", "reply_limit": "A", "uri": "douban://douban.com/photo/2677935040", "likers_count": 0, "reactions_count": 0, "comments_count": 0, "position": 4}, {"read_count": 1, "image": {"large": {"url": "https://img9.doubanio.com/view/photo/l/public/p2677935038.webp", "width": 1280, "height": 540, "size": 0}, "raw": null, "small": {"url": "https://img9.doubanio.com/view/photo/s/public/p2677935038.webp", "width": 600, "height": 253, "size": 0}, "is_animated": false, "normal": {"url": "https://img9.doubanio.com/view/photo/m/public/p2677935038.webp", "width": 600, "height": 253, "size": 0}}, "create_time": "2021-08-23 14:22:48", "collections_count": 0, "reshares_count": 0, "id": "2677935038", "author": {"loc": {"id": "108296", "name": "\u4e0a\u6d77", "uid": "shanghai"}, "kind": "user", "name": "\u5343\u5bfb\u4ebf\u9009", "url": "https://www.douban.com/people/2574034/", "reg_time": "2008-06-09 11:08:57", "uri": "douban://douban.com/user/2574034", "avatar_side_icon_id": "65", "avatar": "https://img9.doubanio.com/icon/up2574034-9.jpg", "id": "2574034", "type": "user", "avatar_side_icon": "https://img9.doubanio.com/view/files/raw/file-1662088254.png", "uid": "2574034"}, "is_collected": false, "subtype": "photo", "type": "photo", "owner_uri": "douban://douban.com/movie/1301998", "status": null, "reaction_type": 0, "description": "", "sharing_url": "https://www.douban.com/doubanapp/dispatch?uri=/photo/2677935038/", "url": "https://movie.douban.com/photos/photo/2677935038/", "reply_limit": "A", "uri": "douban://douban.com/photo/2677935038", "likers_count": 0, "reactions_count": 0, "comments_count": 0, "position": 5}, {"read_count": 2, "image": {"large": {"url": "https://img9.doubanio.com/view/photo/l/public/p2677935037.webp", "width": 1280, "height": 540, "size": 0}, "raw": null, "small": {"url": "https://img9.doubanio.com/view/photo/s/public/p2677935037.webp", "width": 600, "height": 253, "size": 0}, "is_animated": false, "normal": {"url": "https://img9.doubanio.com/view/photo/m/public/p2677935037.webp", "width": 600, "height": 253, "size": 0}}, "create_time": "2021-08-23 14:22:48", "collections_count": 0, "reshares_count": 0, "id": "2677935037", "author": {"loc": {"id": "108296", "name": "\u4e0a\u6d77", "uid": "shanghai"}, "kind": "user", "name": "\u5343\u5bfb\u4ebf\u9009", "url": "https://www.douban.com/people/2574034/", "reg_time": "2008-06-09 11:08:57", "uri": "douban://douban.com/user/2574034", "avatar_side_icon_id": "65", "avatar": "https://img9.doubanio.com/icon/up2574034-9.jpg", "id": "2574034", "type": "user", "avatar_side_icon": "https://img9.doubanio.com/view/files/raw/file-1662088254.png", "uid": "2574034"}, "is_collected": false, "subtype": "photo", "type": "photo", "owner_uri": "douban://douban.com/movie/1301998", "status": null, "reaction_type": 0, "description": "", "sharing_url": "https://www.douban.com/doubanapp/dispatch?uri=/photo/2677935037/", "url": "https://movie.douban.com/photos/photo/2677935037/", "reply_limit": "A", "uri": "douban://douban.com/photo/2677935037", "likers_count": 0, "reactions_count": 0, "comments_count": 0, "position": 6}, {"read_count": 1, "image": {"large": {"url": "https://img9.doubanio.com/view/photo/l/public/p2677935036.webp", "width": 1280, "height": 540, "size": 0}, "raw": null, "small": {"url": "https://img9.doubanio.com/view/photo/s/public/p2677935036.webp", "width": 600, "height": 253, "size": 0}, "is_animated": false, "normal": {"url": "https://img9.doubanio.com/view/photo/m/public/p2677935036.webp", "width": 600, "height": 253, "size": 0}}, "create_time": "2021-08-23 14:22:48", "collections_count": 0, "reshares_count": 0, "id": "2677935036", "author": {"loc": {"id": "108296", "name": "\u4e0a\u6d77", "uid": "shanghai"}, "kind": "user", "name": "\u5343\u5bfb\u4ebf\u9009", "url": "https://www.douban.com/people/2574034/", "reg_time": "2008-06-09 11:08:57", "uri": "douban://douban.com/user/2574034", "avatar_side_icon_id": "65", "avatar": "https://img9.doubanio.com/icon/up2574034-9.jpg", "id": "2574034", "type": "user", "avatar_side_icon": "https://img9.doubanio.com/view/files/raw/file-1662088254.png", "uid": "2574034"}, "is_collected": false, "subtype": "photo", "type": "photo", "owner_uri": "douban://douban.com/movie/1301998", "status": null, "reaction_type": 0, "description": "", "sharing_url": "https://www.douban.com/doubanapp/dispatch?uri=/photo/2677935036/", "url": "https://movie.douban.com/photos/photo/2677935036/", "reply_limit": "A", "uri": "douban://douban.com/photo/2677935036", "likers_count": 0, "reactions_count": 0, "comments_count": 0, "position": 7}, {"read_count": 2, "image": {"large": {"url": "https://img9.doubanio.com/view/photo/l/public/p2677935035.webp", "width": 1280, "height": 540, "size": 0}, "raw": null, "small": {"url": "https://img9.doubanio.com/view/photo/s/public/p2677935035.webp", "width": 600, "height": 253, "size": 0}, "is_animated": false, "normal": {"url": "https://img9.doubanio.com/view/photo/m/public/p2677935035.webp", "width": 600, "height": 253, "size": 0}}, "create_time": "2021-08-23 14:22:48", "collections_count": 0, "reshares_count": 0, "id": "2677935035", "author": {"loc": {"id": "108296", "name": "\u4e0a\u6d77", "uid": "shanghai"}, "kind": "user", "name": "\u5343\u5bfb\u4ebf\u9009", "url": "https://www.douban.com/people/2574034/", "reg_time": "2008-06-09 11:08:57", "uri": "douban://douban.com/user/2574034", "avatar_side_icon_id": "65", "avatar": "https://img9.doubanio.com/icon/up2574034-9.jpg", "id": "2574034", "type": "user", "avatar_side_icon": "https://img9.doubanio.com/view/files/raw/file-1662088254.png", "uid": "2574034"}, "is_collected": false, "subtype": "photo", "type": "photo", "owner_uri": "douban://douban.com/movie/1301998", "status": null, "reaction_type": 0, "description": "", "sharing_url": "https://www.douban.com/doubanapp/dispatch?uri=/photo/2677935035/", "url": "https://movie.douban.com/photos/photo/2677935035/", "reply_limit": "A", "uri": "douban://douban.com/photo/2677935035", "likers_count": 0, "reactions_count": 0, "comments_count": 0, "position": 8}, {"read_count": 1, "image": {"large": {"url": "https://img9.doubanio.com/view/photo/l/public/p2677935034.webp", "width": 1280, "height": 540, "size": 0}, "raw": null, "small": {"url": "https://img9.doubanio.com/view/photo/s/public/p2677935034.webp", "width": 600, "height": 253, "size": 0}, "is_animated": false, "normal": {"url": "https://img9.doubanio.com/view/photo/m/public/p2677935034.webp", "width": 600, "height": 253, "size": 0}}, "create_time": "2021-08-23 14:22:45", "collections_count": 0, "reshares_count": 0, "id": "2677935034", "author": {"loc": {"id": "108296", "name": "\u4e0a\u6d77", "uid": "shanghai"}, "kind": "user", "name": "\u5343\u5bfb\u4ebf\u9009", "url": "https://www.douban.com/people/2574034/", "reg_time": "2008-06-09 11:08:57", "uri": "douban://douban.com/user/2574034", "avatar_side_icon_id": "65", "avatar": "https://img9.doubanio.com/icon/up2574034-9.jpg", "id": "2574034", "type": "user", "avatar_side_icon": "https://img9.doubanio.com/view/files/raw/file-1662088254.png", "uid": "2574034"}, "is_collected": false, "subtype": "photo", "type": "photo", "owner_uri": "douban://douban.com/movie/1301998", "status": null, "reaction_type": 0, "description": "", "sharing_url": "https://www.douban.com/doubanapp/dispatch?uri=/photo/2677935034/", "url": "https://movie.douban.com/photos/photo/2677935034/", "reply_limit": "A", "uri": "douban://douban.com/photo/2677935034", "likers_count": 0, "reactions_count": 0, "comments_count": 0, "position": 9}, {"read_count": 1, "image": {"large": {"url": "https://img9.doubanio.com/view/photo/l/public/p2677935033.webp", "width": 1280, "height": 540, "size": 0}, "raw": null, "small": {"url": "https://img9.doubanio.com/view/photo/s/public/p2677935033.webp", "width": 600, "height": 253, "size": 0}, "is_animated": false, "normal": {"url": "https://img9.doubanio.com/view/photo/m/public/p2677935033.webp", "width": 600, "height": 253, "size": 0}}, "create_time": "2021-08-23 14:22:45", "collections_count": 0, "reshares_count": 0, "id": "2677935033", "author": {"loc": {"id": "108296", "name": "\u4e0a\u6d77", "uid": "shanghai"}, "kind": "user", "name": "\u5343\u5bfb\u4ebf\u9009", "url": "https://www.douban.com/people/2574034/", "reg_time": "2008-06-09 11:08:57", "uri": "douban://douban.com/user/2574034", "avatar_side_icon_id": "65", "avatar": "https://img9.doubanio.com/icon/up2574034-9.jpg", "id": "2574034", "type": "user", "avatar_side_icon": "https://img9.doubanio.com/view/files/raw/file-1662088254.png", "uid": "2574034"}, "is_collected": false, "subtype": "photo", "type": "photo", "owner_uri": "douban://douban.com/movie/1301998", "status": null, "reaction_type": 0, "description": "", "sharing_url": "https://www.douban.com/doubanapp/dispatch?uri=/photo/2677935033/", "url": "https://movie.douban.com/photos/photo/2677935033/", "reply_limit": "A", "uri": "douban://douban.com/photo/2677935033", "likers_count": 0, "reactions_count": 0, "comments_count": 0, "position": 10}, {"read_count": 0, "image": {"large": {"url": "https://img9.doubanio.com/view/photo/l/public/p2677935031.webp", "width": 1280, "height": 540, "size": 0}, "raw": null, "small": {"url": "https://img9.doubanio.com/view/photo/s/public/p2677935031.webp", "width": 600, "height": 253, "size": 0}, "is_animated": false, "normal": {"url": "https://img9.doubanio.com/view/photo/m/public/p2677935031.webp", "width": 600, "height": 253, "size": 0}}, "create_time": "2021-08-23 14:22:45", "collections_count": 0, "reshares_count": 0, "id": "2677935031", "author": {"loc": {"id": "108296", "name": "\u4e0a\u6d77", "uid": "shanghai"}, "kind": "user", "name": "\u5343\u5bfb\u4ebf\u9009", "url": "https://www.douban.com/people/2574034/", "reg_time": "2008-06-09 11:08:57", "uri": "douban://douban.com/user/2574034", "avatar_side_icon_id": "65", "avatar": "https://img9.doubanio.com/icon/up2574034-9.jpg", "id": "2574034", "type": "user", "avatar_side_icon": "https://img9.doubanio.com/view/files/raw/file-1662088254.png", "uid": "2574034"}, "is_collected": false, "subtype": "photo", "type": "photo", "owner_uri": "douban://douban.com/movie/1301998", "status": null, "reaction_type": 0, "description": "", "sharing_url": "https://www.douban.com/doubanapp/dispatch?uri=/photo/2677935031/", "url": "https://movie.douban.com/photos/photo/2677935031/", "reply_limit": "A", "uri": "douban://douban.com/photo/2677935031", "likers_count": 0, "reactions_count": 0, "comments_count": 0, "position": 11}, {"read_count": 0, "image": {"large": {"url": "https://img9.doubanio.com/view/photo/l/public/p2677935030.webp", "width": 1280, "height": 540, "size": 0}, "raw": null, "small": {"url": "https://img9.doubanio.com/view/photo/s/public/p2677935030.webp", "width": 600, "height": 253, "size": 0}, "is_animated": false, "normal": {"url": "https://img9.doubanio.com/view/photo/m/public/p2677935030.webp", "width": 600, "height": 253, "size": 0}}, "create_time": "2021-08-23 14:22:44", "collections_count": 0, "reshares_count": 0, "id": "2677935030", "author": {"loc": {"id": "108296", "name": "\u4e0a\u6d77", "uid": "shanghai"}, "kind": "user", "name": "\u5343\u5bfb\u4ebf\u9009", "url": "https://www.douban.com/people/2574034/", "reg_time": "2008-06-09 11:08:57", "uri": "douban://douban.com/user/2574034", "avatar_side_icon_id": "65", "avatar": "https://img9.doubanio.com/icon/up2574034-9.jpg", "id": "2574034", "type": "user", "avatar_side_icon": "https://img9.doubanio.com/view/files/raw/file-1662088254.png", "uid": "2574034"}, "is_collected": false, "subtype": "photo", "type": "photo", "owner_uri": "douban://douban.com/movie/1301998", "status": null, "reaction_type": 0, "description": "", "sharing_url": "https://www.douban.com/doubanapp/dispatch?uri=/photo/2677935030/", "url": "https://movie.douban.com/photos/photo/2677935030/", "reply_limit": "A", "uri": "douban://douban.com/photo/2677935030", "likers_count": 0, "reactions_count": 0, "comments_count": 0, "position": 12}, {"read_count": 0, "image": {"large": {"url": "https://img9.doubanio.com/view/photo/l/public/p2677935029.webp", "width": 1280, "height": 540, "size": 0}, "raw": null, "small": {"url": "https://img9.doubanio.com/view/photo/s/public/p2677935029.webp", "width": 600, "height": 253, "size": 0}, "is_animated": false, "normal": {"url": "https://img9.doubanio.com/view/photo/m/public/p2677935029.webp", "width": 600, "height": 253, "size": 0}}, "create_time": "2021-08-23 14:22:44", "collections_count": 0, "reshares_count": 0, "id": "2677935029", "author": {"loc": {"id": "108296", "name": "\u4e0a\u6d77", "uid": "shanghai"}, "kind": "user", "name": "\u5343\u5bfb\u4ebf\u9009", "url": "https://www.douban.com/people/2574034/", "reg_time": "2008-06-09 11:08:57", "uri": "douban://douban.com/user/2574034", "avatar_side_icon_id": "65", "avatar": "https://img9.doubanio.com/icon/up2574034-9.jpg", "id": "2574034", "type": "user", "avatar_side_icon": "https://img9.doubanio.com/view/files/raw/file-1662088254.png", "uid": "2574034"}, "is_collected": false, "subtype": "photo", "type": "photo", "owner_uri": "douban://douban.com/movie/1301998", "status": null, "reaction_type": 0, "description": "", "sharing_url": "https://www.douban.com/doubanapp/dispatch?uri=/photo/2677935029/", "url": "https://movie.douban.com/photos/photo/2677935029/", "reply_limit": "A", "uri": "douban://douban.com/photo/2677935029", "likers_count": 0, "reactions_count": 0, "comments_count": 0, "position": 13}, {"read_count": 0, "image": {"large": {"url": "https://img9.doubanio.com/view/photo/l/public/p2677935028.webp", "width": 1280, "height": 540, "size": 0}, "raw": null, "small": {"url": "https://img9.doubanio.com/view/photo/s/public/p2677935028.webp", "width": 600, "height": 253, "size": 0}, "is_animated": false, "normal": {"url": "https://img9.doubanio.com/view/photo/m/public/p2677935028.webp", "width": 600, "height": 253, "size": 0}}, "create_time": "2021-08-23 14:22:44", "collections_count": 0, "reshares_count": 0, "id": "2677935028", "author": {"loc": {"id": "108296", "name": "\u4e0a\u6d77", "uid": "shanghai"}, "kind": "user", "name": "\u5343\u5bfb\u4ebf\u9009", "url": "https://www.douban.com/people/2574034/", "reg_time": "2008-06-09 11:08:57", "uri": "douban://douban.com/user/2574034", "avatar_side_icon_id": "65", "avatar": "https://img9.doubanio.com/icon/up2574034-9.jpg", "id": "2574034", "type": "user", "avatar_side_icon": "https://img9.doubanio.com/view/files/raw/file-1662088254.png", "uid": "2574034"}, "is_collected": false, "subtype": "photo", "type": "photo", "owner_uri": "douban://douban.com/movie/1301998", "status": null, "reaction_type": 0, "description": "", "sharing_url": "https://www.douban.com/doubanapp/dispatch?uri=/photo/2677935028/", "url": "https://movie.douban.com/photos/photo/2677935028/", "reply_limit": "A", "uri": "douban://douban.com/photo/2677935028", "likers_count": 0, "reactions_count": 0, "comments_count": 0, "position": 14}, {"read_count": 2, "image": {"large": {"url": "https://img9.doubanio.com/view/photo/l/public/p2677935027.webp", "width": 1280, "height": 540, "size": 0}, "raw": null, "small": {"url": "https://img9.doubanio.com/view/photo/s/public/p2677935027.webp", "width": 600, "height": 253, "size": 0}, "is_animated": false, "normal": {"url": "https://img9.doubanio.com/view/photo/m/public/p2677935027.webp", "width": 600, "height": 253, "size": 0}}, "create_time": "2021-08-23 14:22:44", "collections_count": 0, "reshares_count": 0, "id": "2677935027", "author": {"loc": {"id": "108296", "name": "\u4e0a\u6d77", "uid": "shanghai"}, "kind": "user", "name": "\u5343\u5bfb\u4ebf\u9009", "url": "https://www.douban.com/people/2574034/", "reg_time": "2008-06-09 11:08:57", "uri": "douban://douban.com/user/2574034", "avatar_side_icon_id": "65", "avatar": "https://img9.doubanio.com/icon/up2574034-9.jpg", "id": "2574034", "type": "user", "avatar_side_icon": "https://img9.doubanio.com/view/files/raw/file-1662088254.png", "uid": "2574034"}, "is_collected": false, "subtype": "photo", "type": "photo", "owner_uri": "douban://douban.com/movie/1301998", "status": null, "reaction_type": 0, "description": "", "sharing_url": "https://www.douban.com/doubanapp/dispatch?uri=/photo/2677935027/", "url": "https://movie.douban.com/photos/photo/2677935027/", "reply_limit": "A", "uri": "douban://douban.com/photo/2677935027", "likers_count": 0, "reactions_count": 0, "comments_count": 0, "position": 15}, {"read_count": 0, "image": {"large": {"url": "https://img9.doubanio.com/view/photo/l/public/p2677935026.webp", "width": 1280, "height": 540, "size": 0}, "raw": null, "small": {"url": "https://img9.doubanio.com/view/photo/s/public/p2677935026.webp", "width": 600, "height": 253, "size": 0}, "is_animated": false, "normal": {"url": "https://img9.doubanio.com/view/photo/m/public/p2677935026.webp", "width": 600, "height": 253, "size": 0}}, "create_time": "2021-08-23 14:22:44", "collections_count": 0, "reshares_count": 0, "id": "2677935026", "author": {"loc": {"id": "108296", "name": "\u4e0a\u6d77", "uid": "shanghai"}, "kind": "user", "name": "\u5343\u5bfb\u4ebf\u9009", "url": "https://www.douban.com/people/2574034/", "reg_time": "2008-06-09 11:08:57", "uri": "douban://douban.com/user/2574034", "avatar_side_icon_id": "65", "avatar": "https://img9.doubanio.com/icon/up2574034-9.jpg", "id": "2574034", "type": "user", "avatar_side_icon": "https://img9.doubanio.com/view/files/raw/file-1662088254.png", "uid": "2574034"}, "is_collected": false, "subtype": "photo", "type": "photo", "owner_uri": "douban://douban.com/movie/1301998", "status": null, "reaction_type": 0, "description": "", "sharing_url": "https://www.douban.com/doubanapp/dispatch?uri=/photo/2677935026/", "url": "https://movie.douban.com/photos/photo/2677935026/", "reply_limit": "A", "uri": "douban://douban.com/photo/2677935026", "likers_count": 0, "reactions_count": 0, "comments_count": 0, "position": 16}, {"read_count": 0, "image": {"large": {"url": "https://img9.doubanio.com/view/photo/l/public/p2677935025.webp", "width": 1280, "height": 540, "size": 0}, "raw": null, "small": {"url": "https://img9.doubanio.com/view/photo/s/public/p2677935025.webp", "width": 600, "height": 253, "size": 0}, "is_animated": false, "normal": {"url": "https://img9.doubanio.com/view/photo/m/public/p2677935025.webp", "width": 600, "height": 253, "size": 0}}, "create_time": "2021-08-23 14:22:43", "collections_count": 0, "reshares_count": 0, "id": "2677935025", "author": {"loc": {"id": "108296", "name": "\u4e0a\u6d77", "uid": "shanghai"}, "kind": "user", "name": "\u5343\u5bfb\u4ebf\u9009", "url": "https://www.douban.com/people/2574034/", "reg_time": "2008-06-09 11:08:57", "uri": "douban://douban.com/user/2574034", "avatar_side_icon_id": "65", "avatar": "https://img9.doubanio.com/icon/up2574034-9.jpg", "id": "2574034", "type": "user", "avatar_side_icon": "https://img9.doubanio.com/view/files/raw/file-1662088254.png", "uid": "2574034"}, "is_collected": false, "subtype": "photo", "type": "photo", "owner_uri": "douban://douban.com/movie/1301998", "status": null, "reaction_type": 0, "description": "", "sharing_url": "https://www.douban.com/doubanapp/dispatch?uri=/photo/2677935025/", "url": "https://movie.douban.com/photos/photo/2677935025/", "reply_limit": "A", "uri": "douban://douban.com/photo/2677935025", "likers_count": 0, "reactions_count": 0, "comments_count": 0, "position": 17}, {"read_count": 1, "image": {"large": {"url": "https://img9.doubanio.com/view/photo/l/public/p2677935023.webp", "width": 1280, "height": 540, "size": 0}, "raw": null, "small": {"url": "https://img9.doubanio.com/view/photo/s/public/p2677935023.webp", "width": 600, "height": 253, "size": 0}, "is_animated": false, "normal": {"url": "https://img9.doubanio.com/view/photo/m/public/p2677935023.webp", "width": 600, "height": 253, "size": 0}}, "create_time": "2021-08-23 14:22:42", "collections_count": 0, "reshares_count": 0, "id": "2677935023", "author": {"loc": {"id": "108296", "name": "\u4e0a\u6d77", "uid": "shanghai"}, "kind": "user", "name": "\u5343\u5bfb\u4ebf\u9009", "url": "https://www.douban.com/people/2574034/", "reg_time": "2008-06-09 11:08:57", "uri": "douban://douban.com/user/2574034", "avatar_side_icon_id": "65", "avatar": "https://img9.doubanio.com/icon/up2574034-9.jpg", "id": "2574034", "type": "user", "avatar_side_icon": "https://img9.doubanio.com/view/files/raw/file-1662088254.png", "uid": "2574034"}, "is_collected": false, "subtype": "photo", "type": "photo", "owner_uri": "douban://douban.com/movie/1301998", "status": null, "reaction_type": 0, "description": "", "sharing_url": "https://www.douban.com/doubanapp/dispatch?uri=/photo/2677935023/", "url": "https://movie.douban.com/photos/photo/2677935023/", "reply_limit": "A", "uri": "douban://douban.com/photo/2677935023", "likers_count": 0, "reactions_count": 0, "comments_count": 0, "position": 18}, {"read_count": 0, "image": {"large": {"url": "https://img9.doubanio.com/view/photo/l/public/p2677935022.webp", "width": 1280, "height": 540, "size": 0}, "raw": null, "small": {"url": "https://img9.doubanio.com/view/photo/s/public/p2677935022.webp", "width": 600, "height": 253, "size": 0}, "is_animated": false, "normal": {"url": "https://img9.doubanio.com/view/photo/m/public/p2677935022.webp", "width": 600, "height": 253, "size": 0}}, "create_time": "2021-08-23 14:22:42", "collections_count": 0, "reshares_count": 0, "id": "2677935022", "author": {"loc": {"id": "108296", "name": "\u4e0a\u6d77", "uid": "shanghai"}, "kind": "user", "name": "\u5343\u5bfb\u4ebf\u9009", "url": "https://www.douban.com/people/2574034/", "reg_time": "2008-06-09 11:08:57", "uri": "douban://douban.com/user/2574034", "avatar_side_icon_id": "65", "avatar": "https://img9.doubanio.com/icon/up2574034-9.jpg", "id": "2574034", "type": "user", "avatar_side_icon": "https://img9.doubanio.com/view/files/raw/file-1662088254.png", "uid": "2574034"}, "is_collected": false, "subtype": "photo", "type": "photo", "owner_uri": "douban://douban.com/movie/1301998", "status": null, "reaction_type": 0, "description": "", "sharing_url": "https://www.douban.com/doubanapp/dispatch?uri=/photo/2677935022/", "url": "https://movie.douban.com/photos/photo/2677935022/", "reply_limit": "A", "uri": "douban://douban.com/photo/2677935022", "likers_count": 0, "reactions_count": 0, "comments_count": 0, "position": 19}, {"read_count": 1, "image": {"large": {"url": "https://img9.doubanio.com/view/photo/l/public/p2677935021.webp", "width": 1280, "height": 540, "size": 0}, "raw": null, "small": {"url": "https://img9.doubanio.com/view/photo/s/public/p2677935021.webp", "width": 600, "height": 253, "size": 0}, "is_animated": false, "normal": {"url": "https://img9.doubanio.com/view/photo/m/public/p2677935021.webp", "width": 600, "height": 253, "size": 0}}, "create_time": "2021-08-23 14:22:41", "collections_count": 0, "reshares_count": 0, "id": "2677935021", "author": {"loc": {"id": "108296", "name": "\u4e0a\u6d77", "uid": "shanghai"}, "kind": "user", "name": "\u5343\u5bfb\u4ebf\u9009", "url": "https://www.douban.com/people/2574034/", "reg_time": "2008-06-09 11:08:57", "uri": "douban://douban.com/user/2574034", "avatar_side_icon_id": "65", "avatar": "https://img9.doubanio.com/icon/up2574034-9.jpg", "id": "2574034", "type": "user", "avatar_side_icon": "https://img9.doubanio.com/view/files/raw/file-1662088254.png", "uid": "2574034"}, "is_collected": false, "subtype": "photo", "type": "photo", "owner_uri": "douban://douban.com/movie/1301998", "status": null, "reaction_type": 0, "description": "", "sharing_url": "https://www.douban.com/doubanapp/dispatch?uri=/photo/2677935021/", "url": "https://movie.douban.com/photos/photo/2677935021/", "reply_limit": "A", "uri": "douban://douban.com/photo/2677935021", "likers_count": 0, "reactions_count": 0, "comments_count": 0, "position": 20}, {"read_count": 0, "image": {"large": {"url": "https://img9.doubanio.com/view/photo/l/public/p2677935020.webp", "width": 1280, "height": 540, "size": 0}, "raw": null, "small": {"url": "https://img9.doubanio.com/view/photo/s/public/p2677935020.webp", "width": 600, "height": 253, "size": 0}, "is_animated": false, "normal": {"url": "https://img9.doubanio.com/view/photo/m/public/p2677935020.webp", "width": 600, "height": 253, "size": 0}}, "create_time": "2021-08-23 14:22:41", "collections_count": 0, "reshares_count": 0, "id": "2677935020", "author": {"loc": {"id": "108296", "name": "\u4e0a\u6d77", "uid": "shanghai"}, "kind": "user", "name": "\u5343\u5bfb\u4ebf\u9009", "url": "https://www.douban.com/people/2574034/", "reg_time": "2008-06-09 11:08:57", "uri": "douban://douban.com/user/2574034", "avatar_side_icon_id": "65", "avatar": "https://img9.doubanio.com/icon/up2574034-9.jpg", "id": "2574034", "type": "user", "avatar_side_icon": "https://img9.doubanio.com/view/files/raw/file-1662088254.png", "uid": "2574034"}, "is_collected": false, "subtype": "photo", "type": "photo", "owner_uri": "douban://douban.com/movie/1301998", "status": null, "reaction_type": 0, "description": "", "sharing_url": "https://www.douban.com/doubanapp/dispatch?uri=/photo/2677935020/", "url": "https://movie.douban.com/photos/photo/2677935020/", "reply_limit": "A", "uri": "douban://douban.com/photo/2677935020", "likers_count": 0, "reactions_count": 0, "comments_count": 0, "position": 21}, {"read_count": 0, "image": {"large": {"url": "https://img9.doubanio.com/view/photo/l/public/p2677935019.webp", "width": 1280, "height": 540, "size": 0}, "raw": null, "small": {"url": "https://img9.doubanio.com/view/photo/s/public/p2677935019.webp", "width": 600, "height": 253, "size": 0}, "is_animated": false, "normal": {"url": "https://img9.doubanio.com/view/photo/m/public/p2677935019.webp", "width": 600, "height": 253, "size": 0}}, "create_time": "2021-08-23 14:22:41", "collections_count": 0, "reshares_count": 0, "id": "2677935019", "author": {"loc": {"id": "108296", "name": "\u4e0a\u6d77", "uid": "shanghai"}, "kind": "user", "name": "\u5343\u5bfb\u4ebf\u9009", "url": "https://www.douban.com/people/2574034/", "reg_time": "2008-06-09 11:08:57", "uri": "douban://douban.com/user/2574034", "avatar_side_icon_id": "65", "avatar": "https://img9.doubanio.com/icon/up2574034-9.jpg", "id": "2574034", "type": "user", "avatar_side_icon": "https://img9.doubanio.com/view/files/raw/file-1662088254.png", "uid": "2574034"}, "is_collected": false, "subtype": "photo", "type": "photo", "owner_uri": "douban://douban.com/movie/1301998", "status": null, "reaction_type": 0, "description": "", "sharing_url": "https://www.douban.com/doubanapp/dispatch?uri=/photo/2677935019/", "url": "https://movie.douban.com/photos/photo/2677935019/", "reply_limit": "A", "uri": "douban://douban.com/photo/2677935019", "likers_count": 0, "reactions_count": 0, "comments_count": 0, "position": 22}, {"read_count": 2, "image": {"large": {"url": "https://img9.doubanio.com/view/photo/l/public/p2677935018.webp", "width": 1280, "height": 540, "size": 0}, "raw": null, "small": {"url": "https://img9.doubanio.com/view/photo/s/public/p2677935018.webp", "width": 600, "height": 253, "size": 0}, "is_animated": false, "normal": {"url": "https://img9.doubanio.com/view/photo/m/public/p2677935018.webp", "width": 600, "height": 253, "size": 0}}, "create_time": "2021-08-23 14:22:40", "collections_count": 0, "reshares_count": 0, "id": "2677935018", "author": {"loc": {"id": "108296", "name": "\u4e0a\u6d77", "uid": "shanghai"}, "kind": "user", "name": "\u5343\u5bfb\u4ebf\u9009", "url": "https://www.douban.com/people/2574034/", "reg_time": "2008-06-09 11:08:57", "uri": "douban://douban.com/user/2574034", "avatar_side_icon_id": "65", "avatar": "https://img9.doubanio.com/icon/up2574034-9.jpg", "id": "2574034", "type": "user", "avatar_side_icon": "https://img9.doubanio.com/view/files/raw/file-1662088254.png", "uid": "2574034"}, "is_collected": false, "subtype": "photo", "type": "photo", "owner_uri": "douban://douban.com/movie/1301998", "status": null, "reaction_type": 0, "description": "", "sharing_url": "https://www.douban.com/doubanapp/dispatch?uri=/photo/2677935018/", "url": "https://movie.douban.com/photos/photo/2677935018/", "reply_limit": "A", "uri": "douban://douban.com/photo/2677935018", "likers_count": 0, "reactions_count": 0, "comments_count": 0, "position": 23}, {"read_count": 0, "image": {"large": {"url": "https://img9.doubanio.com/view/photo/l/public/p2677935016.webp", "width": 1280, "height": 540, "size": 0}, "raw": null, "small": {"url": "https://img9.doubanio.com/view/photo/s/public/p2677935016.webp", "width": 600, "height": 253, "size": 0}, "is_animated": false, "normal": {"url": "https://img9.doubanio.com/view/photo/m/public/p2677935016.webp", "width": 600, "height": 253, "size": 0}}, "create_time": "2021-08-23 14:22:39", "collections_count": 0, "reshares_count": 0, "id": "2677935016", "author": {"loc": {"id": "108296", "name": "\u4e0a\u6d77", "uid": "shanghai"}, "kind": "user", "name": "\u5343\u5bfb\u4ebf\u9009", "url": "https://www.douban.com/people/2574034/", "reg_time": "2008-06-09 11:08:57", "uri": "douban://douban.com/user/2574034", "avatar_side_icon_id": "65", "avatar": "https://img9.doubanio.com/icon/up2574034-9.jpg", "id": "2574034", "type": "user", "avatar_side_icon": "https://img9.doubanio.com/view/files/raw/file-1662088254.png", "uid": "2574034"}, "is_collected": false, "subtype": "photo", "type": "photo", "owner_uri": "douban://douban.com/movie/1301998", "status": null, "reaction_type": 0, "description": "", "sharing_url": "https://www.douban.com/doubanapp/dispatch?uri=/photo/2677935016/", "url": "https://movie.douban.com/photos/photo/2677935016/", "reply_limit": "A", "uri": "douban://douban.com/photo/2677935016", "likers_count": 0, "reactions_count": 0, "comments_count": 0, "position": 24}, {"read_count": 0, "image": {"large": {"url": "https://img9.doubanio.com/view/photo/l/public/p2677935015.webp", "width": 1280, "height": 540, "size": 0}, "raw": null, "small": {"url": "https://img9.doubanio.com/view/photo/s/public/p2677935015.webp", "width": 600, "height": 253, "size": 0}, "is_animated": false, "normal": {"url": "https://img9.doubanio.com/view/photo/m/public/p2677935015.webp", "width": 600, "height": 253, "size": 0}}, "create_time": "2021-08-23 14:22:39", "collections_count": 0, "reshares_count": 0, "id": "2677935015", "author": {"loc": {"id": "108296", "name": "\u4e0a\u6d77", "uid": "shanghai"}, "kind": "user", "name": "\u5343\u5bfb\u4ebf\u9009", "url": "https://www.douban.com/people/2574034/", "reg_time": "2008-06-09 11:08:57", "uri": "douban://douban.com/user/2574034", "avatar_side_icon_id": "65", "avatar": "https://img9.doubanio.com/icon/up2574034-9.jpg", "id": "2574034", "type": "user", "avatar_side_icon": "https://img9.doubanio.com/view/files/raw/file-1662088254.png", "uid": "2574034"}, "is_collected": false, "subtype": "photo", "type": "photo", "owner_uri": "douban://douban.com/movie/1301998", "status": null, "reaction_type": 0, "description": "", "sharing_url": "https://www.douban.com/doubanapp/dispatch?uri=/photo/2677935015/", "url": "https://movie.douban.com/photos/photo/2677935015/", "reply_limit": "A", "uri": "douban://douban.com/photo/2677935015", "likers_count": 0, "reactions_count": 0, "comments_count": 0, "position": 25}, {"read_count": 0, "image": {"large": {"url": "https://img9.doubanio.com/view/photo/l/public/p2677935014.webp", "width": 1280, "height": 540, "size": 0}, "raw": null, "small": {"url": "https://img9.doubanio.com/view/photo/s/public/p2677935014.webp", "width": 600, "height": 253, "size": 0}, "is_animated": false, "normal": {"url": "https://img9.doubanio.com/view/photo/m/public/p2677935014.webp", "width": 600, "height": 253, "size": 0}}, "create_time": "2021-08-23 14:22:39", "collections_count": 0, "reshares_count": 0, "id": "2677935014", "author": {"loc": {"id": "108296", "name": "\u4e0a\u6d77", "uid": "shanghai"}, "kind": "user", "name": "\u5343\u5bfb\u4ebf\u9009", "url": "https://www.douban.com/people/2574034/", "reg_time": "2008-06-09 11:08:57", "uri": "douban://douban.com/user/2574034", "avatar_side_icon_id": "65", "avatar": "https://img9.doubanio.com/icon/up2574034-9.jpg", "id": "2574034", "type": "user", "avatar_side_icon": "https://img9.doubanio.com/view/files/raw/file-1662088254.png", "uid": "2574034"}, "is_collected": false, "subtype": "photo", "type": "photo", "owner_uri": "douban://douban.com/movie/1301998", "status": null, "reaction_type": 0, "description": "", "sharing_url": "https://www.douban.com/doubanapp/dispatch?uri=/photo/2677935014/", "url": "https://movie.douban.com/photos/photo/2677935014/", "reply_limit": "A", "uri": "douban://douban.com/photo/2677935014", "likers_count": 0, "reactions_count": 0, "comments_count": 0, "position": 26}, {"read_count": 0, "image": {"large": {"url": "https://img9.doubanio.com/view/photo/l/public/p2677935013.webp", "width": 1280, "height": 540, "size": 0}, "raw": null, "small": {"url": "https://img9.doubanio.com/view/photo/s/public/p2677935013.webp", "width": 600, "height": 253, "size": 0}, "is_animated": false, "normal": {"url": "https://img9.doubanio.com/view/photo/m/public/p2677935013.webp", "width": 600, "height": 253, "size": 0}}, "create_time": "2021-08-23 14:22:38", "collections_count": 0, "reshares_count": 0, "id": "2677935013", "author": {"loc": {"id": "108296", "name": "\u4e0a\u6d77", "uid": "shanghai"}, "kind": "user", "name": "\u5343\u5bfb\u4ebf\u9009", "url": "https://www.douban.com/people/2574034/", "reg_time": "2008-06-09 11:08:57", "uri": "douban://douban.com/user/2574034", "avatar_side_icon_id": "65", "avatar": "https://img9.doubanio.com/icon/up2574034-9.jpg", "id": "2574034", "type": "user", "avatar_side_icon": "https://img9.doubanio.com/view/files/raw/file-1662088254.png", "uid": "2574034"}, "is_collected": false, "subtype": "photo", "type": "photo", "owner_uri": "douban://douban.com/movie/1301998", "status": null, "reaction_type": 0, "description": "", "sharing_url": "https://www.douban.com/doubanapp/dispatch?uri=/photo/2677935013/", "url": "https://movie.douban.com/photos/photo/2677935013/", "reply_limit": "A", "uri": "douban://douban.com/photo/2677935013", "likers_count": 0, "reactions_count": 0, "comments_count": 0, "position": 27}, {"read_count": 0, "image": {"large": {"url": "https://img9.doubanio.com/view/photo/l/public/p2677935012.webp", "width": 1280, "height": 540, "size": 0}, "raw": null, "small": {"url": "https://img9.doubanio.com/view/photo/s/public/p2677935012.webp", "width": 600, "height": 253, "size": 0}, "is_animated": false, "normal": {"url": "https://img9.doubanio.com/view/photo/m/public/p2677935012.webp", "width": 600, "height": 253, "size": 0}}, "create_time": "2021-08-23 14:22:38", "collections_count": 0, "reshares_count": 0, "id": "2677935012", "author": {"loc": {"id": "108296", "name": "\u4e0a\u6d77", "uid": "shanghai"}, "kind": "user", "name": "\u5343\u5bfb\u4ebf\u9009", "url": "https://www.douban.com/people/2574034/", "reg_time": "2008-06-09 11:08:57", "uri": "douban://douban.com/user/2574034", "avatar_side_icon_id": "65", "avatar": "https://img9.doubanio.com/icon/up2574034-9.jpg", "id": "2574034", "type": "user", "avatar_side_icon": "https://img9.doubanio.com/view/files/raw/file-1662088254.png", "uid": "2574034"}, "is_collected": false, "subtype": "photo", "type": "photo", "owner_uri": "douban://douban.com/movie/1301998", "status": null, "reaction_type": 0, "description": "", "sharing_url": "https://www.douban.com/doubanapp/dispatch?uri=/photo/2677935012/", "url": "https://movie.douban.com/photos/photo/2677935012/", "reply_limit": "A", "uri": "douban://douban.com/photo/2677935012", "likers_count": 0, "reactions_count": 0, "comments_count": 0, "position": 28}, {"read_count": 0, "image": {"large": {"url": "https://img9.doubanio.com/view/photo/l/public/p2677935008.webp", "width": 1280, "height": 540, "size": 0}, "raw": null, "small": {"url": "https://img9.doubanio.com/view/photo/s/public/p2677935008.webp", "width": 600, "height": 253, "size": 0}, "is_animated": false, "normal": {"url": "https://img9.doubanio.com/view/photo/m/public/p2677935008.webp", "width": 600, "height": 253, "size": 0}}, "create_time": "2021-08-23 14:22:37", "collections_count": 0, "reshares_count": 0, "id": "2677935008", "author": {"loc": {"id": "108296", "name": "\u4e0a\u6d77", "uid": "shanghai"}, "kind": "user", "name": "\u5343\u5bfb\u4ebf\u9009", "url": "https://www.douban.com/people/2574034/", "reg_time": "2008-06-09 11:08:57", "uri": "douban://douban.com/user/2574034", "avatar_side_icon_id": "65", "avatar": "https://img9.doubanio.com/icon/up2574034-9.jpg", "id": "2574034", "type": "user", "avatar_side_icon": "https://img9.doubanio.com/view/files/raw/file-1662088254.png", "uid": "2574034"}, "is_collected": false, "subtype": "photo", "type": "photo", "owner_uri": "douban://douban.com/movie/1301998", "status": null, "reaction_type": 0, "description": "", "sharing_url": "https://www.douban.com/doubanapp/dispatch?uri=/photo/2677935008/", "url": "https://movie.douban.com/photos/photo/2677935008/", "reply_limit": "A", "uri": "douban://douban.com/photo/2677935008", "likers_count": 0, "reactions_count": 0, "comments_count": 0, "position": 29}, {"read_count": 1, "image": {"large": {"url": "https://img9.doubanio.com/view/photo/l/public/p2677935005.webp", "width": 1280, "height": 540, "size": 0}, "raw": null, "small": {"url": "https://img9.doubanio.com/view/photo/s/public/p2677935005.webp", "width": 600, "height": 253, "size": 0}, "is_animated": false, "normal": {"url": "https://img9.doubanio.com/view/photo/m/public/p2677935005.webp", "width": 600, "height": 253, "size": 0}}, "create_time": "2021-08-23 14:22:37", "collections_count": 0, "reshares_count": 0, "id": "2677935005", "author": {"loc": {"id": "108296", "name": "\u4e0a\u6d77", "uid": "shanghai"}, "kind": "user", "name": "\u5343\u5bfb\u4ebf\u9009", "url": "https://www.douban.com/people/2574034/", "reg_time": "2008-06-09 11:08:57", "uri": "douban://douban.com/user/2574034", "avatar_side_icon_id": "65", "avatar": "https://img9.doubanio.com/icon/up2574034-9.jpg", "id": "2574034", "type": "user", "avatar_side_icon": "https://img9.doubanio.com/view/files/raw/file-1662088254.png", "uid": "2574034"}, "is_collected": false, "subtype": "photo", "type": "photo", "owner_uri": "douban://douban.com/movie/1301998", "status": null, "reaction_type": 0, "description": "", "sharing_url": "https://www.douban.com/doubanapp/dispatch?uri=/photo/2677935005/", "url": "https://movie.douban.com/photos/photo/2677935005/", "reply_limit": "A", "uri": "douban://douban.com/photo/2677935005", "likers_count": 0, "reactions_count": 0, "comments_count": 0, "position": 30}, {"read_count": 0, "image": {"large": {"url": "https://img9.doubanio.com/view/photo/l/public/p2677935004.webp", "width": 1280, "height": 540, "size": 0}, "raw": null, "small": {"url": "https://img9.doubanio.com/view/photo/s/public/p2677935004.webp", "width": 600, "height": 253, "size": 0}, "is_animated": false, "normal": {"url": "https://img9.doubanio.com/view/photo/m/public/p2677935004.webp", "width": 600, "height": 253, "size": 0}}, "create_time": "2021-08-23 14:22:36", "collections_count": 0, "reshares_count": 0, "id": "2677935004", "author": {"loc": {"id": "108296", "name": "\u4e0a\u6d77", "uid": "shanghai"}, "kind": "user", "name": "\u5343\u5bfb\u4ebf\u9009", "url": "https://www.douban.com/people/2574034/", "reg_time": "2008-06-09 11:08:57", "uri": "douban://douban.com/user/2574034", "avatar_side_icon_id": "65", "avatar": "https://img9.doubanio.com/icon/up2574034-9.jpg", "id": "2574034", "type": "user", "avatar_side_icon": "https://img9.doubanio.com/view/files/raw/file-1662088254.png", "uid": "2574034"}, "is_collected": false, "subtype": "photo", "type": "photo", "owner_uri": "douban://douban.com/movie/1301998", "status": null, "reaction_type": 0, "description": "", "sharing_url": "https://www.douban.com/doubanapp/dispatch?uri=/photo/2677935004/", "url": "https://movie.douban.com/photos/photo/2677935004/", "reply_limit": "A", "uri": "douban://douban.com/photo/2677935004", "likers_count": 0, "reactions_count": 0, "comments_count": 0, "position": 31}, {"read_count": 1, "image": {"large": {"url": "https://img9.doubanio.com/view/photo/l/public/p2677935003.webp", "width": 1280, "height": 540, "size": 0}, "raw": null, "small": {"url": "https://img9.doubanio.com/view/photo/s/public/p2677935003.webp", "width": 600, "height": 253, "size": 0}, "is_animated": false, "normal": {"url": "https://img9.doubanio.com/view/photo/m/public/p2677935003.webp", "width": 600, "height": 253, "size": 0}}, "create_time": "2021-08-23 14:22:36", "collections_count": 0, "reshares_count": 0, "id": "2677935003", "author": {"loc": {"id": "108296", "name": "\u4e0a\u6d77", "uid": "shanghai"}, "kind": "user", "name": "\u5343\u5bfb\u4ebf\u9009", "url": "https://www.douban.com/people/2574034/", "reg_time": "2008-06-09 11:08:57", "uri": "douban://douban.com/user/2574034", "avatar_side_icon_id": "65", "avatar": "https://img9.doubanio.com/icon/up2574034-9.jpg", "id": "2574034", "type": "user", "avatar_side_icon": "https://img9.doubanio.com/view/files/raw/file-1662088254.png", "uid": "2574034"}, "is_collected": false, "subtype": "photo", "type": "photo", "owner_uri": "douban://douban.com/movie/1301998", "status": null, "reaction_type": 0, "description": "", "sharing_url": "https://www.douban.com/doubanapp/dispatch?uri=/photo/2677935003/", "url": "https://movie.douban.com/photos/photo/2677935003/", "reply_limit": "A", "uri": "douban://douban.com/photo/2677935003", "likers_count": 0, "reactions_count": 0, "comments_count": 0, "position": 32}, {"read_count": 0, "image": {"large": {"url": "https://img9.doubanio.com/view/photo/l/public/p2677934996.webp", "width": 1280, "height": 540, "size": 0}, "raw": null, "small": {"url": "https://img9.doubanio.com/view/photo/s/public/p2677934996.webp", "width": 600, "height": 253, "size": 0}, "is_animated": false, "normal": {"url": "https://img9.doubanio.com/view/photo/m/public/p2677934996.webp", "width": 600, "height": 253, "size": 0}}, "create_time": "2021-08-23 14:22:36", "collections_count": 0, "reshares_count": 0, "id": "2677934996", "author": {"loc": {"id": "108296", "name": "\u4e0a\u6d77", "uid": "shanghai"}, "kind": "user", "name": "\u5343\u5bfb\u4ebf\u9009", "url": "https://www.douban.com/people/2574034/", "reg_time": "2008-06-09 11:08:57", "uri": "douban://douban.com/user/2574034", "avatar_side_icon_id": "65", "avatar": "https://img9.doubanio.com/icon/up2574034-9.jpg", "id": "2574034", "type": "user", "avatar_side_icon": "https://img9.doubanio.com/view/files/raw/file-1662088254.png", "uid": "2574034"}, "is_collected": false, "subtype": "photo", "type": "photo", "owner_uri": "douban://douban.com/movie/1301998", "status": null, "reaction_type": 0, "description": "", "sharing_url": "https://www.douban.com/doubanapp/dispatch?uri=/photo/2677934996/", "url": "https://movie.douban.com/photos/photo/2677934996/", "reply_limit": "A", "uri": "douban://douban.com/photo/2677934996", "likers_count": 0, "reactions_count": 0, "comments_count": 0, "position": 33}, {"read_count": 0, "image": {"large": {"url": "https://img9.doubanio.com/view/photo/l/public/p2677934995.webp", "width": 1280, "height": 540, "size": 0}, "raw": null, "small": {"url": "https://img9.doubanio.com/view/photo/s/public/p2677934995.webp", "width": 600, "height": 253, "size": 0}, "is_animated": false, "normal": {"url": "https://img9.doubanio.com/view/photo/m/public/p2677934995.webp", "width": 600, "height": 253, "size": 0}}, "create_time": "2021-08-23 14:22:36", "collections_count": 0, "reshares_count": 0, "id": "2677934995", "author": {"loc": {"id": "108296", "name": "\u4e0a\u6d77", "uid": "shanghai"}, "kind": "user", "name": "\u5343\u5bfb\u4ebf\u9009", "url": "https://www.douban.com/people/2574034/", "reg_time": "2008-06-09 11:08:57", "uri": "douban://douban.com/user/2574034", "avatar_side_icon_id": "65", "avatar": "https://img9.doubanio.com/icon/up2574034-9.jpg", "id": "2574034", "type": "user", "avatar_side_icon": "https://img9.doubanio.com/view/files/raw/file-1662088254.png", "uid": "2574034"}, "is_collected": false, "subtype": "photo", "type": "photo", "owner_uri": "douban://douban.com/movie/1301998", "status": null, "reaction_type": 0, "description": "", "sharing_url": "https://www.douban.com/doubanapp/dispatch?uri=/photo/2677934995/", "url": "https://movie.douban.com/photos/photo/2677934995/", "reply_limit": "A", "uri": "douban://douban.com/photo/2677934995", "likers_count": 0, "reactions_count": 0, "comments_count": 0, "position": 34}, {"read_count": 0, "image": {"large": {"url": "https://img9.doubanio.com/view/photo/l/public/p2677934994.webp", "width": 1280, "height": 540, "size": 0}, "raw": null, "small": {"url": "https://img9.doubanio.com/view/photo/s/public/p2677934994.webp", "width": 600, "height": 253, "size": 0}, "is_animated": false, "normal": {"url": "https://img9.doubanio.com/view/photo/m/public/p2677934994.webp", "width": 600, "height": 253, "size": 0}}, "create_time": "2021-08-23 14:22:36", "collections_count": 0, "reshares_count": 0, "id": "2677934994", "author": {"loc": {"id": "108296", "name": "\u4e0a\u6d77", "uid": "shanghai"}, "kind": "user", "name": "\u5343\u5bfb\u4ebf\u9009", "url": "https://www.douban.com/people/2574034/", "reg_time": "2008-06-09 11:08:57", "uri": "douban://douban.com/user/2574034", "avatar_side_icon_id": "65", "avatar": "https://img9.doubanio.com/icon/up2574034-9.jpg", "id": "2574034", "type": "user", "avatar_side_icon": "https://img9.doubanio.com/view/files/raw/file-1662088254.png", "uid": "2574034"}, "is_collected": false, "subtype": "photo", "type": "photo", "owner_uri": "douban://douban.com/movie/1301998", "status": null, "reaction_type": 0, "description": "", "sharing_url": "https://www.douban.com/doubanapp/dispatch?uri=/photo/2677934994/", "url": "https://movie.douban.com/photos/photo/2677934994/", "reply_limit": "A", "uri": "douban://douban.com/photo/2677934994", "likers_count": 0, "reactions_count": 0, "comments_count": 0, "position": 35}, {"read_count": 1, "image": {"large": {"url": "https://img9.doubanio.com/view/photo/l/public/p2677934993.webp", "width": 1280, "height": 540, "size": 0}, "raw": null, "small": {"url": "https://img9.doubanio.com/view/photo/s/public/p2677934993.webp", "width": 600, "height": 253, "size": 0}, "is_animated": false, "normal": {"url": "https://img9.doubanio.com/view/photo/m/public/p2677934993.webp", "width": 600, "height": 253, "size": 0}}, "create_time": "2021-08-23 14:22:35", "collections_count": 0, "reshares_count": 0, "id": "2677934993", "author": {"loc": {"id": "108296", "name": "\u4e0a\u6d77", "uid": "shanghai"}, "kind": "user", "name": "\u5343\u5bfb\u4ebf\u9009", "url": "https://www.douban.com/people/2574034/", "reg_time": "2008-06-09 11:08:57", "uri": "douban://douban.com/user/2574034", "avatar_side_icon_id": "65", "avatar": "https://img9.doubanio.com/icon/up2574034-9.jpg", "id": "2574034", "type": "user", "avatar_side_icon": "https://img9.doubanio.com/view/files/raw/file-1662088254.png", "uid": "2574034"}, "is_collected": false, "subtype": "photo", "type": "photo", "owner_uri": "douban://douban.com/movie/1301998", "status": null, "reaction_type": 0, "description": "", "sharing_url": "https://www.douban.com/doubanapp/dispatch?uri=/photo/2677934993/", "url": "https://movie.douban.com/photos/photo/2677934993/", "reply_limit": "A", "uri": "douban://douban.com/photo/2677934993", "likers_count": 0, "reactions_count": 0, "comments_count": 0, "position": 36}, {"read_count": 0, "image": {"large": {"url": "https://img9.doubanio.com/view/photo/l/public/p2677934991.webp", "width": 1280, "height": 540, "size": 0}, "raw": null, "small": {"url": "https://img9.doubanio.com/view/photo/s/public/p2677934991.webp", "width": 600, "height": 253, "size": 0}, "is_animated": false, "normal": {"url": "https://img9.doubanio.com/view/photo/m/public/p2677934991.webp", "width": 600, "height": 253, "size": 0}}, "create_time": "2021-08-23 14:22:34", "collections_count": 0, "reshares_count": 0, "id": "2677934991", "author": {"loc": {"id": "108296", "name": "\u4e0a\u6d77", "uid": "shanghai"}, "kind": "user", "name": "\u5343\u5bfb\u4ebf\u9009", "url": "https://www.douban.com/people/2574034/", "reg_time": "2008-06-09 11:08:57", "uri": "douban://douban.com/user/2574034", "avatar_side_icon_id": "65", "avatar": "https://img9.doubanio.com/icon/up2574034-9.jpg", "id": "2574034", "type": "user", "avatar_side_icon": "https://img9.doubanio.com/view/files/raw/file-1662088254.png", "uid": "2574034"}, "is_collected": false, "subtype": "photo", "type": "photo", "owner_uri": "douban://douban.com/movie/1301998", "status": null, "reaction_type": 0, "description": "", "sharing_url": "https://www.douban.com/doubanapp/dispatch?uri=/photo/2677934991/", "url": "https://movie.douban.com/photos/photo/2677934991/", "reply_limit": "A", "uri": "douban://douban.com/photo/2677934991", "likers_count": 0, "reactions_count": 0, "comments_count": 0, "position": 37}, {"read_count": 0, "image": {"large": {"url": "https://img9.doubanio.com/view/photo/l/public/p2677934990.webp", "width": 1280, "height": 540, "size": 0}, "raw": null, "small": {"url": "https://img9.doubanio.com/view/photo/s/public/p2677934990.webp", "width": 600, "height": 253, "size": 0}, "is_animated": false, "normal": {"url": "https://img9.doubanio.com/view/photo/m/public/p2677934990.webp", "width": 600, "height": 253, "size": 0}}, "create_time": "2021-08-23 14:22:34", "collections_count": 0, "reshares_count": 0, "id": "2677934990", "author": {"loc": {"id": "108296", "name": "\u4e0a\u6d77", "uid": "shanghai"}, "kind": "user", "name": "\u5343\u5bfb\u4ebf\u9009", "url": "https://www.douban.com/people/2574034/", "reg_time": "2008-06-09 11:08:57", "uri": "douban://douban.com/user/2574034", "avatar_side_icon_id": "65", "avatar": "https://img9.doubanio.com/icon/up2574034-9.jpg", "id": "2574034", "type": "user", "avatar_side_icon": "https://img9.doubanio.com/view/files/raw/file-1662088254.png", "uid": "2574034"}, "is_collected": false, "subtype": "photo", "type": "photo", "owner_uri": "douban://douban.com/movie/1301998", "status": null, "reaction_type": 0, "description": "", "sharing_url": "https://www.douban.com/doubanapp/dispatch?uri=/photo/2677934990/", "url": "https://movie.douban.com/photos/photo/2677934990/", "reply_limit": "A", "uri": "douban://douban.com/photo/2677934990", "likers_count": 0, "reactions_count": 0, "comments_count": 0, "position": 38}, {"read_count": 0, "image": {"large": {"url": "https://img9.doubanio.com/view/photo/l/public/p2677934989.webp", "width": 1280, "height": 540, "size": 0}, "raw": null, "small": {"url": "https://img9.doubanio.com/view/photo/s/public/p2677934989.webp", "width": 600, "height": 253, "size": 0}, "is_animated": false, "normal": {"url": "https://img9.doubanio.com/view/photo/m/public/p2677934989.webp", "width": 600, "height": 253, "size": 0}}, "create_time": "2021-08-23 14:22:34", "collections_count": 0, "reshares_count": 0, "id": "2677934989", "author": {"loc": {"id": "108296", "name": "\u4e0a\u6d77", "uid": "shanghai"}, "kind": "user", "name": "\u5343\u5bfb\u4ebf\u9009", "url": "https://www.douban.com/people/2574034/", "reg_time": "2008-06-09 11:08:57", "uri": "douban://douban.com/user/2574034", "avatar_side_icon_id": "65", "avatar": "https://img9.doubanio.com/icon/up2574034-9.jpg", "id": "2574034", "type": "user", "avatar_side_icon": "https://img9.doubanio.com/view/files/raw/file-1662088254.png", "uid": "2574034"}, "is_collected": false, "subtype": "photo", "type": "photo", "owner_uri": "douban://douban.com/movie/1301998", "status": null, "reaction_type": 0, "description": "", "sharing_url": "https://www.douban.com/doubanapp/dispatch?uri=/photo/2677934989/", "url": "https://movie.douban.com/photos/photo/2677934989/", "reply_limit": "A", "uri": "douban://douban.com/photo/2677934989", "likers_count": 0, "reactions_count": 0, "comments_count": 0, "position": 39}, {"read_count": 0, "image": {"large": {"url": "https://img9.doubanio.com/view/photo/l/public/p2677934988.webp", "width": 1280, "height": 540, "size": 0}, "raw": null, "small": {"url": "https://img9.doubanio.com/view/photo/s/public/p2677934988.webp", "width": 600, "height": 253, "size": 0}, "is_animated": false, "normal": {"url": "https://img9.doubanio.com/view/photo/m/public/p2677934988.webp", "width": 600, "height": 253, "size": 0}}, "create_time": "2021-08-23 14:22:33", "collections_count": 0, "reshares_count": 0, "id": "2677934988", "author": {"loc": {"id": "108296", "name": "\u4e0a\u6d77", "uid": "shanghai"}, "kind": "user", "name": "\u5343\u5bfb\u4ebf\u9009", "url": "https://www.douban.com/people/2574034/", "reg_time": "2008-06-09 11:08:57", "uri": "douban://douban.com/user/2574034", "avatar_side_icon_id": "65", "avatar": "https://img9.doubanio.com/icon/up2574034-9.jpg", "id": "2574034", "type": "user", "avatar_side_icon": "https://img9.doubanio.com/view/files/raw/file-1662088254.png", "uid": "2574034"}, "is_collected": false, "subtype": "photo", "type": "photo", "owner_uri": "douban://douban.com/movie/1301998", "status": null, "reaction_type": 0, "description": "", "sharing_url": "https://www.douban.com/doubanapp/dispatch?uri=/photo/2677934988/", "url": "https://movie.douban.com/photos/photo/2677934988/", "reply_limit": "A", "uri": "douban://douban.com/photo/2677934988", "likers_count": 0, "reactions_count": 0, "comments_count": 0, "position": 40}, {"read_count": 1, "image": {"large": {"url": "https://img9.doubanio.com/view/photo/l/public/p2677934987.webp", "width": 1280, "height": 540, "size": 0}, "raw": null, "small": {"url": "https://img9.doubanio.com/view/photo/s/public/p2677934987.webp", "width": 600, "height": 253, "size": 0}, "is_animated": false, "normal": {"url": "https://img9.doubanio.com/view/photo/m/public/p2677934987.webp", "width": 600, "height": 253, "size": 0}}, "create_time": "2021-08-23 14:22:32", "collections_count": 0, "reshares_count": 0, "id": "2677934987", "author": {"loc": {"id": "108296", "name": "\u4e0a\u6d77", "uid": "shanghai"}, "kind": "user", "name": "\u5343\u5bfb\u4ebf\u9009", "url": "https://www.douban.com/people/2574034/", "reg_time": "2008-06-09 11:08:57", "uri": "douban://douban.com/user/2574034", "avatar_side_icon_id": "65", "avatar": "https://img9.doubanio.com/icon/up2574034-9.jpg", "id": "2574034", "type": "user", "avatar_side_icon": "https://img9.doubanio.com/view/files/raw/file-1662088254.png", "uid": "2574034"}, "is_collected": false, "subtype": "photo", "type": "photo", "owner_uri": "douban://douban.com/movie/1301998", "status": null, "reaction_type": 0, "description": "", "sharing_url": "https://www.douban.com/doubanapp/dispatch?uri=/photo/2677934987/", "url": "https://movie.douban.com/photos/photo/2677934987/", "reply_limit": "A", "uri": "douban://douban.com/photo/2677934987", "likers_count": 0, "reactions_count": 0, "comments_count": 0, "position": 41}, {"read_count": 5, "image": {"large": {"url": "https://img9.doubanio.com/view/photo/l/public/p2579484538.webp", "width": 1280, "height": 720, "size": 0}, "raw": null, "small": {"url": "https://img9.doubanio.com/view/photo/s/public/p2579484538.webp", "width": 600, "height": 337, "size": 0}, "is_animated": false, "normal": {"url": "https://img9.doubanio.com/view/photo/m/public/p2579484538.webp", "width": 600, "height": 337, "size": 0}}, "create_time": "2020-01-03 03:17:11", "collections_count": 0, "reshares_count": 0, "id": "2579484538", "author": {"loc": {"id": "108288", "name": "\u5317\u4eac", "uid": "beijing"}, "kind": "user", "name": "\u5b64\u8eab\u6c89\u5bc2\u7684\u68a6\u91cc", "url": "https://www.douban.com/people/53180194/", "reg_time": "2011-07-19 18:39:53", "uri": "douban://douban.com/user/53180194", "avatar_side_icon_id": "", "avatar": "https://img9.doubanio.com/icon/up53180194-22.jpg", "id": "53180194", "type": "user", "avatar_side_icon": "", "uid": "haleyrink1897"}, "is_collected": false, "subtype": "photo", "type": "photo", "owner_uri": "douban://douban.com/movie/1301998", "status": null, "reaction_type": 0, "description": "\u5de6\u62e5\u53f3\u62b1\u4eba\u751f\u5dc5\u5cf0", "sharing_url": "https://www.douban.com/doubanapp/dispatch?uri=/photo/2579484538/", "url": "https://movie.douban.com/photos/photo/2579484538/", "reply_limit": "A", "uri": "douban://douban.com/photo/2579484538", "likers_count": 0, "reactions_count": 0, "comments_count": 0, "position": 42}, {"read_count": 6, "image": {"large": {"url": "https://img9.doubanio.com/view/photo/l/public/p2579484537.webp", "width": 1280, "height": 720, "size": 0}, "raw": null, "small": {"url": "https://img9.doubanio.com/view/photo/s/public/p2579484537.webp", "width": 600, "height": 337, "size": 0}, "is_animated": false, "normal": {"url": "https://img9.doubanio.com/view/photo/m/public/p2579484537.webp", "width": 600, "height": 337, "size": 0}}, "create_time": "2020-01-03 03:17:08", "collections_count": 1, "reshares_count": 0, "id": "2579484537", "author": {"loc": {"id": "108288", "name": "\u5317\u4eac", "uid": "beijing"}, "kind": "user", "name": "\u5b64\u8eab\u6c89\u5bc2\u7684\u68a6\u91cc", "url": "https://www.douban.com/people/53180194/", "reg_time": "2011-07-19 18:39:53", "uri": "douban://douban.com/user/53180194", "avatar_side_icon_id": "", "avatar": "https://img9.doubanio.com/icon/up53180194-22.jpg", "id": "53180194", "type": "user", "avatar_side_icon": "", "uid": "haleyrink1897"}, "is_collected": false, "subtype": "photo", "type": "photo", "owner_uri": "douban://douban.com/movie/1301998", "status": null, "reaction_type": 0, "description": "\u5de6\u62e5\u53f3\u62b1\u4eba\u751f\u5dc5\u5cf0", "sharing_url": "https://www.douban.com/doubanapp/dispatch?uri=/photo/2579484537/", "url": "https://movie.douban.com/photos/photo/2579484537/", "reply_limit": "A", "uri": "douban://douban.com/photo/2579484537", "likers_count": 0, "reactions_count": 0, "comments_count": 0, "position": 43}, {"read_count": 188, "image": {"large": {"url": "https://qnmob3.doubanio.com/view/photo/large/public/p1356833375.jpg?imageView2/2/q/80/w/600/h/3000/format/webp", "width": 600, "height": 255, "size": 0}, "raw": null, "small": {"url": "https://img9.doubanio.com/view/photo/s/public/p1356833375.webp", "width": 600, "height": 255, "size": 0}, "is_animated": false, "normal": {"url": "https://img9.doubanio.com/view/photo/m/public/p1356833375.webp", "width": 600, "height": 255, "size": 0}}, "create_time": "2011-12-28 16:26:14", "collections_count": 0, "reshares_count": 0, "id": "1356833375", "author": {"loc": {"id": "118174", "name": "\u6e29\u5dde", "uid": "wenzhou"}, "kind": "user", "name": "\u718a\u732b\u602a", "url": "https://www.douban.com/people/2635654/", "reg_time": "2008-06-25 12:19:10", "uri": "douban://douban.com/user/2635654", "avatar_side_icon_id": "", "avatar": "https://img9.doubanio.com/icon/up2635654-2.jpg", "id": "2635654", "type": "user", "avatar_side_icon": "", "uid": "panda874"}, "is_collected": false, "subtype": "photo", "type": "photo", "owner_uri": "douban://douban.com/movie/1301998", "status": null, "reaction_type": 0, "description": "\u914d\u4e50 Jerry Goldsmith", "sharing_url": "https://www.douban.com/doubanapp/dispatch?uri=/photo/1356833375/", "url": "https://movie.douban.com/photos/photo/1356833375/", "reply_limit": "A", "uri": "douban://douban.com/photo/1356833375", "likers_count": 0, "reactions_count": 0, "comments_count": 0, "position": 47}, {"read_count": 299, "image": {"large": {"url": "https://qnmob3.doubanio.com/view/photo/large/public/p895015346.jpg?imageView2/2/q/80/w/600/h/3000/format/webp", "width": 600, "height": 400, "size": 0}, "raw": null, "small": {"url": "https://img9.doubanio.com/view/photo/s/public/p895015346.webp", "width": 600, "height": 400, "size": 0}, "is_animated": false, "normal": {"url": "https://img9.doubanio.com/view/photo/m/public/p895015346.webp", "width": 600, "height": 400, "size": 0}}, "create_time": "2011-03-16 13:35:31", "collections_count": 0, "reshares_count": 0, "id": "895015346", "author": {"loc": {"id": "108296", "name": "\u4e0a\u6d77", "uid": "shanghai"}, "kind": "user", "name": "\u9c7c\u86cb", "url": "https://www.douban.com/people/2041761/", "reg_time": "2007-11-27 14:43:46", "uri": "douban://douban.com/user/2041761", "avatar_side_icon_id": "", "avatar": "https://img9.doubanio.com/icon/up2041761-11.jpg", "id": "2041761", "type": "user", "avatar_side_icon": "", "uid": "2041761"}, "is_collected": false, "subtype": "photo", "type": "photo", "owner_uri": "douban://douban.com/movie/1301998", "status": null, "reaction_type": 0, "description": "", "sharing_url": "https://www.douban.com/doubanapp/dispatch?uri=/photo/895015346/", "url": "https://movie.douban.com/photos/photo/895015346/", "reply_limit": "A", "uri": "douban://douban.com/photo/895015346", "likers_count": 0, "reactions_count": 0, "comments_count": 3, "position": 48}], "w": 0, "total": 50, "start": 0, "movie_info": {"id": "1301998", "title": "\u5929\u9b54\u7eed\u96c6", "original_title": "Omen II: Damien", "year": "1978", "is_tv": false, "rating": {"count": 745, "max": 10, "star_count": 3.0, "value": 6.4}, "poster": "https://img9.doubanio.com/view/photo/m_ratio_poster/public/p2427457638.webp"}}