{"count": 49, "c": 90, "f": 0, "o": 0, "n": 0, "photos": [{"read_count": 526, "image": {"large": {"url": "https://img9.doubanio.com/view/photo/l/public/p2208039061.webp", "width": 979, "height": 1089, "size": 0}, "raw": null, "small": {"url": "https://img9.doubanio.com/view/photo/s/public/p2208039061.webp", "width": 539, "height": 600, "size": 0}, "is_animated": false, "normal": {"url": "https://img9.doubanio.com/view/photo/m/public/p2208039061.webp", "width": 539, "height": 600, "size": 0}}, "create_time": "2014-10-27 22:41:45", "collections_count": 0, "reshares_count": 1, "id": "2208039061", "author": {"loc": {"id": "108296", "name": "\u4e0a\u6d77", "uid": "shanghai"}, "kind": "user", "name": "\u55b5\u5927", "url": "https://www.douban.com/people/51396220/", "reg_time": "2011-05-07 00:15:16", "uri": "douban://douban.com/user/51396220", "avatar_side_icon_id": "", "avatar": "https://img9.doubanio.com/icon/up51396220-2.jpg", "id": "51396220", "type": "user", "avatar_side_icon": "", "uid": "51396220"}, "is_collected": false, "subtype": "photo", "type": "photo", "owner_uri": "douban://douban.com/tv/25732562", "status": null, "reaction_type": 0, "description": "", "sharing_url": "https://www.douban.com/doubanapp/dispatch?uri=/photo/2208039061/", "url": "https://movie.douban.com/photos/photo/2208039061/", "reply_limit": "A", "uri": "douban://douban.com/photo/2208039061", "likers_count": 1, "reactions_count": 1, "comments_count": 2, "position": 0}, {"read_count": 114, "image": {"large": {"url": "https://img9.doubanio.com/view/photo/l/public/p2197233941.webp", "width": 720, "height": 400, "size": 0}, "raw": null, "small": {"url": "https://img9.doubanio.com/view/photo/s/public/p2197233941.webp", "width": 600, "height": 333, "size": 0}, "is_animated": false, "normal": {"url": "https://img9.doubanio.com/view/photo/m/public/p2197233941.webp", "width": 600, "height": 333, "size": 0}}, "create_time": "2014-08-25 11:39:26", "collections_count": 1, "reshares_count": 0, "id": "2197233941", "author": {"loc": {"id": "118096", "name": "\u6ca7\u5dde", "uid": "cangzhou"}, "kind": "user", "name": "\u8309\u8389\u9999\u7247", "url": "https://www.douban.com/people/75681431/", "reg_time": "2013-07-23 14:21:59", "uri": "douban://douban.com/user/75681431", "avatar_side_icon_id": "", "avatar": "https://img9.doubanio.com/icon/up75681431-2.jpg", "id": "75681431", "type": "user", "avatar_side_icon": "", "uid": "75681431"}, "is_collected": false, "subtype": "photo", "type": "photo", "owner_uri": "douban://douban.com/tv/25732562", "status": null, "reaction_type": 0, "description": "", "sharing_url": "https://www.douban.com/doubanapp/dispatch?uri=/photo/2197233941/", "url": "https://movie.douban.com/photos/photo/2197233941/", "reply_limit": "A", "uri": "douban://douban.com/photo/2197233941", "likers_count": 1, "reactions_count": 1, "comments_count": 0, "position": 26}, {"read_count": 27, "image": {"large": {"url": "https://img9.doubanio.com/view/photo/l/public/p2196474824.webp", "width": 720, "height": 400, "size": 0}, "raw": null, "small": {"url": "https://img9.doubanio.com/view/photo/s/public/p2196474824.webp", "width": 600, "height": 333, "size": 0}, "is_animated": false, "normal": {"url": "https://img9.doubanio.com/view/photo/m/public/p2196474824.webp", "width": 600, "height": 333, "size": 0}}, "create_time": "2014-08-20 13:27:19", "collections_count": 0, "reshares_count": 0, "id": "2196474824", "author": {"loc": {"id": "118096", "name": "\u6ca7\u5dde", "uid": "cangzhou"}, "kind": "user", "name": "\u8309\u8389\u9999\u7247", "url": "https://www.douban.com/people/75681431/", "reg_time": "2013-07-23 14:21:59", "uri": "douban://douban.com/user/75681431", "avatar_side_icon_id": "", "avatar": "https://img9.doubanio.com/icon/up75681431-2.jpg", "id": "75681431", "type": "user", "avatar_side_icon": "", "uid": "75681431"}, "is_collected": false, "subtype": "photo", "type": "photo", "owner_uri": "douban://douban.com/tv/25732562", "status": null, "reaction_type": 0, "description": "", "sharing_url": "https://www.douban.com/doubanapp/dispatch?uri=/photo/2196474824/", "url": "https://movie.douban.com/photos/photo/2196474824/", "reply_limit": "A", "uri": "douban://douban.com/photo/2196474824", "likers_count": 1, "reactions_count": 1, "comments_count": 0, "position": 41}, {"read_count": 20, "image": {"large": {"url": "https://img9.doubanio.com/view/photo/l/public/p2572201881.webp", "width": 1600, "height": 902, "size": 0}, "raw": null, "small": {"url": "https://img9.doubanio.com/view/photo/s/public/p2572201881.webp", "width": 600, "height": 338, "size": 0}, "is_animated": false, "normal": {"url": "https://img9.doubanio.com/view/photo/m/public/p2572201881.webp", "width": 600, "height": 338, "size": 0}}, "create_time": "2019-10-22 23:14:36", "collections_count": 0, "reshares_count": 0, "id": "2572201881", "author": {"loc": null, "kind": "user", "name": "\u6843\u6843", "url": "https://www.douban.com/people/205717906/", "reg_time": "2019-10-22 22:35:10", "uri": "douban://douban.com/user/205717906", "avatar_side_icon_id": "", "avatar": "https://img9.doubanio.com/icon/up205717906-8.jpg", "id": "205717906", "type": "user", "avatar_side_icon": "", "uid": "205717906"}, "is_collected": false, "subtype": "photo", "type": "photo", "owner_uri": "douban://douban.com/tv/25732562", "status": null, "reaction_type": 0, "description": "wes\uff01\uff01\uff01\uff01", "sharing_url": "https://www.douban.com/doubanapp/dispatch?uri=/photo/2572201881/", "url": "https://movie.douban.com/photos/photo/2572201881/", "reply_limit": "A", "uri": "douban://douban.com/photo/2572201881", "likers_count": 0, "reactions_count": 0, "comments_count": 1, "position": 1}, {"read_count": 10, "image": {"large": {"url": "https://img9.doubanio.com/view/photo/l/public/p2572201878.webp", "width": 1600, "height": 900, "size": 0}, "raw": null, "small": {"url": "https://img9.doubanio.com/view/photo/s/public/p2572201878.webp", "width": 600, "height": 337, "size": 0}, "is_animated": false, "normal": {"url": "https://img9.doubanio.com/view/photo/m/public/p2572201878.webp", "width": 600, "height": 337, "size": 0}}, "create_time": "2019-10-22 23:14:35", "collections_count": 0, "reshares_count": 0, "id": "2572201878", "author": {"loc": null, "kind": "user", "name": "\u6843\u6843", "url": "https://www.douban.com/people/205717906/", "reg_time": "2019-10-22 22:35:10", "uri": "douban://douban.com/user/205717906", "avatar_side_icon_id": "", "avatar": "https://img9.doubanio.com/icon/up205717906-8.jpg", "id": "205717906", "type": "user", "avatar_side_icon": "", "uid": "205717906"}, "is_collected": false, "subtype": "photo", "type": "photo", "owner_uri": "douban://douban.com/tv/25732562", "status": null, "reaction_type": 0, "description": "\u4e24\u4e2a\u4eba\u5728\u821e\u4f1a\u4e0a", "sharing_url": "https://www.douban.com/doubanapp/dispatch?uri=/photo/2572201878/", "url": "https://movie.douban.com/photos/photo/2572201878/", "reply_limit": "A", "uri": "douban://douban.com/photo/2572201878", "likers_count": 0, "reactions_count": 0, "comments_count": 0, "position": 2}, {"read_count": 8, "image": {"large": {"url": "https://img9.doubanio.com/view/photo/l/public/p2572201877.webp", "width": 1600, "height": 887, "size": 0}, "raw": null, "small": {"url": "https://img9.doubanio.com/view/photo/s/public/p2572201877.webp", "width": 600, "height": 332, "size": 0}, "is_animated": false, "normal": {"url": "https://img9.doubanio.com/view/photo/m/public/p2572201877.webp", "width": 600, "height": 332, "size": 0}}, "create_time": "2019-10-22 23:14:35", "collections_count": 0, "reshares_count": 0, "id": "2572201877", "author": {"loc": null, "kind": "user", "name": "\u6843\u6843", "url": "https://www.douban.com/people/205717906/", "reg_time": "2019-10-22 22:35:10", "uri": "douban://douban.com/user/205717906", "avatar_side_icon_id": "", "avatar": "https://img9.doubanio.com/icon/up205717906-8.jpg", "id": "205717906", "type": "user", "avatar_side_icon": "", "uid": "205717906"}, "is_collected": false, "subtype": "photo", "type": "photo", "owner_uri": "douban://douban.com/tv/25732562", "status": null, "reaction_type": 0, "description": "\u4e07\u5723\u8282\u6d3e\u5bf9\r\n", "sharing_url": "https://www.douban.com/doubanapp/dispatch?uri=/photo/2572201877/", "url": "https://movie.douban.com/photos/photo/2572201877/", "reply_limit": "A", "uri": "douban://douban.com/photo/2572201877", "likers_count": 0, "reactions_count": 0, "comments_count": 0, "position": 3}, {"read_count": 54, "image": {"large": {"url": "https://img9.doubanio.com/view/photo/l/public/p2313379790.webp", "width": 1024, "height": 576, "size": 0}, "raw": null, "small": {"url": "https://img9.doubanio.com/view/photo/s/public/p2313379790.webp", "width": 600, "height": 337, "size": 0}, "is_animated": false, "normal": {"url": "https://img9.doubanio.com/view/photo/m/public/p2313379790.webp", "width": 600, "height": 337, "size": 0}}, "create_time": "2016-01-24 22:57:48", "collections_count": 0, "reshares_count": 0, "id": "2313379790", "author": {"loc": {"id": "118096", "name": "\u6ca7\u5dde", "uid": "cangzhou"}, "kind": "user", "name": "\u8309\u8389\u9999\u7247", "url": "https://www.douban.com/people/75681431/", "reg_time": "2013-07-23 14:21:59", "uri": "douban://douban.com/user/75681431", "avatar_side_icon_id": "", "avatar": "https://img9.doubanio.com/icon/up75681431-2.jpg", "id": "75681431", "type": "user", "avatar_side_icon": "", "uid": "75681431"}, "is_collected": false, "subtype": "photo", "type": "photo", "owner_uri": "douban://douban.com/tv/25732562", "status": null, "reaction_type": 0, "description": "", "sharing_url": "https://www.douban.com/doubanapp/dispatch?uri=/photo/2313379790/", "url": "https://movie.douban.com/photos/photo/2313379790/", "reply_limit": "A", "uri": "douban://douban.com/photo/2313379790", "likers_count": 0, "reactions_count": 0, "comments_count": 0, "position": 4}, {"read_count": 45, "image": {"large": {"url": "https://img9.doubanio.com/view/photo/l/public/p2313327361.webp", "width": 1024, "height": 576, "size": 0}, "raw": null, "small": {"url": "https://img9.doubanio.com/view/photo/s/public/p2313327361.webp", "width": 600, "height": 337, "size": 0}, "is_animated": false, "normal": {"url": "https://img9.doubanio.com/view/photo/m/public/p2313327361.webp", "width": 600, "height": 337, "size": 0}}, "create_time": "2016-01-24 20:44:50", "collections_count": 0, "reshares_count": 0, "id": "2313327361", "author": {"loc": {"id": "118096", "name": "\u6ca7\u5dde", "uid": "cangzhou"}, "kind": "user", "name": "\u8309\u8389\u9999\u7247", "url": "https://www.douban.com/people/75681431/", "reg_time": "2013-07-23 14:21:59", "uri": "douban://douban.com/user/75681431", "avatar_side_icon_id": "", "avatar": "https://img9.doubanio.com/icon/up75681431-2.jpg", "id": "75681431", "type": "user", "avatar_side_icon": "", "uid": "75681431"}, "is_collected": false, "subtype": "photo", "type": "photo", "owner_uri": "douban://douban.com/tv/25732562", "status": null, "reaction_type": 0, "description": "", "sharing_url": "https://www.douban.com/doubanapp/dispatch?uri=/photo/2313327361/", "url": "https://movie.douban.com/photos/photo/2313327361/", "reply_limit": "A", "uri": "douban://douban.com/photo/2313327361", "likers_count": 0, "reactions_count": 0, "comments_count": 0, "position": 5}, {"read_count": 31, "image": {"large": {"url": "https://img9.doubanio.com/view/photo/l/public/p2312540645.webp", "width": 1024, "height": 576, "size": 0}, "raw": null, "small": {"url": "https://img9.doubanio.com/view/photo/s/public/p2312540645.webp", "width": 600, "height": 337, "size": 0}, "is_animated": false, "normal": {"url": "https://img9.doubanio.com/view/photo/m/public/p2312540645.webp", "width": 600, "height": 337, "size": 0}}, "create_time": "2016-01-22 20:36:10", "collections_count": 0, "reshares_count": 0, "id": "2312540645", "author": {"loc": {"id": "118096", "name": "\u6ca7\u5dde", "uid": "cangzhou"}, "kind": "user", "name": "\u8309\u8389\u9999\u7247", "url": "https://www.douban.com/people/75681431/", "reg_time": "2013-07-23 14:21:59", "uri": "douban://douban.com/user/75681431", "avatar_side_icon_id": "", "avatar": "https://img9.doubanio.com/icon/up75681431-2.jpg", "id": "75681431", "type": "user", "avatar_side_icon": "", "uid": "75681431"}, "is_collected": false, "subtype": "photo", "type": "photo", "owner_uri": "douban://douban.com/tv/25732562", "status": null, "reaction_type": 0, "description": "", "sharing_url": "https://www.douban.com/doubanapp/dispatch?uri=/photo/2312540645/", "url": "https://movie.douban.com/photos/photo/2312540645/", "reply_limit": "A", "uri": "douban://douban.com/photo/2312540645", "likers_count": 0, "reactions_count": 0, "comments_count": 0, "position": 6}, {"read_count": 31, "image": {"large": {"url": "https://img9.doubanio.com/view/photo/l/public/p2311394401.webp", "width": 1024, "height": 576, "size": 0}, "raw": null, "small": {"url": "https://img9.doubanio.com/view/photo/s/public/p2311394401.webp", "width": 600, "height": 337, "size": 0}, "is_animated": false, "normal": {"url": "https://img9.doubanio.com/view/photo/m/public/p2311394401.webp", "width": 600, "height": 337, "size": 0}}, "create_time": "2016-01-19 22:36:10", "collections_count": 0, "reshares_count": 0, "id": "2311394401", "author": {"loc": {"id": "118096", "name": "\u6ca7\u5dde", "uid": "cangzhou"}, "kind": "user", "name": "\u8309\u8389\u9999\u7247", "url": "https://www.douban.com/people/75681431/", "reg_time": "2013-07-23 14:21:59", "uri": "douban://douban.com/user/75681431", "avatar_side_icon_id": "", "avatar": "https://img9.doubanio.com/icon/up75681431-2.jpg", "id": "75681431", "type": "user", "avatar_side_icon": "", "uid": "75681431"}, "is_collected": false, "subtype": "photo", "type": "photo", "owner_uri": "douban://douban.com/tv/25732562", "status": null, "reaction_type": 0, "description": "", "sharing_url": "https://www.douban.com/doubanapp/dispatch?uri=/photo/2311394401/", "url": "https://movie.douban.com/photos/photo/2311394401/", "reply_limit": "A", "uri": "douban://douban.com/photo/2311394401", "likers_count": 0, "reactions_count": 0, "comments_count": 0, "position": 7}, {"read_count": 35, "image": {"large": {"url": "https://img9.doubanio.com/view/photo/l/public/p2311394356.webp", "width": 1024, "height": 576, "size": 0}, "raw": null, "small": {"url": "https://img9.doubanio.com/view/photo/s/public/p2311394356.webp", "width": 600, "height": 337, "size": 0}, "is_animated": false, "normal": {"url": "https://img9.doubanio.com/view/photo/m/public/p2311394356.webp", "width": 600, "height": 337, "size": 0}}, "create_time": "2016-01-19 22:35:54", "collections_count": 0, "reshares_count": 0, "id": "2311394356", "author": {"loc": {"id": "118096", "name": "\u6ca7\u5dde", "uid": "cangzhou"}, "kind": "user", "name": "\u8309\u8389\u9999\u7247", "url": "https://www.douban.com/people/75681431/", "reg_time": "2013-07-23 14:21:59", "uri": "douban://douban.com/user/75681431", "avatar_side_icon_id": "", "avatar": "https://img9.doubanio.com/icon/up75681431-2.jpg", "id": "75681431", "type": "user", "avatar_side_icon": "", "uid": "75681431"}, "is_collected": false, "subtype": "photo", "type": "photo", "owner_uri": "douban://douban.com/tv/25732562", "status": null, "reaction_type": 0, "description": "", "sharing_url": "https://www.douban.com/doubanapp/dispatch?uri=/photo/2311394356/", "url": "https://movie.douban.com/photos/photo/2311394356/", "reply_limit": "A", "uri": "douban://douban.com/photo/2311394356", "likers_count": 0, "reactions_count": 0, "comments_count": 0, "position": 8}, {"read_count": 19, "image": {"large": {"url": "https://img9.doubanio.com/view/photo/l/public/p2311355892.webp", "width": 1024, "height": 576, "size": 0}, "raw": null, "small": {"url": "https://img9.doubanio.com/view/photo/s/public/p2311355892.webp", "width": 600, "height": 337, "size": 0}, "is_animated": false, "normal": {"url": "https://img9.doubanio.com/view/photo/m/public/p2311355892.webp", "width": 600, "height": 337, "size": 0}}, "create_time": "2016-01-19 21:10:56", "collections_count": 0, "reshares_count": 0, "id": "2311355892", "author": {"loc": {"id": "118096", "name": "\u6ca7\u5dde", "uid": "cangzhou"}, "kind": "user", "name": "\u8309\u8389\u9999\u7247", "url": "https://www.douban.com/people/75681431/", "reg_time": "2013-07-23 14:21:59", "uri": "douban://douban.com/user/75681431", "avatar_side_icon_id": "", "avatar": "https://img9.doubanio.com/icon/up75681431-2.jpg", "id": "75681431", "type": "user", "avatar_side_icon": "", "uid": "75681431"}, "is_collected": false, "subtype": "photo", "type": "photo", "owner_uri": "douban://douban.com/tv/25732562", "status": null, "reaction_type": 0, "description": "", "sharing_url": "https://www.douban.com/doubanapp/dispatch?uri=/photo/2311355892/", "url": "https://movie.douban.com/photos/photo/2311355892/", "reply_limit": "A", "uri": "douban://douban.com/photo/2311355892", "likers_count": 0, "reactions_count": 0, "comments_count": 0, "position": 9}, {"read_count": 20, "image": {"large": {"url": "https://img9.doubanio.com/view/photo/l/public/p2311355765.webp", "width": 1024, "height": 576, "size": 0}, "raw": null, "small": {"url": "https://img9.doubanio.com/view/photo/s/public/p2311355765.webp", "width": 600, "height": 337, "size": 0}, "is_animated": false, "normal": {"url": "https://img9.doubanio.com/view/photo/m/public/p2311355765.webp", "width": 600, "height": 337, "size": 0}}, "create_time": "2016-01-19 21:10:42", "collections_count": 0, "reshares_count": 0, "id": "2311355765", "author": {"loc": {"id": "118096", "name": "\u6ca7\u5dde", "uid": "cangzhou"}, "kind": "user", "name": "\u8309\u8389\u9999\u7247", "url": "https://www.douban.com/people/75681431/", "reg_time": "2013-07-23 14:21:59", "uri": "douban://douban.com/user/75681431", "avatar_side_icon_id": "", "avatar": "https://img9.doubanio.com/icon/up75681431-2.jpg", "id": "75681431", "type": "user", "avatar_side_icon": "", "uid": "75681431"}, "is_collected": false, "subtype": "photo", "type": "photo", "owner_uri": "douban://douban.com/tv/25732562", "status": null, "reaction_type": 0, "description": "", "sharing_url": "https://www.douban.com/doubanapp/dispatch?uri=/photo/2311355765/", "url": "https://movie.douban.com/photos/photo/2311355765/", "reply_limit": "A", "uri": "douban://douban.com/photo/2311355765", "likers_count": 0, "reactions_count": 0, "comments_count": 0, "position": 10}, {"read_count": 17, "image": {"large": {"url": "https://img9.doubanio.com/view/photo/l/public/p2311355625.webp", "width": 1024, "height": 576, "size": 0}, "raw": null, "small": {"url": "https://img9.doubanio.com/view/photo/s/public/p2311355625.webp", "width": 600, "height": 337, "size": 0}, "is_animated": false, "normal": {"url": "https://img9.doubanio.com/view/photo/m/public/p2311355625.webp", "width": 600, "height": 337, "size": 0}}, "create_time": "2016-01-19 21:10:27", "collections_count": 0, "reshares_count": 0, "id": "2311355625", "author": {"loc": {"id": "118096", "name": "\u6ca7\u5dde", "uid": "cangzhou"}, "kind": "user", "name": "\u8309\u8389\u9999\u7247", "url": "https://www.douban.com/people/75681431/", "reg_time": "2013-07-23 14:21:59", "uri": "douban://douban.com/user/75681431", "avatar_side_icon_id": "", "avatar": "https://img9.doubanio.com/icon/up75681431-2.jpg", "id": "75681431", "type": "user", "avatar_side_icon": "", "uid": "75681431"}, "is_collected": false, "subtype": "photo", "type": "photo", "owner_uri": "douban://douban.com/tv/25732562", "status": null, "reaction_type": 0, "description": "", "sharing_url": "https://www.douban.com/doubanapp/dispatch?uri=/photo/2311355625/", "url": "https://movie.douban.com/photos/photo/2311355625/", "reply_limit": "A", "uri": "douban://douban.com/photo/2311355625", "likers_count": 0, "reactions_count": 0, "comments_count": 0, "position": 11}, {"read_count": 11, "image": {"large": {"url": "https://img9.doubanio.com/view/photo/l/public/p2311355499.webp", "width": 1024, "height": 576, "size": 0}, "raw": null, "small": {"url": "https://img9.doubanio.com/view/photo/s/public/p2311355499.webp", "width": 600, "height": 337, "size": 0}, "is_animated": false, "normal": {"url": "https://img9.doubanio.com/view/photo/m/public/p2311355499.webp", "width": 600, "height": 337, "size": 0}}, "create_time": "2016-01-19 21:10:10", "collections_count": 0, "reshares_count": 0, "id": "2311355499", "author": {"loc": {"id": "118096", "name": "\u6ca7\u5dde", "uid": "cangzhou"}, "kind": "user", "name": "\u8309\u8389\u9999\u7247", "url": "https://www.douban.com/people/75681431/", "reg_time": "2013-07-23 14:21:59", "uri": "douban://douban.com/user/75681431", "avatar_side_icon_id": "", "avatar": "https://img9.doubanio.com/icon/up75681431-2.jpg", "id": "75681431", "type": "user", "avatar_side_icon": "", "uid": "75681431"}, "is_collected": false, "subtype": "photo", "type": "photo", "owner_uri": "douban://douban.com/tv/25732562", "status": null, "reaction_type": 0, "description": "", "sharing_url": "https://www.douban.com/doubanapp/dispatch?uri=/photo/2311355499/", "url": "https://movie.douban.com/photos/photo/2311355499/", "reply_limit": "A", "uri": "douban://douban.com/photo/2311355499", "likers_count": 0, "reactions_count": 0, "comments_count": 0, "position": 12}, {"read_count": 15, "image": {"large": {"url": "https://img9.doubanio.com/view/photo/l/public/p2311355376.webp", "width": 1024, "height": 576, "size": 0}, "raw": null, "small": {"url": "https://img9.doubanio.com/view/photo/s/public/p2311355376.webp", "width": 600, "height": 337, "size": 0}, "is_animated": false, "normal": {"url": "https://img9.doubanio.com/view/photo/m/public/p2311355376.webp", "width": 600, "height": 337, "size": 0}}, "create_time": "2016-01-19 21:09:55", "collections_count": 0, "reshares_count": 0, "id": "2311355376", "author": {"loc": {"id": "118096", "name": "\u6ca7\u5dde", "uid": "cangzhou"}, "kind": "user", "name": "\u8309\u8389\u9999\u7247", "url": "https://www.douban.com/people/75681431/", "reg_time": "2013-07-23 14:21:59", "uri": "douban://douban.com/user/75681431", "avatar_side_icon_id": "", "avatar": "https://img9.doubanio.com/icon/up75681431-2.jpg", "id": "75681431", "type": "user", "avatar_side_icon": "", "uid": "75681431"}, "is_collected": false, "subtype": "photo", "type": "photo", "owner_uri": "douban://douban.com/tv/25732562", "status": null, "reaction_type": 0, "description": "", "sharing_url": "https://www.douban.com/doubanapp/dispatch?uri=/photo/2311355376/", "url": "https://movie.douban.com/photos/photo/2311355376/", "reply_limit": "A", "uri": "douban://douban.com/photo/2311355376", "likers_count": 0, "reactions_count": 0, "comments_count": 0, "position": 13}, {"read_count": 16, "image": {"large": {"url": "https://img9.doubanio.com/view/photo/l/public/p2311338121.webp", "width": 1024, "height": 576, "size": 0}, "raw": null, "small": {"url": "https://img9.doubanio.com/view/photo/s/public/p2311338121.webp", "width": 600, "height": 337, "size": 0}, "is_animated": false, "normal": {"url": "https://img9.doubanio.com/view/photo/m/public/p2311338121.webp", "width": 600, "height": 337, "size": 0}}, "create_time": "2016-01-19 20:36:49", "collections_count": 0, "reshares_count": 0, "id": "2311338121", "author": {"loc": {"id": "118096", "name": "\u6ca7\u5dde", "uid": "cangzhou"}, "kind": "user", "name": "\u8309\u8389\u9999\u7247", "url": "https://www.douban.com/people/75681431/", "reg_time": "2013-07-23 14:21:59", "uri": "douban://douban.com/user/75681431", "avatar_side_icon_id": "", "avatar": "https://img9.doubanio.com/icon/up75681431-2.jpg", "id": "75681431", "type": "user", "avatar_side_icon": "", "uid": "75681431"}, "is_collected": false, "subtype": "photo", "type": "photo", "owner_uri": "douban://douban.com/tv/25732562", "status": null, "reaction_type": 0, "description": "", "sharing_url": "https://www.douban.com/doubanapp/dispatch?uri=/photo/2311338121/", "url": "https://movie.douban.com/photos/photo/2311338121/", "reply_limit": "A", "uri": "douban://douban.com/photo/2311338121", "likers_count": 0, "reactions_count": 0, "comments_count": 0, "position": 14}, {"read_count": 16, "image": {"large": {"url": "https://img9.doubanio.com/view/photo/l/public/p2310645051.webp", "width": 1024, "height": 576, "size": 0}, "raw": null, "small": {"url": "https://img9.doubanio.com/view/photo/s/public/p2310645051.webp", "width": 600, "height": 337, "size": 0}, "is_animated": false, "normal": {"url": "https://img9.doubanio.com/view/photo/m/public/p2310645051.webp", "width": 600, "height": 337, "size": 0}}, "create_time": "2016-01-17 22:57:42", "collections_count": 0, "reshares_count": 0, "id": "2310645051", "author": {"loc": {"id": "118096", "name": "\u6ca7\u5dde", "uid": "cangzhou"}, "kind": "user", "name": "\u8309\u8389\u9999\u7247", "url": "https://www.douban.com/people/75681431/", "reg_time": "2013-07-23 14:21:59", "uri": "douban://douban.com/user/75681431", "avatar_side_icon_id": "", "avatar": "https://img9.doubanio.com/icon/up75681431-2.jpg", "id": "75681431", "type": "user", "avatar_side_icon": "", "uid": "75681431"}, "is_collected": false, "subtype": "photo", "type": "photo", "owner_uri": "douban://douban.com/tv/25732562", "status": null, "reaction_type": 0, "description": "", "sharing_url": "https://www.douban.com/doubanapp/dispatch?uri=/photo/2310645051/", "url": "https://movie.douban.com/photos/photo/2310645051/", "reply_limit": "A", "uri": "douban://douban.com/photo/2310645051", "likers_count": 0, "reactions_count": 0, "comments_count": 0, "position": 15}, {"read_count": 21, "image": {"large": {"url": "https://img9.doubanio.com/view/photo/l/public/p2310616810.webp", "width": 1024, "height": 576, "size": 0}, "raw": null, "small": {"url": "https://img9.doubanio.com/view/photo/s/public/p2310616810.webp", "width": 600, "height": 337, "size": 0}, "is_animated": false, "normal": {"url": "https://img9.doubanio.com/view/photo/m/public/p2310616810.webp", "width": 600, "height": 337, "size": 0}}, "create_time": "2016-01-17 21:41:54", "collections_count": 0, "reshares_count": 0, "id": "2310616810", "author": {"loc": {"id": "118096", "name": "\u6ca7\u5dde", "uid": "cangzhou"}, "kind": "user", "name": "\u8309\u8389\u9999\u7247", "url": "https://www.douban.com/people/75681431/", "reg_time": "2013-07-23 14:21:59", "uri": "douban://douban.com/user/75681431", "avatar_side_icon_id": "", "avatar": "https://img9.doubanio.com/icon/up75681431-2.jpg", "id": "75681431", "type": "user", "avatar_side_icon": "", "uid": "75681431"}, "is_collected": false, "subtype": "photo", "type": "photo", "owner_uri": "douban://douban.com/tv/25732562", "status": null, "reaction_type": 0, "description": "", "sharing_url": "https://www.douban.com/doubanapp/dispatch?uri=/photo/2310616810/", "url": "https://movie.douban.com/photos/photo/2310616810/", "reply_limit": "A", "uri": "douban://douban.com/photo/2310616810", "likers_count": 0, "reactions_count": 0, "comments_count": 0, "position": 16}, {"read_count": 5, "image": {"large": {"url": "https://img9.doubanio.com/view/photo/l/public/p2310285493.webp", "width": 1024, "height": 576, "size": 0}, "raw": null, "small": {"url": "https://img9.doubanio.com/view/photo/s/public/p2310285493.webp", "width": 600, "height": 337, "size": 0}, "is_animated": false, "normal": {"url": "https://img9.doubanio.com/view/photo/m/public/p2310285493.webp", "width": 600, "height": 337, "size": 0}}, "create_time": "2016-01-16 22:49:01", "collections_count": 0, "reshares_count": 0, "id": "2310285493", "author": {"loc": {"id": "118096", "name": "\u6ca7\u5dde", "uid": "cangzhou"}, "kind": "user", "name": "\u8309\u8389\u9999\u7247", "url": "https://www.douban.com/people/75681431/", "reg_time": "2013-07-23 14:21:59", "uri": "douban://douban.com/user/75681431", "avatar_side_icon_id": "", "avatar": "https://img9.doubanio.com/icon/up75681431-2.jpg", "id": "75681431", "type": "user", "avatar_side_icon": "", "uid": "75681431"}, "is_collected": false, "subtype": "photo", "type": "photo", "owner_uri": "douban://douban.com/tv/25732562", "status": null, "reaction_type": 0, "description": "", "sharing_url": "https://www.douban.com/doubanapp/dispatch?uri=/photo/2310285493/", "url": "https://movie.douban.com/photos/photo/2310285493/", "reply_limit": "A", "uri": "douban://douban.com/photo/2310285493", "likers_count": 0, "reactions_count": 0, "comments_count": 0, "position": 17}, {"read_count": 19, "image": {"large": {"url": "https://img9.doubanio.com/view/photo/l/public/p2310285019.webp", "width": 1024, "height": 576, "size": 0}, "raw": null, "small": {"url": "https://img9.doubanio.com/view/photo/s/public/p2310285019.webp", "width": 600, "height": 337, "size": 0}, "is_animated": false, "normal": {"url": "https://img9.doubanio.com/view/photo/m/public/p2310285019.webp", "width": 600, "height": 337, "size": 0}}, "create_time": "2016-01-16 22:47:56", "collections_count": 0, "reshares_count": 0, "id": "2310285019", "author": {"loc": {"id": "118096", "name": "\u6ca7\u5dde", "uid": "cangzhou"}, "kind": "user", "name": "\u8309\u8389\u9999\u7247", "url": "https://www.douban.com/people/75681431/", "reg_time": "2013-07-23 14:21:59", "uri": "douban://douban.com/user/75681431", "avatar_side_icon_id": "", "avatar": "https://img9.doubanio.com/icon/up75681431-2.jpg", "id": "75681431", "type": "user", "avatar_side_icon": "", "uid": "75681431"}, "is_collected": false, "subtype": "photo", "type": "photo", "owner_uri": "douban://douban.com/tv/25732562", "status": null, "reaction_type": 0, "description": "", "sharing_url": "https://www.douban.com/doubanapp/dispatch?uri=/photo/2310285019/", "url": "https://movie.douban.com/photos/photo/2310285019/", "reply_limit": "A", "uri": "douban://douban.com/photo/2310285019", "likers_count": 0, "reactions_count": 0, "comments_count": 0, "position": 18}, {"read_count": 12, "image": {"large": {"url": "https://img9.doubanio.com/view/photo/l/public/p2310284898.webp", "width": 1024, "height": 576, "size": 0}, "raw": null, "small": {"url": "https://img9.doubanio.com/view/photo/s/public/p2310284898.webp", "width": 600, "height": 337, "size": 0}, "is_animated": false, "normal": {"url": "https://img9.doubanio.com/view/photo/m/public/p2310284898.webp", "width": 600, "height": 337, "size": 0}}, "create_time": "2016-01-16 22:47:41", "collections_count": 0, "reshares_count": 0, "id": "2310284898", "author": {"loc": {"id": "118096", "name": "\u6ca7\u5dde", "uid": "cangzhou"}, "kind": "user", "name": "\u8309\u8389\u9999\u7247", "url": "https://www.douban.com/people/75681431/", "reg_time": "2013-07-23 14:21:59", "uri": "douban://douban.com/user/75681431", "avatar_side_icon_id": "", "avatar": "https://img9.doubanio.com/icon/up75681431-2.jpg", "id": "75681431", "type": "user", "avatar_side_icon": "", "uid": "75681431"}, "is_collected": false, "subtype": "photo", "type": "photo", "owner_uri": "douban://douban.com/tv/25732562", "status": null, "reaction_type": 0, "description": "", "sharing_url": "https://www.douban.com/doubanapp/dispatch?uri=/photo/2310284898/", "url": "https://movie.douban.com/photos/photo/2310284898/", "reply_limit": "A", "uri": "douban://douban.com/photo/2310284898", "likers_count": 0, "reactions_count": 0, "comments_count": 0, "position": 19}, {"read_count": 58, "image": {"large": {"url": "https://img9.doubanio.com/view/photo/l/public/p2197287544.webp", "width": 720, "height": 400, "size": 0}, "raw": null, "small": {"url": "https://img9.doubanio.com/view/photo/s/public/p2197287544.webp", "width": 600, "height": 333, "size": 0}, "is_animated": false, "normal": {"url": "https://img9.doubanio.com/view/photo/m/public/p2197287544.webp", "width": 600, "height": 333, "size": 0}}, "create_time": "2014-08-25 17:50:39", "collections_count": 0, "reshares_count": 0, "id": "2197287544", "author": {"loc": {"id": "118096", "name": "\u6ca7\u5dde", "uid": "cangzhou"}, "kind": "user", "name": "\u8309\u8389\u9999\u7247", "url": "https://www.douban.com/people/75681431/", "reg_time": "2013-07-23 14:21:59", "uri": "douban://douban.com/user/75681431", "avatar_side_icon_id": "", "avatar": "https://img9.doubanio.com/icon/up75681431-2.jpg", "id": "75681431", "type": "user", "avatar_side_icon": "", "uid": "75681431"}, "is_collected": false, "subtype": "photo", "type": "photo", "owner_uri": "douban://douban.com/tv/25732562", "status": null, "reaction_type": 0, "description": "", "sharing_url": "https://www.douban.com/doubanapp/dispatch?uri=/photo/2197287544/", "url": "https://movie.douban.com/photos/photo/2197287544/", "reply_limit": "A", "uri": "douban://douban.com/photo/2197287544", "likers_count": 0, "reactions_count": 0, "comments_count": 0, "position": 20}, {"read_count": 60, "image": {"large": {"url": "https://img9.doubanio.com/view/photo/l/public/p2197287382.webp", "width": 720, "height": 400, "size": 0}, "raw": null, "small": {"url": "https://img9.doubanio.com/view/photo/s/public/p2197287382.webp", "width": 600, "height": 333, "size": 0}, "is_animated": false, "normal": {"url": "https://img9.doubanio.com/view/photo/m/public/p2197287382.webp", "width": 600, "height": 333, "size": 0}}, "create_time": "2014-08-25 17:49:32", "collections_count": 0, "reshares_count": 0, "id": "2197287382", "author": {"loc": {"id": "118096", "name": "\u6ca7\u5dde", "uid": "cangzhou"}, "kind": "user", "name": "\u8309\u8389\u9999\u7247", "url": "https://www.douban.com/people/75681431/", "reg_time": "2013-07-23 14:21:59", "uri": "douban://douban.com/user/75681431", "avatar_side_icon_id": "", "avatar": "https://img9.doubanio.com/icon/up75681431-2.jpg", "id": "75681431", "type": "user", "avatar_side_icon": "", "uid": "75681431"}, "is_collected": false, "subtype": "photo", "type": "photo", "owner_uri": "douban://douban.com/tv/25732562", "status": null, "reaction_type": 0, "description": "", "sharing_url": "https://www.douban.com/doubanapp/dispatch?uri=/photo/2197287382/", "url": "https://movie.douban.com/photos/photo/2197287382/", "reply_limit": "A", "uri": "douban://douban.com/photo/2197287382", "likers_count": 0, "reactions_count": 0, "comments_count": 0, "position": 21}, {"read_count": 64, "image": {"large": {"url": "https://img9.doubanio.com/view/photo/l/public/p2197238787.webp", "width": 720, "height": 400, "size": 0}, "raw": null, "small": {"url": "https://img9.doubanio.com/view/photo/s/public/p2197238787.webp", "width": 600, "height": 333, "size": 0}, "is_animated": false, "normal": {"url": "https://img9.doubanio.com/view/photo/m/public/p2197238787.webp", "width": 600, "height": 333, "size": 0}}, "create_time": "2014-08-25 12:12:56", "collections_count": 0, "reshares_count": 0, "id": "2197238787", "author": {"loc": {"id": "118096", "name": "\u6ca7\u5dde", "uid": "cangzhou"}, "kind": "user", "name": "\u8309\u8389\u9999\u7247", "url": "https://www.douban.com/people/75681431/", "reg_time": "2013-07-23 14:21:59", "uri": "douban://douban.com/user/75681431", "avatar_side_icon_id": "", "avatar": "https://img9.doubanio.com/icon/up75681431-2.jpg", "id": "75681431", "type": "user", "avatar_side_icon": "", "uid": "75681431"}, "is_collected": false, "subtype": "photo", "type": "photo", "owner_uri": "douban://douban.com/tv/25732562", "status": null, "reaction_type": 0, "description": "", "sharing_url": "https://www.douban.com/doubanapp/dispatch?uri=/photo/2197238787/", "url": "https://movie.douban.com/photos/photo/2197238787/", "reply_limit": "A", "uri": "douban://douban.com/photo/2197238787", "likers_count": 0, "reactions_count": 0, "comments_count": 0, "position": 22}, {"read_count": 46, "image": {"large": {"url": "https://img9.doubanio.com/view/photo/l/public/p2197238630.webp", "width": 720, "height": 400, "size": 0}, "raw": null, "small": {"url": "https://img9.doubanio.com/view/photo/s/public/p2197238630.webp", "width": 600, "height": 333, "size": 0}, "is_animated": false, "normal": {"url": "https://img9.doubanio.com/view/photo/m/public/p2197238630.webp", "width": 600, "height": 333, "size": 0}}, "create_time": "2014-08-25 12:12:19", "collections_count": 0, "reshares_count": 0, "id": "2197238630", "author": {"loc": {"id": "118096", "name": "\u6ca7\u5dde", "uid": "cangzhou"}, "kind": "user", "name": "\u8309\u8389\u9999\u7247", "url": "https://www.douban.com/people/75681431/", "reg_time": "2013-07-23 14:21:59", "uri": "douban://douban.com/user/75681431", "avatar_side_icon_id": "", "avatar": "https://img9.doubanio.com/icon/up75681431-2.jpg", "id": "75681431", "type": "user", "avatar_side_icon": "", "uid": "75681431"}, "is_collected": false, "subtype": "photo", "type": "photo", "owner_uri": "douban://douban.com/tv/25732562", "status": null, "reaction_type": 0, "description": "", "sharing_url": "https://www.douban.com/doubanapp/dispatch?uri=/photo/2197238630/", "url": "https://movie.douban.com/photos/photo/2197238630/", "reply_limit": "A", "uri": "douban://douban.com/photo/2197238630", "likers_count": 0, "reactions_count": 0, "comments_count": 0, "position": 23}, {"read_count": 43, "image": {"large": {"url": "https://img9.doubanio.com/view/photo/l/public/p2197238604.webp", "width": 720, "height": 400, "size": 0}, "raw": null, "small": {"url": "https://img9.doubanio.com/view/photo/s/public/p2197238604.webp", "width": 600, "height": 333, "size": 0}, "is_animated": false, "normal": {"url": "https://img9.doubanio.com/view/photo/m/public/p2197238604.webp", "width": 600, "height": 333, "size": 0}}, "create_time": "2014-08-25 12:12:03", "collections_count": 0, "reshares_count": 0, "id": "2197238604", "author": {"loc": {"id": "118096", "name": "\u6ca7\u5dde", "uid": "cangzhou"}, "kind": "user", "name": "\u8309\u8389\u9999\u7247", "url": "https://www.douban.com/people/75681431/", "reg_time": "2013-07-23 14:21:59", "uri": "douban://douban.com/user/75681431", "avatar_side_icon_id": "", "avatar": "https://img9.doubanio.com/icon/up75681431-2.jpg", "id": "75681431", "type": "user", "avatar_side_icon": "", "uid": "75681431"}, "is_collected": false, "subtype": "photo", "type": "photo", "owner_uri": "douban://douban.com/tv/25732562", "status": null, "reaction_type": 0, "description": "", "sharing_url": "https://www.douban.com/doubanapp/dispatch?uri=/photo/2197238604/", "url": "https://movie.douban.com/photos/photo/2197238604/", "reply_limit": "A", "uri": "douban://douban.com/photo/2197238604", "likers_count": 0, "reactions_count": 0, "comments_count": 0, "position": 24}, {"read_count": 42, "image": {"large": {"url": "https://img9.doubanio.com/view/photo/l/public/p2197233976.webp", "width": 720, "height": 400, "size": 0}, "raw": null, "small": {"url": "https://img9.doubanio.com/view/photo/s/public/p2197233976.webp", "width": 600, "height": 333, "size": 0}, "is_animated": false, "normal": {"url": "https://img9.doubanio.com/view/photo/m/public/p2197233976.webp", "width": 600, "height": 333, "size": 0}}, "create_time": "2014-08-25 11:39:47", "collections_count": 0, "reshares_count": 0, "id": "2197233976", "author": {"loc": {"id": "118096", "name": "\u6ca7\u5dde", "uid": "cangzhou"}, "kind": "user", "name": "\u8309\u8389\u9999\u7247", "url": "https://www.douban.com/people/75681431/", "reg_time": "2013-07-23 14:21:59", "uri": "douban://douban.com/user/75681431", "avatar_side_icon_id": "", "avatar": "https://img9.doubanio.com/icon/up75681431-2.jpg", "id": "75681431", "type": "user", "avatar_side_icon": "", "uid": "75681431"}, "is_collected": false, "subtype": "photo", "type": "photo", "owner_uri": "douban://douban.com/tv/25732562", "status": null, "reaction_type": 0, "description": "", "sharing_url": "https://www.douban.com/doubanapp/dispatch?uri=/photo/2197233976/", "url": "https://movie.douban.com/photos/photo/2197233976/", "reply_limit": "A", "uri": "douban://douban.com/photo/2197233976", "likers_count": 0, "reactions_count": 0, "comments_count": 0, "position": 25}, {"read_count": 41, "image": {"large": {"url": "https://img9.doubanio.com/view/photo/l/public/p2197233827.webp", "width": 720, "height": 400, "size": 0}, "raw": null, "small": {"url": "https://img9.doubanio.com/view/photo/s/public/p2197233827.webp", "width": 600, "height": 333, "size": 0}, "is_animated": false, "normal": {"url": "https://img9.doubanio.com/view/photo/m/public/p2197233827.webp", "width": 600, "height": 333, "size": 0}}, "create_time": "2014-08-25 11:39:06", "collections_count": 0, "reshares_count": 0, "id": "2197233827", "author": {"loc": {"id": "118096", "name": "\u6ca7\u5dde", "uid": "cangzhou"}, "kind": "user", "name": "\u8309\u8389\u9999\u7247", "url": "https://www.douban.com/people/75681431/", "reg_time": "2013-07-23 14:21:59", "uri": "douban://douban.com/user/75681431", "avatar_side_icon_id": "", "avatar": "https://img9.doubanio.com/icon/up75681431-2.jpg", "id": "75681431", "type": "user", "avatar_side_icon": "", "uid": "75681431"}, "is_collected": false, "subtype": "photo", "type": "photo", "owner_uri": "douban://douban.com/tv/25732562", "status": null, "reaction_type": 0, "description": "", "sharing_url": "https://www.douban.com/doubanapp/dispatch?uri=/photo/2197233827/", "url": "https://movie.douban.com/photos/photo/2197233827/", "reply_limit": "A", "uri": "douban://douban.com/photo/2197233827", "likers_count": 0, "reactions_count": 0, "comments_count": 0, "position": 27}, {"read_count": 39, "image": {"large": {"url": "https://img9.doubanio.com/view/photo/l/public/p2197233780.webp", "width": 720, "height": 400, "size": 0}, "raw": null, "small": {"url": "https://img9.doubanio.com/view/photo/s/public/p2197233780.webp", "width": 600, "height": 333, "size": 0}, "is_animated": false, "normal": {"url": "https://img9.doubanio.com/view/photo/m/public/p2197233780.webp", "width": 600, "height": 333, "size": 0}}, "create_time": "2014-08-25 11:38:43", "collections_count": 0, "reshares_count": 0, "id": "2197233780", "author": {"loc": {"id": "118096", "name": "\u6ca7\u5dde", "uid": "cangzhou"}, "kind": "user", "name": "\u8309\u8389\u9999\u7247", "url": "https://www.douban.com/people/75681431/", "reg_time": "2013-07-23 14:21:59", "uri": "douban://douban.com/user/75681431", "avatar_side_icon_id": "", "avatar": "https://img9.doubanio.com/icon/up75681431-2.jpg", "id": "75681431", "type": "user", "avatar_side_icon": "", "uid": "75681431"}, "is_collected": false, "subtype": "photo", "type": "photo", "owner_uri": "douban://douban.com/tv/25732562", "status": null, "reaction_type": 0, "description": "", "sharing_url": "https://www.douban.com/doubanapp/dispatch?uri=/photo/2197233780/", "url": "https://movie.douban.com/photos/photo/2197233780/", "reply_limit": "A", "uri": "douban://douban.com/photo/2197233780", "likers_count": 0, "reactions_count": 0, "comments_count": 0, "position": 28}, {"read_count": 29, "image": {"large": {"url": "https://img9.doubanio.com/view/photo/l/public/p2197233744.webp", "width": 720, "height": 400, "size": 0}, "raw": null, "small": {"url": "https://img9.doubanio.com/view/photo/s/public/p2197233744.webp", "width": 600, "height": 333, "size": 0}, "is_animated": false, "normal": {"url": "https://img9.doubanio.com/view/photo/m/public/p2197233744.webp", "width": 600, "height": 333, "size": 0}}, "create_time": "2014-08-25 11:38:22", "collections_count": 0, "reshares_count": 0, "id": "2197233744", "author": {"loc": {"id": "118096", "name": "\u6ca7\u5dde", "uid": "cangzhou"}, "kind": "user", "name": "\u8309\u8389\u9999\u7247", "url": "https://www.douban.com/people/75681431/", "reg_time": "2013-07-23 14:21:59", "uri": "douban://douban.com/user/75681431", "avatar_side_icon_id": "", "avatar": "https://img9.doubanio.com/icon/up75681431-2.jpg", "id": "75681431", "type": "user", "avatar_side_icon": "", "uid": "75681431"}, "is_collected": false, "subtype": "photo", "type": "photo", "owner_uri": "douban://douban.com/tv/25732562", "status": null, "reaction_type": 0, "description": "", "sharing_url": "https://www.douban.com/doubanapp/dispatch?uri=/photo/2197233744/", "url": "https://movie.douban.com/photos/photo/2197233744/", "reply_limit": "A", "uri": "douban://douban.com/photo/2197233744", "likers_count": 0, "reactions_count": 0, "comments_count": 0, "position": 29}, {"read_count": 31, "image": {"large": {"url": "https://img9.doubanio.com/view/photo/l/public/p2197233715.webp", "width": 720, "height": 400, "size": 0}, "raw": null, "small": {"url": "https://img9.doubanio.com/view/photo/s/public/p2197233715.webp", "width": 600, "height": 333, "size": 0}, "is_animated": false, "normal": {"url": "https://img9.doubanio.com/view/photo/m/public/p2197233715.webp", "width": 600, "height": 333, "size": 0}}, "create_time": "2014-08-25 11:38:04", "collections_count": 0, "reshares_count": 0, "id": "2197233715", "author": {"loc": {"id": "118096", "name": "\u6ca7\u5dde", "uid": "cangzhou"}, "kind": "user", "name": "\u8309\u8389\u9999\u7247", "url": "https://www.douban.com/people/75681431/", "reg_time": "2013-07-23 14:21:59", "uri": "douban://douban.com/user/75681431", "avatar_side_icon_id": "", "avatar": "https://img9.doubanio.com/icon/up75681431-2.jpg", "id": "75681431", "type": "user", "avatar_side_icon": "", "uid": "75681431"}, "is_collected": false, "subtype": "photo", "type": "photo", "owner_uri": "douban://douban.com/tv/25732562", "status": null, "reaction_type": 0, "description": "", "sharing_url": "https://www.douban.com/doubanapp/dispatch?uri=/photo/2197233715/", "url": "https://movie.douban.com/photos/photo/2197233715/", "reply_limit": "A", "uri": "douban://douban.com/photo/2197233715", "likers_count": 0, "reactions_count": 0, "comments_count": 0, "position": 30}, {"read_count": 33, "image": {"large": {"url": "https://img9.doubanio.com/view/photo/l/public/p2197233665.webp", "width": 720, "height": 400, "size": 0}, "raw": null, "small": {"url": "https://img9.doubanio.com/view/photo/s/public/p2197233665.webp", "width": 600, "height": 333, "size": 0}, "is_animated": false, "normal": {"url": "https://img9.doubanio.com/view/photo/m/public/p2197233665.webp", "width": 600, "height": 333, "size": 0}}, "create_time": "2014-08-25 11:37:42", "collections_count": 0, "reshares_count": 0, "id": "2197233665", "author": {"loc": {"id": "118096", "name": "\u6ca7\u5dde", "uid": "cangzhou"}, "kind": "user", "name": "\u8309\u8389\u9999\u7247", "url": "https://www.douban.com/people/75681431/", "reg_time": "2013-07-23 14:21:59", "uri": "douban://douban.com/user/75681431", "avatar_side_icon_id": "", "avatar": "https://img9.doubanio.com/icon/up75681431-2.jpg", "id": "75681431", "type": "user", "avatar_side_icon": "", "uid": "75681431"}, "is_collected": false, "subtype": "photo", "type": "photo", "owner_uri": "douban://douban.com/tv/25732562", "status": null, "reaction_type": 0, "description": "", "sharing_url": "https://www.douban.com/doubanapp/dispatch?uri=/photo/2197233665/", "url": "https://movie.douban.com/photos/photo/2197233665/", "reply_limit": "A", "uri": "douban://douban.com/photo/2197233665", "likers_count": 0, "reactions_count": 0, "comments_count": 0, "position": 31}, {"read_count": 21, "image": {"large": {"url": "https://img9.doubanio.com/view/photo/l/public/p2197233617.webp", "width": 720, "height": 400, "size": 0}, "raw": null, "small": {"url": "https://img9.doubanio.com/view/photo/s/public/p2197233617.webp", "width": 600, "height": 333, "size": 0}, "is_animated": false, "normal": {"url": "https://img9.doubanio.com/view/photo/m/public/p2197233617.webp", "width": 600, "height": 333, "size": 0}}, "create_time": "2014-08-25 11:37:20", "collections_count": 0, "reshares_count": 0, "id": "2197233617", "author": {"loc": {"id": "118096", "name": "\u6ca7\u5dde", "uid": "cangzhou"}, "kind": "user", "name": "\u8309\u8389\u9999\u7247", "url": "https://www.douban.com/people/75681431/", "reg_time": "2013-07-23 14:21:59", "uri": "douban://douban.com/user/75681431", "avatar_side_icon_id": "", "avatar": "https://img9.doubanio.com/icon/up75681431-2.jpg", "id": "75681431", "type": "user", "avatar_side_icon": "", "uid": "75681431"}, "is_collected": false, "subtype": "photo", "type": "photo", "owner_uri": "douban://douban.com/tv/25732562", "status": null, "reaction_type": 0, "description": "", "sharing_url": "https://www.douban.com/doubanapp/dispatch?uri=/photo/2197233617/", "url": "https://movie.douban.com/photos/photo/2197233617/", "reply_limit": "A", "uri": "douban://douban.com/photo/2197233617", "likers_count": 0, "reactions_count": 0, "comments_count": 0, "position": 32}, {"read_count": 19, "image": {"large": {"url": "https://img9.doubanio.com/view/photo/l/public/p2197233589.webp", "width": 720, "height": 400, "size": 0}, "raw": null, "small": {"url": "https://img9.doubanio.com/view/photo/s/public/p2197233589.webp", "width": 600, "height": 333, "size": 0}, "is_animated": false, "normal": {"url": "https://img9.doubanio.com/view/photo/m/public/p2197233589.webp", "width": 600, "height": 333, "size": 0}}, "create_time": "2014-08-25 11:37:00", "collections_count": 0, "reshares_count": 0, "id": "2197233589", "author": {"loc": {"id": "118096", "name": "\u6ca7\u5dde", "uid": "cangzhou"}, "kind": "user", "name": "\u8309\u8389\u9999\u7247", "url": "https://www.douban.com/people/75681431/", "reg_time": "2013-07-23 14:21:59", "uri": "douban://douban.com/user/75681431", "avatar_side_icon_id": "", "avatar": "https://img9.doubanio.com/icon/up75681431-2.jpg", "id": "75681431", "type": "user", "avatar_side_icon": "", "uid": "75681431"}, "is_collected": false, "subtype": "photo", "type": "photo", "owner_uri": "douban://douban.com/tv/25732562", "status": null, "reaction_type": 0, "description": "", "sharing_url": "https://www.douban.com/doubanapp/dispatch?uri=/photo/2197233589/", "url": "https://movie.douban.com/photos/photo/2197233589/", "reply_limit": "A", "uri": "douban://douban.com/photo/2197233589", "likers_count": 0, "reactions_count": 0, "comments_count": 0, "position": 33}, {"read_count": 22, "image": {"large": {"url": "https://img9.doubanio.com/view/photo/l/public/p2197233560.webp", "width": 720, "height": 400, "size": 0}, "raw": null, "small": {"url": "https://img9.doubanio.com/view/photo/s/public/p2197233560.webp", "width": 600, "height": 333, "size": 0}, "is_animated": false, "normal": {"url": "https://img9.doubanio.com/view/photo/m/public/p2197233560.webp", "width": 600, "height": 333, "size": 0}}, "create_time": "2014-08-25 11:36:43", "collections_count": 0, "reshares_count": 0, "id": "2197233560", "author": {"loc": {"id": "118096", "name": "\u6ca7\u5dde", "uid": "cangzhou"}, "kind": "user", "name": "\u8309\u8389\u9999\u7247", "url": "https://www.douban.com/people/75681431/", "reg_time": "2013-07-23 14:21:59", "uri": "douban://douban.com/user/75681431", "avatar_side_icon_id": "", "avatar": "https://img9.doubanio.com/icon/up75681431-2.jpg", "id": "75681431", "type": "user", "avatar_side_icon": "", "uid": "75681431"}, "is_collected": false, "subtype": "photo", "type": "photo", "owner_uri": "douban://douban.com/tv/25732562", "status": null, "reaction_type": 0, "description": "", "sharing_url": "https://www.douban.com/doubanapp/dispatch?uri=/photo/2197233560/", "url": "https://movie.douban.com/photos/photo/2197233560/", "reply_limit": "A", "uri": "douban://douban.com/photo/2197233560", "likers_count": 0, "reactions_count": 0, "comments_count": 0, "position": 34}, {"read_count": 25, "image": {"large": {"url": "https://img9.doubanio.com/view/photo/l/public/p2196475093.webp", "width": 720, "height": 400, "size": 0}, "raw": null, "small": {"url": "https://img9.doubanio.com/view/photo/s/public/p2196475093.webp", "width": 600, "height": 333, "size": 0}, "is_animated": false, "normal": {"url": "https://img9.doubanio.com/view/photo/m/public/p2196475093.webp", "width": 600, "height": 333, "size": 0}}, "create_time": "2014-08-20 13:29:00", "collections_count": 0, "reshares_count": 0, "id": "2196475093", "author": {"loc": {"id": "118096", "name": "\u6ca7\u5dde", "uid": "cangzhou"}, "kind": "user", "name": "\u8309\u8389\u9999\u7247", "url": "https://www.douban.com/people/75681431/", "reg_time": "2013-07-23 14:21:59", "uri": "douban://douban.com/user/75681431", "avatar_side_icon_id": "", "avatar": "https://img9.doubanio.com/icon/up75681431-2.jpg", "id": "75681431", "type": "user", "avatar_side_icon": "", "uid": "75681431"}, "is_collected": false, "subtype": "photo", "type": "photo", "owner_uri": "douban://douban.com/tv/25732562", "status": null, "reaction_type": 0, "description": "", "sharing_url": "https://www.douban.com/doubanapp/dispatch?uri=/photo/2196475093/", "url": "https://movie.douban.com/photos/photo/2196475093/", "reply_limit": "A", "uri": "douban://douban.com/photo/2196475093", "likers_count": 0, "reactions_count": 0, "comments_count": 0, "position": 35}, {"read_count": 38, "image": {"large": {"url": "https://img9.doubanio.com/view/photo/l/public/p2196475055.webp", "width": 720, "height": 400, "size": 0}, "raw": null, "small": {"url": "https://img9.doubanio.com/view/photo/s/public/p2196475055.webp", "width": 600, "height": 333, "size": 0}, "is_animated": false, "normal": {"url": "https://img9.doubanio.com/view/photo/m/public/p2196475055.webp", "width": 600, "height": 333, "size": 0}}, "create_time": "2014-08-20 13:28:42", "collections_count": 0, "reshares_count": 0, "id": "2196475055", "author": {"loc": {"id": "118096", "name": "\u6ca7\u5dde", "uid": "cangzhou"}, "kind": "user", "name": "\u8309\u8389\u9999\u7247", "url": "https://www.douban.com/people/75681431/", "reg_time": "2013-07-23 14:21:59", "uri": "douban://douban.com/user/75681431", "avatar_side_icon_id": "", "avatar": "https://img9.doubanio.com/icon/up75681431-2.jpg", "id": "75681431", "type": "user", "avatar_side_icon": "", "uid": "75681431"}, "is_collected": false, "subtype": "photo", "type": "photo", "owner_uri": "douban://douban.com/tv/25732562", "status": null, "reaction_type": 0, "description": "", "sharing_url": "https://www.douban.com/doubanapp/dispatch?uri=/photo/2196475055/", "url": "https://movie.douban.com/photos/photo/2196475055/", "reply_limit": "A", "uri": "douban://douban.com/photo/2196475055", "likers_count": 0, "reactions_count": 0, "comments_count": 1, "position": 36}, {"read_count": 25, "image": {"large": {"url": "https://img9.doubanio.com/view/photo/l/public/p2196475003.webp", "width": 720, "height": 400, "size": 0}, "raw": null, "small": {"url": "https://img9.doubanio.com/view/photo/s/public/p2196475003.webp", "width": 600, "height": 333, "size": 0}, "is_animated": false, "normal": {"url": "https://img9.doubanio.com/view/photo/m/public/p2196475003.webp", "width": 600, "height": 333, "size": 0}}, "create_time": "2014-08-20 13:28:26", "collections_count": 0, "reshares_count": 0, "id": "2196475003", "author": {"loc": {"id": "118096", "name": "\u6ca7\u5dde", "uid": "cangzhou"}, "kind": "user", "name": "\u8309\u8389\u9999\u7247", "url": "https://www.douban.com/people/75681431/", "reg_time": "2013-07-23 14:21:59", "uri": "douban://douban.com/user/75681431", "avatar_side_icon_id": "", "avatar": "https://img9.doubanio.com/icon/up75681431-2.jpg", "id": "75681431", "type": "user", "avatar_side_icon": "", "uid": "75681431"}, "is_collected": false, "subtype": "photo", "type": "photo", "owner_uri": "douban://douban.com/tv/25732562", "status": null, "reaction_type": 0, "description": "", "sharing_url": "https://www.douban.com/doubanapp/dispatch?uri=/photo/2196475003/", "url": "https://movie.douban.com/photos/photo/2196475003/", "reply_limit": "A", "uri": "douban://douban.com/photo/2196475003", "likers_count": 0, "reactions_count": 0, "comments_count": 1, "position": 37}, {"read_count": 25, "image": {"large": {"url": "https://img9.doubanio.com/view/photo/l/public/p2196474948.webp", "width": 720, "height": 400, "size": 0}, "raw": null, "small": {"url": "https://img9.doubanio.com/view/photo/s/public/p2196474948.webp", "width": 600, "height": 333, "size": 0}, "is_animated": false, "normal": {"url": "https://img9.doubanio.com/view/photo/m/public/p2196474948.webp", "width": 600, "height": 333, "size": 0}}, "create_time": "2014-08-20 13:28:08", "collections_count": 0, "reshares_count": 0, "id": "2196474948", "author": {"loc": {"id": "118096", "name": "\u6ca7\u5dde", "uid": "cangzhou"}, "kind": "user", "name": "\u8309\u8389\u9999\u7247", "url": "https://www.douban.com/people/75681431/", "reg_time": "2013-07-23 14:21:59", "uri": "douban://douban.com/user/75681431", "avatar_side_icon_id": "", "avatar": "https://img9.doubanio.com/icon/up75681431-2.jpg", "id": "75681431", "type": "user", "avatar_side_icon": "", "uid": "75681431"}, "is_collected": false, "subtype": "photo", "type": "photo", "owner_uri": "douban://douban.com/tv/25732562", "status": null, "reaction_type": 0, "description": "", "sharing_url": "https://www.douban.com/doubanapp/dispatch?uri=/photo/2196474948/", "url": "https://movie.douban.com/photos/photo/2196474948/", "reply_limit": "A", "uri": "douban://douban.com/photo/2196474948", "likers_count": 0, "reactions_count": 0, "comments_count": 0, "position": 38}, {"read_count": 19, "image": {"large": {"url": "https://img9.doubanio.com/view/photo/l/public/p2196474910.webp", "width": 720, "height": 400, "size": 0}, "raw": null, "small": {"url": "https://img9.doubanio.com/view/photo/s/public/p2196474910.webp", "width": 600, "height": 333, "size": 0}, "is_animated": false, "normal": {"url": "https://img9.doubanio.com/view/photo/m/public/p2196474910.webp", "width": 600, "height": 333, "size": 0}}, "create_time": "2014-08-20 13:27:52", "collections_count": 0, "reshares_count": 0, "id": "2196474910", "author": {"loc": {"id": "118096", "name": "\u6ca7\u5dde", "uid": "cangzhou"}, "kind": "user", "name": "\u8309\u8389\u9999\u7247", "url": "https://www.douban.com/people/75681431/", "reg_time": "2013-07-23 14:21:59", "uri": "douban://douban.com/user/75681431", "avatar_side_icon_id": "", "avatar": "https://img9.doubanio.com/icon/up75681431-2.jpg", "id": "75681431", "type": "user", "avatar_side_icon": "", "uid": "75681431"}, "is_collected": false, "subtype": "photo", "type": "photo", "owner_uri": "douban://douban.com/tv/25732562", "status": null, "reaction_type": 0, "description": "", "sharing_url": "https://www.douban.com/doubanapp/dispatch?uri=/photo/2196474910/", "url": "https://movie.douban.com/photos/photo/2196474910/", "reply_limit": "A", "uri": "douban://douban.com/photo/2196474910", "likers_count": 0, "reactions_count": 0, "comments_count": 0, "position": 39}, {"read_count": 19, "image": {"large": {"url": "https://img9.doubanio.com/view/photo/l/public/p2196474871.webp", "width": 720, "height": 400, "size": 0}, "raw": null, "small": {"url": "https://img9.doubanio.com/view/photo/s/public/p2196474871.webp", "width": 600, "height": 333, "size": 0}, "is_animated": false, "normal": {"url": "https://img9.doubanio.com/view/photo/m/public/p2196474871.webp", "width": 600, "height": 333, "size": 0}}, "create_time": "2014-08-20 13:27:36", "collections_count": 0, "reshares_count": 0, "id": "2196474871", "author": {"loc": {"id": "118096", "name": "\u6ca7\u5dde", "uid": "cangzhou"}, "kind": "user", "name": "\u8309\u8389\u9999\u7247", "url": "https://www.douban.com/people/75681431/", "reg_time": "2013-07-23 14:21:59", "uri": "douban://douban.com/user/75681431", "avatar_side_icon_id": "", "avatar": "https://img9.doubanio.com/icon/up75681431-2.jpg", "id": "75681431", "type": "user", "avatar_side_icon": "", "uid": "75681431"}, "is_collected": false, "subtype": "photo", "type": "photo", "owner_uri": "douban://douban.com/tv/25732562", "status": null, "reaction_type": 0, "description": "", "sharing_url": "https://www.douban.com/doubanapp/dispatch?uri=/photo/2196474871/", "url": "https://movie.douban.com/photos/photo/2196474871/", "reply_limit": "A", "uri": "douban://douban.com/photo/2196474871", "likers_count": 0, "reactions_count": 0, "comments_count": 0, "position": 40}, {"read_count": 16, "image": {"large": {"url": "https://img9.doubanio.com/view/photo/l/public/p2196474804.webp", "width": 720, "height": 400, "size": 0}, "raw": null, "small": {"url": "https://img9.doubanio.com/view/photo/s/public/p2196474804.webp", "width": 600, "height": 333, "size": 0}, "is_animated": false, "normal": {"url": "https://img9.doubanio.com/view/photo/m/public/p2196474804.webp", "width": 600, "height": 333, "size": 0}}, "create_time": "2014-08-20 13:27:03", "collections_count": 0, "reshares_count": 0, "id": "2196474804", "author": {"loc": {"id": "118096", "name": "\u6ca7\u5dde", "uid": "cangzhou"}, "kind": "user", "name": "\u8309\u8389\u9999\u7247", "url": "https://www.douban.com/people/75681431/", "reg_time": "2013-07-23 14:21:59", "uri": "douban://douban.com/user/75681431", "avatar_side_icon_id": "", "avatar": "https://img9.doubanio.com/icon/up75681431-2.jpg", "id": "75681431", "type": "user", "avatar_side_icon": "", "uid": "75681431"}, "is_collected": false, "subtype": "photo", "type": "photo", "owner_uri": "douban://douban.com/tv/25732562", "status": null, "reaction_type": 0, "description": "", "sharing_url": "https://www.douban.com/doubanapp/dispatch?uri=/photo/2196474804/", "url": "https://movie.douban.com/photos/photo/2196474804/", "reply_limit": "A", "uri": "douban://douban.com/photo/2196474804", "likers_count": 0, "reactions_count": 0, "comments_count": 0, "position": 42}, {"read_count": 16, "image": {"large": {"url": "https://img9.doubanio.com/view/photo/l/public/p2196474771.webp", "width": 720, "height": 400, "size": 0}, "raw": null, "small": {"url": "https://img9.doubanio.com/view/photo/s/public/p2196474771.webp", "width": 600, "height": 333, "size": 0}, "is_animated": false, "normal": {"url": "https://img9.doubanio.com/view/photo/m/public/p2196474771.webp", "width": 600, "height": 333, "size": 0}}, "create_time": "2014-08-20 13:26:46", "collections_count": 0, "reshares_count": 0, "id": "2196474771", "author": {"loc": {"id": "118096", "name": "\u6ca7\u5dde", "uid": "cangzhou"}, "kind": "user", "name": "\u8309\u8389\u9999\u7247", "url": "https://www.douban.com/people/75681431/", "reg_time": "2013-07-23 14:21:59", "uri": "douban://douban.com/user/75681431", "avatar_side_icon_id": "", "avatar": "https://img9.doubanio.com/icon/up75681431-2.jpg", "id": "75681431", "type": "user", "avatar_side_icon": "", "uid": "75681431"}, "is_collected": false, "subtype": "photo", "type": "photo", "owner_uri": "douban://douban.com/tv/25732562", "status": null, "reaction_type": 0, "description": "", "sharing_url": "https://www.douban.com/doubanapp/dispatch?uri=/photo/2196474771/", "url": "https://movie.douban.com/photos/photo/2196474771/", "reply_limit": "A", "uri": "douban://douban.com/photo/2196474771", "likers_count": 0, "reactions_count": 0, "comments_count": 0, "position": 43}, {"read_count": 25, "image": {"large": {"url": "https://img9.doubanio.com/view/photo/l/public/p2190426318.webp", "width": 720, "height": 400, "size": 0}, "raw": null, "small": {"url": "https://img9.doubanio.com/view/photo/s/public/p2190426318.webp", "width": 600, "height": 333, "size": 0}, "is_animated": false, "normal": {"url": "https://img9.doubanio.com/view/photo/m/public/p2190426318.webp", "width": 600, "height": 333, "size": 0}}, "create_time": "2014-07-07 21:48:51", "collections_count": 0, "reshares_count": 0, "id": "2190426318", "author": {"loc": {"id": "118096", "name": "\u6ca7\u5dde", "uid": "cangzhou"}, "kind": "user", "name": "\u8309\u8389\u9999\u7247", "url": "https://www.douban.com/people/75681431/", "reg_time": "2013-07-23 14:21:59", "uri": "douban://douban.com/user/75681431", "avatar_side_icon_id": "", "avatar": "https://img9.doubanio.com/icon/up75681431-2.jpg", "id": "75681431", "type": "user", "avatar_side_icon": "", "uid": "75681431"}, "is_collected": false, "subtype": "photo", "type": "photo", "owner_uri": "douban://douban.com/tv/25732562", "status": null, "reaction_type": 0, "description": "", "sharing_url": "https://www.douban.com/doubanapp/dispatch?uri=/photo/2190426318/", "url": "https://movie.douban.com/photos/photo/2190426318/", "reply_limit": "A", "uri": "douban://douban.com/photo/2190426318", "likers_count": 0, "reactions_count": 0, "comments_count": 0, "position": 44}, {"read_count": 23, "image": {"large": {"url": "https://img9.doubanio.com/view/photo/l/public/p2178654053.webp", "width": 720, "height": 400, "size": 0}, "raw": null, "small": {"url": "https://img9.doubanio.com/view/photo/s/public/p2178654053.webp", "width": 600, "height": 333, "size": 0}, "is_animated": false, "normal": {"url": "https://img9.doubanio.com/view/photo/m/public/p2178654053.webp", "width": 600, "height": 333, "size": 0}}, "create_time": "2014-04-13 18:47:00", "collections_count": 0, "reshares_count": 0, "id": "2178654053", "author": {"loc": {"id": "118096", "name": "\u6ca7\u5dde", "uid": "cangzhou"}, "kind": "user", "name": "\u8309\u8389\u9999\u7247", "url": "https://www.douban.com/people/75681431/", "reg_time": "2013-07-23 14:21:59", "uri": "douban://douban.com/user/75681431", "avatar_side_icon_id": "", "avatar": "https://img9.doubanio.com/icon/up75681431-2.jpg", "id": "75681431", "type": "user", "avatar_side_icon": "", "uid": "75681431"}, "is_collected": false, "subtype": "photo", "type": "photo", "owner_uri": "douban://douban.com/tv/25732562", "status": null, "reaction_type": 0, "description": "", "sharing_url": "https://www.douban.com/doubanapp/dispatch?uri=/photo/2178654053/", "url": "https://movie.douban.com/photos/photo/2178654053/", "reply_limit": "A", "uri": "douban://douban.com/photo/2178654053", "likers_count": 0, "reactions_count": 0, "comments_count": 0, "position": 45}, {"read_count": 17, "image": {"large": {"url": "https://img9.doubanio.com/view/photo/l/public/p2178654024.webp", "width": 720, "height": 400, "size": 0}, "raw": null, "small": {"url": "https://img9.doubanio.com/view/photo/s/public/p2178654024.webp", "width": 600, "height": 333, "size": 0}, "is_animated": false, "normal": {"url": "https://img9.doubanio.com/view/photo/m/public/p2178654024.webp", "width": 600, "height": 333, "size": 0}}, "create_time": "2014-04-13 18:46:44", "collections_count": 0, "reshares_count": 0, "id": "2178654024", "author": {"loc": {"id": "118096", "name": "\u6ca7\u5dde", "uid": "cangzhou"}, "kind": "user", "name": "\u8309\u8389\u9999\u7247", "url": "https://www.douban.com/people/75681431/", "reg_time": "2013-07-23 14:21:59", "uri": "douban://douban.com/user/75681431", "avatar_side_icon_id": "", "avatar": "https://img9.doubanio.com/icon/up75681431-2.jpg", "id": "75681431", "type": "user", "avatar_side_icon": "", "uid": "75681431"}, "is_collected": false, "subtype": "photo", "type": "photo", "owner_uri": "douban://douban.com/tv/25732562", "status": null, "reaction_type": 0, "description": "", "sharing_url": "https://www.douban.com/doubanapp/dispatch?uri=/photo/2178654024/", "url": "https://movie.douban.com/photos/photo/2178654024/", "reply_limit": "A", "uri": "douban://douban.com/photo/2178654024", "likers_count": 0, "reactions_count": 0, "comments_count": 0, "position": 46}, {"read_count": 12, "image": {"large": {"url": "https://img9.doubanio.com/view/photo/l/public/p2178654004.webp", "width": 720, "height": 400, "size": 0}, "raw": null, "small": {"url": "https://img9.doubanio.com/view/photo/s/public/p2178654004.webp", "width": 600, "height": 333, "size": 0}, "is_animated": false, "normal": {"url": "https://img9.doubanio.com/view/photo/m/public/p2178654004.webp", "width": 600, "height": 333, "size": 0}}, "create_time": "2014-04-13 18:46:29", "collections_count": 0, "reshares_count": 0, "id": "2178654004", "author": {"loc": {"id": "118096", "name": "\u6ca7\u5dde", "uid": "cangzhou"}, "kind": "user", "name": "\u8309\u8389\u9999\u7247", "url": "https://www.douban.com/people/75681431/", "reg_time": "2013-07-23 14:21:59", "uri": "douban://douban.com/user/75681431", "avatar_side_icon_id": "", "avatar": "https://img9.doubanio.com/icon/up75681431-2.jpg", "id": "75681431", "type": "user", "avatar_side_icon": "", "uid": "75681431"}, "is_collected": false, "subtype": "photo", "type": "photo", "owner_uri": "douban://douban.com/tv/25732562", "status": null, "reaction_type": 0, "description": "", "sharing_url": "https://www.douban.com/doubanapp/dispatch?uri=/photo/2178654004/", "url": "https://movie.douban.com/photos/photo/2178654004/", "reply_limit": "A", "uri": "douban://douban.com/photo/2178654004", "likers_count": 0, "reactions_count": 0, "comments_count": 0, "position": 47}, {"read_count": 20, "image": {"large": {"url": "https://img9.doubanio.com/view/photo/l/public/p2178653961.webp", "width": 720, "height": 400, "size": 0}, "raw": null, "small": {"url": "https://img9.doubanio.com/view/photo/s/public/p2178653961.webp", "width": 600, "height": 333, "size": 0}, "is_animated": false, "normal": {"url": "https://img9.doubanio.com/view/photo/m/public/p2178653961.webp", "width": 600, "height": 333, "size": 0}}, "create_time": "2014-04-13 18:46:15", "collections_count": 0, "reshares_count": 0, "id": "2178653961", "author": {"loc": {"id": "118096", "name": "\u6ca7\u5dde", "uid": "cangzhou"}, "kind": "user", "name": "\u8309\u8389\u9999\u7247", "url": "https://www.douban.com/people/75681431/", "reg_time": "2013-07-23 14:21:59", "uri": "douban://douban.com/user/75681431", "avatar_side_icon_id": "", "avatar": "https://img9.doubanio.com/icon/up75681431-2.jpg", "id": "75681431", "type": "user", "avatar_side_icon": "", "uid": "75681431"}, "is_collected": false, "subtype": "photo", "type": "photo", "owner_uri": "douban://douban.com/tv/25732562", "status": null, "reaction_type": 0, "description": "", "sharing_url": "https://www.douban.com/doubanapp/dispatch?uri=/photo/2178653961/", "url": "https://movie.douban.com/photos/photo/2178653961/", "reply_limit": "A", "uri": "douban://douban.com/photo/2178653961", "likers_count": 0, "reactions_count": 0, "comments_count": 0, "position": 48}], "w": 0, "total": 90, "start": 0, "movie_info": {"id": "25732562", "title": "\u72d7\u72d7\u535a\u5ba2 \u7b2c\u4e8c\u5b63", "original_title": "Dog with a Blog Season 2", "year": "2013", "is_tv": true, "rating": {"count": 856, "max": 10, "star_count": 4.5, "value": 8.9}, "poster": "https://img9.doubanio.com/view/photo/m_ratio_poster/public/p2871366872.webp"}}