{"count": 49, "c": 0, "f": 0, "o": 75, "n": 0, "photos": [{"read_count": 2401, "image": {"large": {"url": "https://img9.doubanio.com/view/photo/l/public/p2681329455.webp", "width": 1600, "height": 1120, "size": 0}, "raw": null, "small": {"url": "https://img9.doubanio.com/view/photo/s/public/p2681329455.webp", "width": 600, "height": 420, "size": 0}, "normal": {"url": "https://img9.doubanio.com/view/photo/m/public/p2681329455.webp", "width": 600, "height": 420, "size": 0}, "is_animated": false}, "create_time": "2021-09-10 10:05:33", "collections_count": 2, "reshares_count": 0, "id": "2681329455", "author": {"loc": {"id": "118370", "name": "\u6797\u829d", "uid": "linzhi"}, "kind": "user", "name": "\u5ddd\u6c99\ud83c\udde8\ud83c\uddf3", "url": "https://www.douban.com/people/222194554/", "reg_time": "2020-08-25 17:00:54", "uri": "douban://douban.com/user/222194554", "avatar_side_icon_id": "", "avatar": "https://img9.doubanio.com/icon/up222194554-6.jpg", "id": "222194554", "type": "user", "avatar_side_icon": "", "uid": "222194554"}, "is_collected": false, "subtype": "photo", "type": "photo", "owner_uri": "douban://douban.com/tv/35371695", "status": null, "reaction_type": 0, "description": "", "sharing_url": "https://www.douban.com/doubanapp/dispatch?uri=/photo/2681329455/", "url": "https://movie.douban.com/photos/photo/2681329455/", "reply_limit": "A", "uri": "douban://douban.com/photo/2681329455", "likers_count": 22, "reactions_count": 22, "comments_count": 0, "position": 63}, {"read_count": 597, "image": {"large": {"url": "https://img9.doubanio.com/view/photo/l/public/p2669221561.webp", "width": 1066, "height": 1600, "size": 0}, "raw": null, "small": {"url": "https://img9.doubanio.com/view/photo/s/public/p2669221561.webp", "width": 400, "height": 600, "size": 0}, "normal": {"url": "https://img9.doubanio.com/view/photo/m/public/p2669221561.webp", "width": 400, "height": 600, "size": 0}, "is_animated": false}, "create_time": "2021-07-09 21:55:33", "collections_count": 1, "reshares_count": 1, "id": "2669221561", "author": {"loc": null, "kind": "user", "name": "\u8c46\u53cb236971692", "url": "https://www.douban.com/people/236971692/", "reg_time": "2021-04-26 12:30:25", "uri": "douban://douban.com/user/236971692", "avatar_side_icon_id": "", "avatar": "https://img9.doubanio.com/img/files/file-1609845567.png", "id": "236971692", "type": "user", "avatar_side_icon": "", "uid": "236971692"}, "is_collected": false, "subtype": "photo", "type": "photo", "owner_uri": "douban://douban.com/tv/35371695", "status": null, "reaction_type": 0, "description": "", "sharing_url": "https://www.douban.com/doubanapp/dispatch?uri=/photo/2669221561/", "url": "https://movie.douban.com/photos/photo/2669221561/", "reply_limit": "A", "uri": "douban://douban.com/photo/2669221561", "likers_count": 12, "reactions_count": 12, "comments_count": 0, "position": 0}, {"read_count": 778, "image": {"large": {"url": "https://img9.doubanio.com/view/photo/l/public/p2665998704.webp", "width": 1600, "height": 1067, "size": 0}, "raw": null, "small": {"url": "https://img9.doubanio.com/view/photo/s/public/p2665998704.webp", "width": 600, "height": 400, "size": 0}, "normal": {"url": "https://img9.doubanio.com/view/photo/m/public/p2665998704.webp", "width": 600, "height": 400, "size": 0}, "is_animated": false}, "create_time": "2021-06-30 17:08:37", "collections_count": 1, "reshares_count": 1, "id": "2665998704", "author": {"loc": {"id": "108296", "name": "\u4e0a\u6d77", "uid": "shanghai"}, "kind": "user", "name": "six-up", "url": "https://www.douban.com/people/228811628/", "reg_time": "2020-12-22 22:48:12", "uri": "douban://douban.com/user/228811628", "avatar_side_icon_id": "", "avatar": "https://img9.doubanio.com/icon/up228811628-2.jpg", "id": "228811628", "type": "user", "avatar_side_icon": "", "uid": "228811628"}, "is_collected": false, "subtype": "photo", "type": "photo", "owner_uri": "douban://douban.com/tv/35371695", "status": null, "reaction_type": 0, "description": "", "sharing_url": "https://www.douban.com/doubanapp/dispatch?uri=/photo/2665998704/", "url": "https://movie.douban.com/photos/photo/2665998704/", "reply_limit": "A", "uri": "douban://douban.com/photo/2665998704", "likers_count": 9, "reactions_count": 9, "comments_count": 4, "position": 1}, {"read_count": 419, "image": {"large": {"url": "https://img9.doubanio.com/view/photo/l/public/p2665998707.webp", "width": 1600, "height": 1066, "size": 0}, "raw": null, "small": {"url": "https://img9.doubanio.com/view/photo/s/public/p2665998707.webp", "width": 600, "height": 400, "size": 0}, "normal": {"url": "https://img9.doubanio.com/view/photo/m/public/p2665998707.webp", "width": 600, "height": 400, "size": 0}, "is_animated": false}, "create_time": "2021-06-30 17:08:39", "collections_count": 1, "reshares_count": 1, "id": "2665998707", "author": {"loc": {"id": "108296", "name": "\u4e0a\u6d77", "uid": "shanghai"}, "kind": "user", "name": "six-up", "url": "https://www.douban.com/people/228811628/", "reg_time": "2020-12-22 22:48:12", "uri": "douban://douban.com/user/228811628", "avatar_side_icon_id": "", "avatar": "https://img9.doubanio.com/icon/up228811628-2.jpg", "id": "228811628", "type": "user", "avatar_side_icon": "", "uid": "228811628"}, "is_collected": false, "subtype": "photo", "type": "photo", "owner_uri": "douban://douban.com/tv/35371695", "status": null, "reaction_type": 0, "description": "", "sharing_url": "https://www.douban.com/doubanapp/dispatch?uri=/photo/2665998707/", "url": "https://movie.douban.com/photos/photo/2665998707/", "reply_limit": "A", "uri": "douban://douban.com/photo/2665998707", "likers_count": 6, "reactions_count": 6, "comments_count": 0, "position": 2}, {"read_count": 372, "image": {"large": {"url": "https://img9.doubanio.com/view/photo/l/public/p2872963009.webp", "width": 1600, "height": 1067, "size": 0}, "raw": null, "small": {"url": "https://img9.doubanio.com/view/photo/s/public/p2872963009.webp", "width": 600, "height": 400, "size": 0}, "normal": {"url": "https://img9.doubanio.com/view/photo/m/public/p2872963009.webp", "width": 600, "height": 400, "size": 0}, "is_animated": false}, "create_time": "2022-05-13 12:47:50", "collections_count": 0, "reshares_count": 0, "id": "2872963009", "author": {"loc": null, "kind": "user", "name": "\u8c46\u53cb254021938", "url": "https://www.douban.com/people/254021938/", "reg_time": "2022-02-14 16:31:00", "uri": "douban://douban.com/user/254021938", "avatar_side_icon_id": "", "avatar": "https://img9.doubanio.com/img/files/file-1609845567.png", "id": "254021938", "type": "user", "avatar_side_icon": "", "uid": "254021938"}, "is_collected": false, "subtype": "photo", "type": "photo", "owner_uri": "douban://douban.com/tv/35371695", "status": null, "reaction_type": 0, "description": "", "sharing_url": "https://www.douban.com/doubanapp/dispatch?uri=/photo/2872963009/", "url": "https://movie.douban.com/photos/photo/2872963009/", "reply_limit": "A", "uri": "douban://douban.com/photo/2872963009", "likers_count": 4, "reactions_count": 4, "comments_count": 1, "position": 5}, {"read_count": 226, "image": {"large": {"url": "https://img9.doubanio.com/view/photo/l/public/p2872963033.webp", "width": 1600, "height": 1067, "size": 0}, "raw": null, "small": {"url": "https://img9.doubanio.com/view/photo/s/public/p2872963033.webp", "width": 600, "height": 400, "size": 0}, "normal": {"url": "https://img9.doubanio.com/view/photo/m/public/p2872963033.webp", "width": 600, "height": 400, "size": 0}, "is_animated": false}, "create_time": "2022-05-13 12:47:58", "collections_count": 1, "reshares_count": 0, "id": "2872963033", "author": {"loc": null, "kind": "user", "name": "\u8c46\u53cb254021938", "url": "https://www.douban.com/people/254021938/", "reg_time": "2022-02-14 16:31:00", "uri": "douban://douban.com/user/254021938", "avatar_side_icon_id": "", "avatar": "https://img9.doubanio.com/img/files/file-1609845567.png", "id": "254021938", "type": "user", "avatar_side_icon": "", "uid": "254021938"}, "is_collected": false, "subtype": "photo", "type": "photo", "owner_uri": "douban://douban.com/tv/35371695", "status": null, "reaction_type": 0, "description": "", "sharing_url": "https://www.douban.com/doubanapp/dispatch?uri=/photo/2872963033/", "url": "https://movie.douban.com/photos/photo/2872963033/", "reply_limit": "A", "uri": "douban://douban.com/photo/2872963033", "likers_count": 3, "reactions_count": 3, "comments_count": 0, "position": 4}, {"read_count": 198, "image": {"large": {"url": "https://img9.doubanio.com/view/photo/l/public/p2669221543.webp", "width": 1600, "height": 1066, "size": 0}, "raw": null, "small": {"url": "https://img9.doubanio.com/view/photo/s/public/p2669221543.webp", "width": 600, "height": 400, "size": 0}, "normal": {"url": "https://img9.doubanio.com/view/photo/m/public/p2669221543.webp", "width": 600, "height": 400, "size": 0}, "is_animated": false}, "create_time": "2021-07-09 21:55:26", "collections_count": 0, "reshares_count": 1, "id": "2669221543", "author": {"loc": null, "kind": "user", "name": "\u8c46\u53cb236971692", "url": "https://www.douban.com/people/236971692/", "reg_time": "2021-04-26 12:30:25", "uri": "douban://douban.com/user/236971692", "avatar_side_icon_id": "", "avatar": "https://img9.doubanio.com/img/files/file-1609845567.png", "id": "236971692", "type": "user", "avatar_side_icon": "", "uid": "236971692"}, "is_collected": false, "subtype": "photo", "type": "photo", "owner_uri": "douban://douban.com/tv/35371695", "status": null, "reaction_type": 0, "description": "", "sharing_url": "https://www.douban.com/doubanapp/dispatch?uri=/photo/2669221543/", "url": "https://movie.douban.com/photos/photo/2669221543/", "reply_limit": "A", "uri": "douban://douban.com/photo/2669221543", "likers_count": 1, "reactions_count": 1, "comments_count": 0, "position": 6}, {"read_count": 159, "image": {"large": {"url": "https://img9.doubanio.com/view/photo/l/public/p2669221521.webp", "width": 1066, "height": 1600, "size": 0}, "raw": null, "small": {"url": "https://img9.doubanio.com/view/photo/s/public/p2669221521.webp", "width": 400, "height": 600, "size": 0}, "normal": {"url": "https://img9.doubanio.com/view/photo/m/public/p2669221521.webp", "width": 400, "height": 600, "size": 0}, "is_animated": false}, "create_time": "2021-07-09 21:55:17", "collections_count": 0, "reshares_count": 0, "id": "2669221521", "author": {"loc": null, "kind": "user", "name": "\u8c46\u53cb236971692", "url": "https://www.douban.com/people/236971692/", "reg_time": "2021-04-26 12:30:25", "uri": "douban://douban.com/user/236971692", "avatar_side_icon_id": "", "avatar": "https://img9.doubanio.com/img/files/file-1609845567.png", "id": "236971692", "type": "user", "avatar_side_icon": "", "uid": "236971692"}, "is_collected": false, "subtype": "photo", "type": "photo", "owner_uri": "douban://douban.com/tv/35371695", "status": null, "reaction_type": 0, "description": "", "sharing_url": "https://www.douban.com/doubanapp/dispatch?uri=/photo/2669221521/", "url": "https://movie.douban.com/photos/photo/2669221521/", "reply_limit": "A", "uri": "douban://douban.com/photo/2669221521", "likers_count": 3, "reactions_count": 3, "comments_count": 0, "position": 64}, {"read_count": 81, "image": {"large": {"url": "https://img9.doubanio.com/view/photo/l/public/p2872962874.webp", "width": 1600, "height": 1066, "size": 0}, "raw": null, "small": {"url": "https://img9.doubanio.com/view/photo/s/public/p2872962874.webp", "width": 600, "height": 400, "size": 0}, "normal": {"url": "https://img9.doubanio.com/view/photo/m/public/p2872962874.webp", "width": 600, "height": 400, "size": 0}, "is_animated": false}, "create_time": "2022-05-13 12:46:37", "collections_count": 0, "reshares_count": 0, "id": "2872962874", "author": {"loc": null, "kind": "user", "name": "\u8c46\u53cb254021938", "url": "https://www.douban.com/people/254021938/", "reg_time": "2022-02-14 16:31:00", "uri": "douban://douban.com/user/254021938", "avatar_side_icon_id": "", "avatar": "https://img9.doubanio.com/img/files/file-1609845567.png", "id": "254021938", "type": "user", "avatar_side_icon": "", "uid": "254021938"}, "is_collected": false, "subtype": "photo", "type": "photo", "owner_uri": "douban://douban.com/tv/35371695", "status": null, "reaction_type": 0, "description": "", "sharing_url": "https://www.douban.com/doubanapp/dispatch?uri=/photo/2872962874/", "url": "https://movie.douban.com/photos/photo/2872962874/", "reply_limit": "A", "uri": "douban://douban.com/photo/2872962874", "likers_count": 1, "reactions_count": 1, "comments_count": 0, "position": 10}, {"read_count": 77, "image": {"large": {"url": "https://img9.doubanio.com/view/photo/l/public/p2665998702.webp", "width": 1600, "height": 1067, "size": 0}, "raw": null, "small": {"url": "https://img9.doubanio.com/view/photo/s/public/p2665998702.webp", "width": 600, "height": 400, "size": 0}, "normal": {"url": "https://img9.doubanio.com/view/photo/m/public/p2665998702.webp", "width": 600, "height": 400, "size": 0}, "is_animated": false}, "create_time": "2021-06-30 17:08:37", "collections_count": 0, "reshares_count": 0, "id": "2665998702", "author": {"loc": {"id": "108296", "name": "\u4e0a\u6d77", "uid": "shanghai"}, "kind": "user", "name": "six-up", "url": "https://www.douban.com/people/228811628/", "reg_time": "2020-12-22 22:48:12", "uri": "douban://douban.com/user/228811628", "avatar_side_icon_id": "", "avatar": "https://img9.doubanio.com/icon/up228811628-2.jpg", "id": "228811628", "type": "user", "avatar_side_icon": "", "uid": "228811628"}, "is_collected": false, "subtype": "photo", "type": "photo", "owner_uri": "douban://douban.com/tv/35371695", "status": null, "reaction_type": 0, "description": "", "sharing_url": "https://www.douban.com/doubanapp/dispatch?uri=/photo/2665998702/", "url": "https://movie.douban.com/photos/photo/2665998702/", "reply_limit": "A", "uri": "douban://douban.com/photo/2665998702", "likers_count": 2, "reactions_count": 2, "comments_count": 0, "position": 74}, {"read_count": 57, "image": {"large": {"url": "https://img9.doubanio.com/view/photo/l/public/p2873361894.webp", "width": 1600, "height": 1066, "size": 0}, "raw": null, "small": {"url": "https://img9.doubanio.com/view/photo/s/public/p2873361894.webp", "width": 600, "height": 400, "size": 0}, "normal": {"url": "https://img9.doubanio.com/view/photo/m/public/p2873361894.webp", "width": 600, "height": 400, "size": 0}, "is_animated": false}, "create_time": "2022-05-21 13:32:57", "collections_count": 0, "reshares_count": 0, "id": "2873361894", "author": {"loc": null, "kind": "user", "name": "\u8c46\u53cb254021938", "url": "https://www.douban.com/people/254021938/", "reg_time": "2022-02-14 16:31:00", "uri": "douban://douban.com/user/254021938", "avatar_side_icon_id": "", "avatar": "https://img9.doubanio.com/img/files/file-1609845567.png", "id": "254021938", "type": "user", "avatar_side_icon": "", "uid": "254021938"}, "is_collected": false, "subtype": "photo", "type": "photo", "owner_uri": "douban://douban.com/tv/35371695", "status": null, "reaction_type": 0, "description": "", "sharing_url": "https://www.douban.com/doubanapp/dispatch?uri=/photo/2873361894/", "url": "https://movie.douban.com/photos/photo/2873361894/", "reply_limit": "A", "uri": "douban://douban.com/photo/2873361894", "likers_count": 1, "reactions_count": 1, "comments_count": 0, "position": 13}, {"read_count": 79, "image": {"large": {"url": "https://img9.doubanio.com/view/photo/l/public/p2873361889.webp", "width": 1600, "height": 1064, "size": 0}, "raw": null, "small": {"url": "https://img9.doubanio.com/view/photo/s/public/p2873361889.webp", "width": 600, "height": 399, "size": 0}, "normal": {"url": "https://img9.doubanio.com/view/photo/m/public/p2873361889.webp", "width": 600, "height": 399, "size": 0}, "is_animated": false}, "create_time": "2022-05-21 13:32:53", "collections_count": 0, "reshares_count": 0, "id": "2873361889", "author": {"loc": null, "kind": "user", "name": "\u8c46\u53cb254021938", "url": "https://www.douban.com/people/254021938/", "reg_time": "2022-02-14 16:31:00", "uri": "douban://douban.com/user/254021938", "avatar_side_icon_id": "", "avatar": "https://img9.doubanio.com/img/files/file-1609845567.png", "id": "254021938", "type": "user", "avatar_side_icon": "", "uid": "254021938"}, "is_collected": false, "subtype": "photo", "type": "photo", "owner_uri": "douban://douban.com/tv/35371695", "status": null, "reaction_type": 0, "description": "", "sharing_url": "https://www.douban.com/doubanapp/dispatch?uri=/photo/2873361889/", "url": "https://movie.douban.com/photos/photo/2873361889/", "reply_limit": "A", "uri": "douban://douban.com/photo/2873361889", "likers_count": 1, "reactions_count": 1, "comments_count": 0, "position": 17}, {"read_count": 64, "image": {"large": {"url": "https://img9.doubanio.com/view/photo/l/public/p2873274196.webp", "width": 1067, "height": 1600, "size": 0}, "raw": null, "small": {"url": "https://img9.doubanio.com/view/photo/s/public/p2873274196.webp", "width": 400, "height": 600, "size": 0}, "normal": {"url": "https://img9.doubanio.com/view/photo/m/public/p2873274196.webp", "width": 400, "height": 600, "size": 0}, "is_animated": false}, "create_time": "2022-05-19 16:33:13", "collections_count": 0, "reshares_count": 0, "id": "2873274196", "author": {"loc": null, "kind": "user", "name": "\u8c46\u53cb254021938", "url": "https://www.douban.com/people/254021938/", "reg_time": "2022-02-14 16:31:00", "uri": "douban://douban.com/user/254021938", "avatar_side_icon_id": "", "avatar": "https://img9.doubanio.com/img/files/file-1609845567.png", "id": "254021938", "type": "user", "avatar_side_icon": "", "uid": "254021938"}, "is_collected": false, "subtype": "photo", "type": "photo", "owner_uri": "douban://douban.com/tv/35371695", "status": null, "reaction_type": 0, "description": "", "sharing_url": "https://www.douban.com/doubanapp/dispatch?uri=/photo/2873274196/", "url": "https://movie.douban.com/photos/photo/2873274196/", "reply_limit": "A", "uri": "douban://douban.com/photo/2873274196", "likers_count": 1, "reactions_count": 1, "comments_count": 0, "position": 23}, {"read_count": 55, "image": {"large": {"url": "https://img9.doubanio.com/view/photo/l/public/p2873274191.webp", "width": 1067, "height": 1600, "size": 0}, "raw": null, "small": {"url": "https://img9.doubanio.com/view/photo/s/public/p2873274191.webp", "width": 400, "height": 600, "size": 0}, "normal": {"url": "https://img9.doubanio.com/view/photo/m/public/p2873274191.webp", "width": 400, "height": 600, "size": 0}, "is_animated": false}, "create_time": "2022-05-19 16:32:57", "collections_count": 0, "reshares_count": 0, "id": "2873274191", "author": {"loc": null, "kind": "user", "name": "\u8c46\u53cb254021938", "url": "https://www.douban.com/people/254021938/", "reg_time": "2022-02-14 16:31:00", "uri": "douban://douban.com/user/254021938", "avatar_side_icon_id": "", "avatar": "https://img9.doubanio.com/img/files/file-1609845567.png", "id": "254021938", "type": "user", "avatar_side_icon": "", "uid": "254021938"}, "is_collected": false, "subtype": "photo", "type": "photo", "owner_uri": "douban://douban.com/tv/35371695", "status": null, "reaction_type": 0, "description": "", "sharing_url": "https://www.douban.com/doubanapp/dispatch?uri=/photo/2873274191/", "url": "https://movie.douban.com/photos/photo/2873274191/", "reply_limit": "A", "uri": "douban://douban.com/photo/2873274191", "likers_count": 1, "reactions_count": 1, "comments_count": 0, "position": 24}, {"read_count": 54, "image": {"large": {"url": "https://img9.doubanio.com/view/photo/l/public/p2873274189.webp", "width": 1067, "height": 1600, "size": 0}, "raw": null, "small": {"url": "https://img9.doubanio.com/view/photo/s/public/p2873274189.webp", "width": 400, "height": 600, "size": 0}, "normal": {"url": "https://img9.doubanio.com/view/photo/m/public/p2873274189.webp", "width": 400, "height": 600, "size": 0}, "is_animated": false}, "create_time": "2022-05-19 16:32:57", "collections_count": 0, "reshares_count": 0, "id": "2873274189", "author": {"loc": null, "kind": "user", "name": "\u8c46\u53cb254021938", "url": "https://www.douban.com/people/254021938/", "reg_time": "2022-02-14 16:31:00", "uri": "douban://douban.com/user/254021938", "avatar_side_icon_id": "", "avatar": "https://img9.doubanio.com/img/files/file-1609845567.png", "id": "254021938", "type": "user", "avatar_side_icon": "", "uid": "254021938"}, "is_collected": false, "subtype": "photo", "type": "photo", "owner_uri": "douban://douban.com/tv/35371695", "status": null, "reaction_type": 0, "description": "", "sharing_url": "https://www.douban.com/doubanapp/dispatch?uri=/photo/2873274189/", "url": "https://movie.douban.com/photos/photo/2873274189/", "reply_limit": "A", "uri": "douban://douban.com/photo/2873274189", "likers_count": 1, "reactions_count": 1, "comments_count": 0, "position": 26}, {"read_count": 70, "image": {"large": {"url": "https://img9.doubanio.com/view/photo/l/public/p2873128947.webp", "width": 1600, "height": 1067, "size": 0}, "raw": null, "small": {"url": "https://img9.doubanio.com/view/photo/s/public/p2873128947.webp", "width": 600, "height": 400, "size": 0}, "normal": {"url": "https://img9.doubanio.com/view/photo/m/public/p2873128947.webp", "width": 600, "height": 400, "size": 0}, "is_animated": false}, "create_time": "2022-05-16 16:18:39", "collections_count": 0, "reshares_count": 0, "id": "2873128947", "author": {"loc": null, "kind": "user", "name": "\u8c46\u53cb254021938", "url": "https://www.douban.com/people/254021938/", "reg_time": "2022-02-14 16:31:00", "uri": "douban://douban.com/user/254021938", "avatar_side_icon_id": "", "avatar": "https://img9.doubanio.com/img/files/file-1609845567.png", "id": "254021938", "type": "user", "avatar_side_icon": "", "uid": "254021938"}, "is_collected": false, "subtype": "photo", "type": "photo", "owner_uri": "douban://douban.com/tv/35371695", "status": null, "reaction_type": 0, "description": "", "sharing_url": "https://www.douban.com/doubanapp/dispatch?uri=/photo/2873128947/", "url": "https://movie.douban.com/photos/photo/2873128947/", "reply_limit": "A", "uri": "douban://douban.com/photo/2873128947", "likers_count": 0, "reactions_count": 0, "comments_count": 0, "position": 7}, {"read_count": 68, "image": {"large": {"url": "https://img9.doubanio.com/view/photo/l/public/p2873128946.webp", "width": 1600, "height": 1067, "size": 0}, "raw": null, "small": {"url": "https://img9.doubanio.com/view/photo/s/public/p2873128946.webp", "width": 600, "height": 400, "size": 0}, "normal": {"url": "https://img9.doubanio.com/view/photo/m/public/p2873128946.webp", "width": 600, "height": 400, "size": 0}, "is_animated": false}, "create_time": "2022-05-16 16:18:35", "collections_count": 0, "reshares_count": 0, "id": "2873128946", "author": {"loc": null, "kind": "user", "name": "\u8c46\u53cb254021938", "url": "https://www.douban.com/people/254021938/", "reg_time": "2022-02-14 16:31:00", "uri": "douban://douban.com/user/254021938", "avatar_side_icon_id": "", "avatar": "https://img9.doubanio.com/img/files/file-1609845567.png", "id": "254021938", "type": "user", "avatar_side_icon": "", "uid": "254021938"}, "is_collected": false, "subtype": "photo", "type": "photo", "owner_uri": "douban://douban.com/tv/35371695", "status": null, "reaction_type": 0, "description": "", "sharing_url": "https://www.douban.com/doubanapp/dispatch?uri=/photo/2873128946/", "url": "https://movie.douban.com/photos/photo/2873128946/", "reply_limit": "A", "uri": "douban://douban.com/photo/2873128946", "likers_count": 0, "reactions_count": 0, "comments_count": 0, "position": 8}, {"read_count": 53, "image": {"large": {"url": "https://img9.doubanio.com/view/photo/l/public/p2872962976.webp", "width": 1600, "height": 1067, "size": 0}, "raw": null, "small": {"url": "https://img9.doubanio.com/view/photo/s/public/p2872962976.webp", "width": 600, "height": 400, "size": 0}, "normal": {"url": "https://img9.doubanio.com/view/photo/m/public/p2872962976.webp", "width": 600, "height": 400, "size": 0}, "is_animated": false}, "create_time": "2022-05-13 12:47:45", "collections_count": 0, "reshares_count": 0, "id": "2872962976", "author": {"loc": null, "kind": "user", "name": "\u8c46\u53cb254021938", "url": "https://www.douban.com/people/254021938/", "reg_time": "2022-02-14 16:31:00", "uri": "douban://douban.com/user/254021938", "avatar_side_icon_id": "", "avatar": "https://img9.doubanio.com/img/files/file-1609845567.png", "id": "254021938", "type": "user", "avatar_side_icon": "", "uid": "254021938"}, "is_collected": false, "subtype": "photo", "type": "photo", "owner_uri": "douban://douban.com/tv/35371695", "status": null, "reaction_type": 0, "description": "", "sharing_url": "https://www.douban.com/doubanapp/dispatch?uri=/photo/2872962976/", "url": "https://movie.douban.com/photos/photo/2872962976/", "reply_limit": "A", "uri": "douban://douban.com/photo/2872962976", "likers_count": 1, "reactions_count": 1, "comments_count": 0, "position": 53}, {"read_count": 90, "image": {"large": {"url": "https://img9.doubanio.com/view/photo/l/public/p2872962905.webp", "width": 1600, "height": 1066, "size": 0}, "raw": null, "small": {"url": "https://img9.doubanio.com/view/photo/s/public/p2872962905.webp", "width": 600, "height": 400, "size": 0}, "normal": {"url": "https://img9.doubanio.com/view/photo/m/public/p2872962905.webp", "width": 600, "height": 400, "size": 0}, "is_animated": false}, "create_time": "2022-05-13 12:46:45", "collections_count": 0, "reshares_count": 0, "id": "2872962905", "author": {"loc": null, "kind": "user", "name": "\u8c46\u53cb254021938", "url": "https://www.douban.com/people/254021938/", "reg_time": "2022-02-14 16:31:00", "uri": "douban://douban.com/user/254021938", "avatar_side_icon_id": "", "avatar": "https://img9.doubanio.com/img/files/file-1609845567.png", "id": "254021938", "type": "user", "avatar_side_icon": "", "uid": "254021938"}, "is_collected": false, "subtype": "photo", "type": "photo", "owner_uri": "douban://douban.com/tv/35371695", "status": null, "reaction_type": 0, "description": "", "sharing_url": "https://www.douban.com/doubanapp/dispatch?uri=/photo/2872962905/", "url": "https://movie.douban.com/photos/photo/2872962905/", "reply_limit": "A", "uri": "douban://douban.com/photo/2872962905", "likers_count": 0, "reactions_count": 0, "comments_count": 0, "position": 9}, {"read_count": 95, "image": {"large": {"url": "https://img9.doubanio.com/view/photo/l/public/p2665998701.webp", "width": 1600, "height": 1067, "size": 0}, "raw": null, "small": {"url": "https://img9.doubanio.com/view/photo/s/public/p2665998701.webp", "width": 600, "height": 400, "size": 0}, "normal": {"url": "https://img9.doubanio.com/view/photo/m/public/p2665998701.webp", "width": 600, "height": 400, "size": 0}, "is_animated": false}, "create_time": "2021-06-30 17:08:37", "collections_count": 1, "reshares_count": 0, "id": "2665998701", "author": {"loc": {"id": "108296", "name": "\u4e0a\u6d77", "uid": "shanghai"}, "kind": "user", "name": "six-up", "url": "https://www.douban.com/people/228811628/", "reg_time": "2020-12-22 22:48:12", "uri": "douban://douban.com/user/228811628", "avatar_side_icon_id": "", "avatar": "https://img9.doubanio.com/icon/up228811628-2.jpg", "id": "228811628", "type": "user", "avatar_side_icon": "", "uid": "228811628"}, "is_collected": false, "subtype": "photo", "type": "photo", "owner_uri": "douban://douban.com/tv/35371695", "status": null, "reaction_type": 0, "description": "", "sharing_url": "https://www.douban.com/doubanapp/dispatch?uri=/photo/2665998701/", "url": "https://movie.douban.com/photos/photo/2665998701/", "reply_limit": "A", "uri": "douban://douban.com/photo/2665998701", "likers_count": 1, "reactions_count": 1, "comments_count": 0, "position": 75}, {"read_count": 87, "image": {"large": {"url": "https://img9.doubanio.com/view/photo/l/public/p2665998697.webp", "width": 1067, "height": 1600, "size": 0}, "raw": null, "small": {"url": "https://img9.doubanio.com/view/photo/s/public/p2665998697.webp", "width": 400, "height": 600, "size": 0}, "normal": {"url": "https://img9.doubanio.com/view/photo/m/public/p2665998697.webp", "width": 400, "height": 600, "size": 0}, "is_animated": false}, "create_time": "2021-06-30 17:08:35", "collections_count": 0, "reshares_count": 0, "id": "2665998697", "author": {"loc": {"id": "108296", "name": "\u4e0a\u6d77", "uid": "shanghai"}, "kind": "user", "name": "six-up", "url": "https://www.douban.com/people/228811628/", "reg_time": "2020-12-22 22:48:12", "uri": "douban://douban.com/user/228811628", "avatar_side_icon_id": "", "avatar": "https://img9.doubanio.com/icon/up228811628-2.jpg", "id": "228811628", "type": "user", "avatar_side_icon": "", "uid": "228811628"}, "is_collected": false, "subtype": "photo", "type": "photo", "owner_uri": "douban://douban.com/tv/35371695", "status": null, "reaction_type": 0, "description": "", "sharing_url": "https://www.douban.com/doubanapp/dispatch?uri=/photo/2665998697/", "url": "https://movie.douban.com/photos/photo/2665998697/", "reply_limit": "A", "uri": "douban://douban.com/photo/2665998697", "likers_count": 1, "reactions_count": 1, "comments_count": 1, "position": 77}, {"read_count": 66, "image": {"large": {"url": "https://img9.doubanio.com/view/photo/l/public/p2873361900.webp", "width": 1600, "height": 1067, "size": 0}, "raw": null, "small": {"url": "https://img9.doubanio.com/view/photo/s/public/p2873361900.webp", "width": 600, "height": 400, "size": 0}, "normal": {"url": "https://img9.doubanio.com/view/photo/m/public/p2873361900.webp", "width": 600, "height": 400, "size": 0}, "is_animated": false}, "create_time": "2022-05-21 13:33:04", "collections_count": 0, "reshares_count": 0, "id": "2873361900", "author": {"loc": null, "kind": "user", "name": "\u8c46\u53cb254021938", "url": "https://www.douban.com/people/254021938/", "reg_time": "2022-02-14 16:31:00", "uri": "douban://douban.com/user/254021938", "avatar_side_icon_id": "", "avatar": "https://img9.doubanio.com/img/files/file-1609845567.png", "id": "254021938", "type": "user", "avatar_side_icon": "", "uid": "254021938"}, "is_collected": false, "subtype": "photo", "type": "photo", "owner_uri": "douban://douban.com/tv/35371695", "status": null, "reaction_type": 0, "description": "", "sharing_url": "https://www.douban.com/doubanapp/dispatch?uri=/photo/2873361900/", "url": "https://movie.douban.com/photos/photo/2873361900/", "reply_limit": "A", "uri": "douban://douban.com/photo/2873361900", "likers_count": 0, "reactions_count": 0, "comments_count": 0, "position": 12}, {"read_count": 24, "image": {"large": {"url": "https://img9.doubanio.com/view/photo/l/public/p2873361893.webp", "width": 1600, "height": 899, "size": 0}, "raw": null, "small": {"url": "https://img9.doubanio.com/view/photo/s/public/p2873361893.webp", "width": 600, "height": 337, "size": 0}, "normal": {"url": "https://img9.doubanio.com/view/photo/m/public/p2873361893.webp", "width": 600, "height": 337, "size": 0}, "is_animated": false}, "create_time": "2022-05-21 13:32:53", "collections_count": 0, "reshares_count": 0, "id": "2873361893", "author": {"loc": null, "kind": "user", "name": "\u8c46\u53cb254021938", "url": "https://www.douban.com/people/254021938/", "reg_time": "2022-02-14 16:31:00", "uri": "douban://douban.com/user/254021938", "avatar_side_icon_id": "", "avatar": "https://img9.doubanio.com/img/files/file-1609845567.png", "id": "254021938", "type": "user", "avatar_side_icon": "", "uid": "254021938"}, "is_collected": false, "subtype": "photo", "type": "photo", "owner_uri": "douban://douban.com/tv/35371695", "status": null, "reaction_type": 0, "description": "", "sharing_url": "https://www.douban.com/doubanapp/dispatch?uri=/photo/2873361893/", "url": "https://movie.douban.com/photos/photo/2873361893/", "reply_limit": "A", "uri": "douban://douban.com/photo/2873361893", "likers_count": 0, "reactions_count": 0, "comments_count": 0, "position": 14}, {"read_count": 19, "image": {"large": {"url": "https://img9.doubanio.com/view/photo/l/public/p2873361892.webp", "width": 1600, "height": 901, "size": 0}, "raw": null, "small": {"url": "https://img9.doubanio.com/view/photo/s/public/p2873361892.webp", "width": 600, "height": 338, "size": 0}, "normal": {"url": "https://img9.doubanio.com/view/photo/m/public/p2873361892.webp", "width": 600, "height": 338, "size": 0}, "is_animated": false}, "create_time": "2022-05-21 13:32:53", "collections_count": 0, "reshares_count": 0, "id": "2873361892", "author": {"loc": null, "kind": "user", "name": "\u8c46\u53cb254021938", "url": "https://www.douban.com/people/254021938/", "reg_time": "2022-02-14 16:31:00", "uri": "douban://douban.com/user/254021938", "avatar_side_icon_id": "", "avatar": "https://img9.doubanio.com/img/files/file-1609845567.png", "id": "254021938", "type": "user", "avatar_side_icon": "", "uid": "254021938"}, "is_collected": false, "subtype": "photo", "type": "photo", "owner_uri": "douban://douban.com/tv/35371695", "status": null, "reaction_type": 0, "description": "", "sharing_url": "https://www.douban.com/doubanapp/dispatch?uri=/photo/2873361892/", "url": "https://movie.douban.com/photos/photo/2873361892/", "reply_limit": "A", "uri": "douban://douban.com/photo/2873361892", "likers_count": 0, "reactions_count": 0, "comments_count": 0, "position": 15}, {"read_count": 61, "image": {"large": {"url": "https://img9.doubanio.com/view/photo/l/public/p2873361891.webp", "width": 1600, "height": 901, "size": 0}, "raw": null, "small": {"url": "https://img9.doubanio.com/view/photo/s/public/p2873361891.webp", "width": 600, "height": 338, "size": 0}, "normal": {"url": "https://img9.doubanio.com/view/photo/m/public/p2873361891.webp", "width": 600, "height": 338, "size": 0}, "is_animated": false}, "create_time": "2022-05-21 13:32:53", "collections_count": 0, "reshares_count": 0, "id": "2873361891", "author": {"loc": null, "kind": "user", "name": "\u8c46\u53cb254021938", "url": "https://www.douban.com/people/254021938/", "reg_time": "2022-02-14 16:31:00", "uri": "douban://douban.com/user/254021938", "avatar_side_icon_id": "", "avatar": "https://img9.doubanio.com/img/files/file-1609845567.png", "id": "254021938", "type": "user", "avatar_side_icon": "", "uid": "254021938"}, "is_collected": false, "subtype": "photo", "type": "photo", "owner_uri": "douban://douban.com/tv/35371695", "status": null, "reaction_type": 0, "description": "", "sharing_url": "https://www.douban.com/doubanapp/dispatch?uri=/photo/2873361891/", "url": "https://movie.douban.com/photos/photo/2873361891/", "reply_limit": "A", "uri": "douban://douban.com/photo/2873361891", "likers_count": 0, "reactions_count": 0, "comments_count": 0, "position": 16}, {"read_count": 64, "image": {"large": {"url": "https://img9.doubanio.com/view/photo/l/public/p2873361888.webp", "width": 1600, "height": 1066, "size": 0}, "raw": null, "small": {"url": "https://img9.doubanio.com/view/photo/s/public/p2873361888.webp", "width": 600, "height": 400, "size": 0}, "normal": {"url": "https://img9.doubanio.com/view/photo/m/public/p2873361888.webp", "width": 600, "height": 400, "size": 0}, "is_animated": false}, "create_time": "2022-05-21 13:32:53", "collections_count": 0, "reshares_count": 0, "id": "2873361888", "author": {"loc": null, "kind": "user", "name": "\u8c46\u53cb254021938", "url": "https://www.douban.com/people/254021938/", "reg_time": "2022-02-14 16:31:00", "uri": "douban://douban.com/user/254021938", "avatar_side_icon_id": "", "avatar": "https://img9.doubanio.com/img/files/file-1609845567.png", "id": "254021938", "type": "user", "avatar_side_icon": "", "uid": "254021938"}, "is_collected": false, "subtype": "photo", "type": "photo", "owner_uri": "douban://douban.com/tv/35371695", "status": null, "reaction_type": 0, "description": "", "sharing_url": "https://www.douban.com/doubanapp/dispatch?uri=/photo/2873361888/", "url": "https://movie.douban.com/photos/photo/2873361888/", "reply_limit": "A", "uri": "douban://douban.com/photo/2873361888", "likers_count": 0, "reactions_count": 0, "comments_count": 0, "position": 18}, {"read_count": 43, "image": {"large": {"url": "https://img9.doubanio.com/view/photo/l/public/p2873361887.webp", "width": 1600, "height": 1066, "size": 0}, "raw": null, "small": {"url": "https://img9.doubanio.com/view/photo/s/public/p2873361887.webp", "width": 600, "height": 400, "size": 0}, "normal": {"url": "https://img9.doubanio.com/view/photo/m/public/p2873361887.webp", "width": 600, "height": 400, "size": 0}, "is_animated": false}, "create_time": "2022-05-21 13:32:52", "collections_count": 0, "reshares_count": 0, "id": "2873361887", "author": {"loc": null, "kind": "user", "name": "\u8c46\u53cb254021938", "url": "https://www.douban.com/people/254021938/", "reg_time": "2022-02-14 16:31:00", "uri": "douban://douban.com/user/254021938", "avatar_side_icon_id": "", "avatar": "https://img9.doubanio.com/img/files/file-1609845567.png", "id": "254021938", "type": "user", "avatar_side_icon": "", "uid": "254021938"}, "is_collected": false, "subtype": "photo", "type": "photo", "owner_uri": "douban://douban.com/tv/35371695", "status": null, "reaction_type": 0, "description": "", "sharing_url": "https://www.douban.com/doubanapp/dispatch?uri=/photo/2873361887/", "url": "https://movie.douban.com/photos/photo/2873361887/", "reply_limit": "A", "uri": "douban://douban.com/photo/2873361887", "likers_count": 0, "reactions_count": 0, "comments_count": 0, "position": 19}, {"read_count": 20, "image": {"large": {"url": "https://img9.doubanio.com/view/photo/l/public/p2873361886.webp", "width": 1600, "height": 901, "size": 0}, "raw": null, "small": {"url": "https://img9.doubanio.com/view/photo/s/public/p2873361886.webp", "width": 600, "height": 338, "size": 0}, "normal": {"url": "https://img9.doubanio.com/view/photo/m/public/p2873361886.webp", "width": 600, "height": 338, "size": 0}, "is_animated": false}, "create_time": "2022-05-21 13:32:52", "collections_count": 0, "reshares_count": 0, "id": "2873361886", "author": {"loc": null, "kind": "user", "name": "\u8c46\u53cb254021938", "url": "https://www.douban.com/people/254021938/", "reg_time": "2022-02-14 16:31:00", "uri": "douban://douban.com/user/254021938", "avatar_side_icon_id": "", "avatar": "https://img9.doubanio.com/img/files/file-1609845567.png", "id": "254021938", "type": "user", "avatar_side_icon": "", "uid": "254021938"}, "is_collected": false, "subtype": "photo", "type": "photo", "owner_uri": "douban://douban.com/tv/35371695", "status": null, "reaction_type": 0, "description": "", "sharing_url": "https://www.douban.com/doubanapp/dispatch?uri=/photo/2873361886/", "url": "https://movie.douban.com/photos/photo/2873361886/", "reply_limit": "A", "uri": "douban://douban.com/photo/2873361886", "likers_count": 0, "reactions_count": 0, "comments_count": 0, "position": 20}, {"read_count": 54, "image": {"large": {"url": "https://img9.doubanio.com/view/photo/l/public/p2873274198.webp", "width": 1600, "height": 1067, "size": 0}, "raw": null, "small": {"url": "https://img9.doubanio.com/view/photo/s/public/p2873274198.webp", "width": 600, "height": 400, "size": 0}, "normal": {"url": "https://img9.doubanio.com/view/photo/m/public/p2873274198.webp", "width": 600, "height": 400, "size": 0}, "is_animated": false}, "create_time": "2022-05-19 16:33:14", "collections_count": 0, "reshares_count": 0, "id": "2873274198", "author": {"loc": null, "kind": "user", "name": "\u8c46\u53cb254021938", "url": "https://www.douban.com/people/254021938/", "reg_time": "2022-02-14 16:31:00", "uri": "douban://douban.com/user/254021938", "avatar_side_icon_id": "", "avatar": "https://img9.doubanio.com/img/files/file-1609845567.png", "id": "254021938", "type": "user", "avatar_side_icon": "", "uid": "254021938"}, "is_collected": false, "subtype": "photo", "type": "photo", "owner_uri": "douban://douban.com/tv/35371695", "status": null, "reaction_type": 0, "description": "", "sharing_url": "https://www.douban.com/doubanapp/dispatch?uri=/photo/2873274198/", "url": "https://movie.douban.com/photos/photo/2873274198/", "reply_limit": "A", "uri": "douban://douban.com/photo/2873274198", "likers_count": 0, "reactions_count": 0, "comments_count": 0, "position": 21}, {"read_count": 34, "image": {"large": {"url": "https://img9.doubanio.com/view/photo/l/public/p2873274197.webp", "width": 1067, "height": 1600, "size": 0}, "raw": null, "small": {"url": "https://img9.doubanio.com/view/photo/s/public/p2873274197.webp", "width": 400, "height": 600, "size": 0}, "normal": {"url": "https://img9.doubanio.com/view/photo/m/public/p2873274197.webp", "width": 400, "height": 600, "size": 0}, "is_animated": false}, "create_time": "2022-05-19 16:33:14", "collections_count": 0, "reshares_count": 0, "id": "2873274197", "author": {"loc": null, "kind": "user", "name": "\u8c46\u53cb254021938", "url": "https://www.douban.com/people/254021938/", "reg_time": "2022-02-14 16:31:00", "uri": "douban://douban.com/user/254021938", "avatar_side_icon_id": "", "avatar": "https://img9.doubanio.com/img/files/file-1609845567.png", "id": "254021938", "type": "user", "avatar_side_icon": "", "uid": "254021938"}, "is_collected": false, "subtype": "photo", "type": "photo", "owner_uri": "douban://douban.com/tv/35371695", "status": null, "reaction_type": 0, "description": "", "sharing_url": "https://www.douban.com/doubanapp/dispatch?uri=/photo/2873274197/", "url": "https://movie.douban.com/photos/photo/2873274197/", "reply_limit": "A", "uri": "douban://douban.com/photo/2873274197", "likers_count": 0, "reactions_count": 0, "comments_count": 0, "position": 22}, {"read_count": 47, "image": {"large": {"url": "https://img9.doubanio.com/view/photo/l/public/p2873274190.webp", "width": 1067, "height": 1600, "size": 0}, "raw": null, "small": {"url": "https://img9.doubanio.com/view/photo/s/public/p2873274190.webp", "width": 400, "height": 600, "size": 0}, "normal": {"url": "https://img9.doubanio.com/view/photo/m/public/p2873274190.webp", "width": 400, "height": 600, "size": 0}, "is_animated": false}, "create_time": "2022-05-19 16:32:57", "collections_count": 0, "reshares_count": 0, "id": "2873274190", "author": {"loc": null, "kind": "user", "name": "\u8c46\u53cb254021938", "url": "https://www.douban.com/people/254021938/", "reg_time": "2022-02-14 16:31:00", "uri": "douban://douban.com/user/254021938", "avatar_side_icon_id": "", "avatar": "https://img9.doubanio.com/img/files/file-1609845567.png", "id": "254021938", "type": "user", "avatar_side_icon": "", "uid": "254021938"}, "is_collected": false, "subtype": "photo", "type": "photo", "owner_uri": "douban://douban.com/tv/35371695", "status": null, "reaction_type": 0, "description": "", "sharing_url": "https://www.douban.com/doubanapp/dispatch?uri=/photo/2873274190/", "url": "https://movie.douban.com/photos/photo/2873274190/", "reply_limit": "A", "uri": "douban://douban.com/photo/2873274190", "likers_count": 0, "reactions_count": 0, "comments_count": 0, "position": 25}, {"read_count": 67, "image": {"large": {"url": "https://img9.doubanio.com/view/photo/l/public/p2873274188.webp", "width": 1600, "height": 1067, "size": 0}, "raw": null, "small": {"url": "https://img9.doubanio.com/view/photo/s/public/p2873274188.webp", "width": 600, "height": 400, "size": 0}, "normal": {"url": "https://img9.doubanio.com/view/photo/m/public/p2873274188.webp", "width": 600, "height": 400, "size": 0}, "is_animated": false}, "create_time": "2022-05-19 16:32:57", "collections_count": 0, "reshares_count": 0, "id": "2873274188", "author": {"loc": null, "kind": "user", "name": "\u8c46\u53cb254021938", "url": "https://www.douban.com/people/254021938/", "reg_time": "2022-02-14 16:31:00", "uri": "douban://douban.com/user/254021938", "avatar_side_icon_id": "", "avatar": "https://img9.doubanio.com/img/files/file-1609845567.png", "id": "254021938", "type": "user", "avatar_side_icon": "", "uid": "254021938"}, "is_collected": false, "subtype": "photo", "type": "photo", "owner_uri": "douban://douban.com/tv/35371695", "status": null, "reaction_type": 0, "description": "", "sharing_url": "https://www.douban.com/doubanapp/dispatch?uri=/photo/2873274188/", "url": "https://movie.douban.com/photos/photo/2873274188/", "reply_limit": "A", "uri": "douban://douban.com/photo/2873274188", "likers_count": 0, "reactions_count": 0, "comments_count": 0, "position": 27}, {"read_count": 17, "image": {"large": {"url": "https://img9.doubanio.com/view/photo/l/public/p2873274187.webp", "width": 1600, "height": 1067, "size": 0}, "raw": null, "small": {"url": "https://img9.doubanio.com/view/photo/s/public/p2873274187.webp", "width": 600, "height": 400, "size": 0}, "normal": {"url": "https://img9.doubanio.com/view/photo/m/public/p2873274187.webp", "width": 600, "height": 400, "size": 0}, "is_animated": false}, "create_time": "2022-05-19 16:32:56", "collections_count": 0, "reshares_count": 0, "id": "2873274187", "author": {"loc": null, "kind": "user", "name": "\u8c46\u53cb254021938", "url": "https://www.douban.com/people/254021938/", "reg_time": "2022-02-14 16:31:00", "uri": "douban://douban.com/user/254021938", "avatar_side_icon_id": "", "avatar": "https://img9.doubanio.com/img/files/file-1609845567.png", "id": "254021938", "type": "user", "avatar_side_icon": "", "uid": "254021938"}, "is_collected": false, "subtype": "photo", "type": "photo", "owner_uri": "douban://douban.com/tv/35371695", "status": null, "reaction_type": 0, "description": "", "sharing_url": "https://www.douban.com/doubanapp/dispatch?uri=/photo/2873274187/", "url": "https://movie.douban.com/photos/photo/2873274187/", "reply_limit": "A", "uri": "douban://douban.com/photo/2873274187", "likers_count": 0, "reactions_count": 0, "comments_count": 0, "position": 28}, {"read_count": 11, "image": {"large": {"url": "https://img9.doubanio.com/view/photo/l/public/p2873274186.webp", "width": 1067, "height": 1600, "size": 0}, "raw": null, "small": {"url": "https://img9.doubanio.com/view/photo/s/public/p2873274186.webp", "width": 400, "height": 600, "size": 0}, "normal": {"url": "https://img9.doubanio.com/view/photo/m/public/p2873274186.webp", "width": 400, "height": 600, "size": 0}, "is_animated": false}, "create_time": "2022-05-19 16:32:56", "collections_count": 0, "reshares_count": 0, "id": "2873274186", "author": {"loc": null, "kind": "user", "name": "\u8c46\u53cb254021938", "url": "https://www.douban.com/people/254021938/", "reg_time": "2022-02-14 16:31:00", "uri": "douban://douban.com/user/254021938", "avatar_side_icon_id": "", "avatar": "https://img9.doubanio.com/img/files/file-1609845567.png", "id": "254021938", "type": "user", "avatar_side_icon": "", "uid": "254021938"}, "is_collected": false, "subtype": "photo", "type": "photo", "owner_uri": "douban://douban.com/tv/35371695", "status": null, "reaction_type": 0, "description": "", "sharing_url": "https://www.douban.com/doubanapp/dispatch?uri=/photo/2873274186/", "url": "https://movie.douban.com/photos/photo/2873274186/", "reply_limit": "A", "uri": "douban://douban.com/photo/2873274186", "likers_count": 0, "reactions_count": 0, "comments_count": 0, "position": 29}, {"read_count": 21, "image": {"large": {"url": "https://img9.doubanio.com/view/photo/l/public/p2873128943.webp", "width": 1600, "height": 1067, "size": 0}, "raw": null, "small": {"url": "https://img9.doubanio.com/view/photo/s/public/p2873128943.webp", "width": 600, "height": 400, "size": 0}, "normal": {"url": "https://img9.doubanio.com/view/photo/m/public/p2873128943.webp", "width": 600, "height": 400, "size": 0}, "is_animated": false}, "create_time": "2022-05-16 16:18:33", "collections_count": 0, "reshares_count": 0, "id": "2873128943", "author": {"loc": null, "kind": "user", "name": "\u8c46\u53cb254021938", "url": "https://www.douban.com/people/254021938/", "reg_time": "2022-02-14 16:31:00", "uri": "douban://douban.com/user/254021938", "avatar_side_icon_id": "", "avatar": "https://img9.doubanio.com/img/files/file-1609845567.png", "id": "254021938", "type": "user", "avatar_side_icon": "", "uid": "254021938"}, "is_collected": false, "subtype": "photo", "type": "photo", "owner_uri": "douban://douban.com/tv/35371695", "status": null, "reaction_type": 0, "description": "", "sharing_url": "https://www.douban.com/doubanapp/dispatch?uri=/photo/2873128943/", "url": "https://movie.douban.com/photos/photo/2873128943/", "reply_limit": "A", "uri": "douban://douban.com/photo/2873128943", "likers_count": 0, "reactions_count": 0, "comments_count": 0, "position": 30}, {"read_count": 19, "image": {"large": {"url": "https://img9.doubanio.com/view/photo/l/public/p2873128942.webp", "width": 1600, "height": 1067, "size": 0}, "raw": null, "small": {"url": "https://img9.doubanio.com/view/photo/s/public/p2873128942.webp", "width": 600, "height": 400, "size": 0}, "normal": {"url": "https://img9.doubanio.com/view/photo/m/public/p2873128942.webp", "width": 600, "height": 400, "size": 0}, "is_animated": false}, "create_time": "2022-05-16 16:18:33", "collections_count": 0, "reshares_count": 0, "id": "2873128942", "author": {"loc": null, "kind": "user", "name": "\u8c46\u53cb254021938", "url": "https://www.douban.com/people/254021938/", "reg_time": "2022-02-14 16:31:00", "uri": "douban://douban.com/user/254021938", "avatar_side_icon_id": "", "avatar": "https://img9.doubanio.com/img/files/file-1609845567.png", "id": "254021938", "type": "user", "avatar_side_icon": "", "uid": "254021938"}, "is_collected": false, "subtype": "photo", "type": "photo", "owner_uri": "douban://douban.com/tv/35371695", "status": null, "reaction_type": 0, "description": "", "sharing_url": "https://www.douban.com/doubanapp/dispatch?uri=/photo/2873128942/", "url": "https://movie.douban.com/photos/photo/2873128942/", "reply_limit": "A", "uri": "douban://douban.com/photo/2873128942", "likers_count": 0, "reactions_count": 0, "comments_count": 0, "position": 31}, {"read_count": 8, "image": {"large": {"url": "https://img9.doubanio.com/view/photo/l/public/p2873128941.webp", "width": 1600, "height": 1067, "size": 0}, "raw": null, "small": {"url": "https://img9.doubanio.com/view/photo/s/public/p2873128941.webp", "width": 600, "height": 400, "size": 0}, "normal": {"url": "https://img9.doubanio.com/view/photo/m/public/p2873128941.webp", "width": 600, "height": 400, "size": 0}, "is_animated": false}, "create_time": "2022-05-16 16:18:33", "collections_count": 0, "reshares_count": 0, "id": "2873128941", "author": {"loc": null, "kind": "user", "name": "\u8c46\u53cb254021938", "url": "https://www.douban.com/people/254021938/", "reg_time": "2022-02-14 16:31:00", "uri": "douban://douban.com/user/254021938", "avatar_side_icon_id": "", "avatar": "https://img9.doubanio.com/img/files/file-1609845567.png", "id": "254021938", "type": "user", "avatar_side_icon": "", "uid": "254021938"}, "is_collected": false, "subtype": "photo", "type": "photo", "owner_uri": "douban://douban.com/tv/35371695", "status": null, "reaction_type": 0, "description": "", "sharing_url": "https://www.douban.com/doubanapp/dispatch?uri=/photo/2873128941/", "url": "https://movie.douban.com/photos/photo/2873128941/", "reply_limit": "A", "uri": "douban://douban.com/photo/2873128941", "likers_count": 0, "reactions_count": 0, "comments_count": 0, "position": 32}, {"read_count": 18, "image": {"large": {"url": "https://img9.doubanio.com/view/photo/l/public/p2873128939.webp", "width": 1600, "height": 1067, "size": 0}, "raw": null, "small": {"url": "https://img9.doubanio.com/view/photo/s/public/p2873128939.webp", "width": 600, "height": 400, "size": 0}, "normal": {"url": "https://img9.doubanio.com/view/photo/m/public/p2873128939.webp", "width": 600, "height": 400, "size": 0}, "is_animated": false}, "create_time": "2022-05-16 16:18:33", "collections_count": 0, "reshares_count": 0, "id": "2873128939", "author": {"loc": null, "kind": "user", "name": "\u8c46\u53cb254021938", "url": "https://www.douban.com/people/254021938/", "reg_time": "2022-02-14 16:31:00", "uri": "douban://douban.com/user/254021938", "avatar_side_icon_id": "", "avatar": "https://img9.doubanio.com/img/files/file-1609845567.png", "id": "254021938", "type": "user", "avatar_side_icon": "", "uid": "254021938"}, "is_collected": false, "subtype": "photo", "type": "photo", "owner_uri": "douban://douban.com/tv/35371695", "status": null, "reaction_type": 0, "description": "", "sharing_url": "https://www.douban.com/doubanapp/dispatch?uri=/photo/2873128939/", "url": "https://movie.douban.com/photos/photo/2873128939/", "reply_limit": "A", "uri": "douban://douban.com/photo/2873128939", "likers_count": 0, "reactions_count": 0, "comments_count": 0, "position": 33}, {"read_count": 21, "image": {"large": {"url": "https://img9.doubanio.com/view/photo/l/public/p2873128938.webp", "width": 1600, "height": 1067, "size": 0}, "raw": null, "small": {"url": "https://img9.doubanio.com/view/photo/s/public/p2873128938.webp", "width": 600, "height": 400, "size": 0}, "normal": {"url": "https://img9.doubanio.com/view/photo/m/public/p2873128938.webp", "width": 600, "height": 400, "size": 0}, "is_animated": false}, "create_time": "2022-05-16 16:18:32", "collections_count": 0, "reshares_count": 0, "id": "2873128938", "author": {"loc": null, "kind": "user", "name": "\u8c46\u53cb254021938", "url": "https://www.douban.com/people/254021938/", "reg_time": "2022-02-14 16:31:00", "uri": "douban://douban.com/user/254021938", "avatar_side_icon_id": "", "avatar": "https://img9.doubanio.com/img/files/file-1609845567.png", "id": "254021938", "type": "user", "avatar_side_icon": "", "uid": "254021938"}, "is_collected": false, "subtype": "photo", "type": "photo", "owner_uri": "douban://douban.com/tv/35371695", "status": null, "reaction_type": 0, "description": "", "sharing_url": "https://www.douban.com/doubanapp/dispatch?uri=/photo/2873128938/", "url": "https://movie.douban.com/photos/photo/2873128938/", "reply_limit": "A", "uri": "douban://douban.com/photo/2873128938", "likers_count": 0, "reactions_count": 0, "comments_count": 0, "position": 34}, {"read_count": 21, "image": {"large": {"url": "https://img9.doubanio.com/view/photo/l/public/p2873128935.webp", "width": 1600, "height": 1067, "size": 0}, "raw": null, "small": {"url": "https://img9.doubanio.com/view/photo/s/public/p2873128935.webp", "width": 600, "height": 400, "size": 0}, "normal": {"url": "https://img9.doubanio.com/view/photo/m/public/p2873128935.webp", "width": 600, "height": 400, "size": 0}, "is_animated": false}, "create_time": "2022-05-16 16:18:31", "collections_count": 0, "reshares_count": 0, "id": "2873128935", "author": {"loc": null, "kind": "user", "name": "\u8c46\u53cb254021938", "url": "https://www.douban.com/people/254021938/", "reg_time": "2022-02-14 16:31:00", "uri": "douban://douban.com/user/254021938", "avatar_side_icon_id": "", "avatar": "https://img9.doubanio.com/img/files/file-1609845567.png", "id": "254021938", "type": "user", "avatar_side_icon": "", "uid": "254021938"}, "is_collected": false, "subtype": "photo", "type": "photo", "owner_uri": "douban://douban.com/tv/35371695", "status": null, "reaction_type": 0, "description": "", "sharing_url": "https://www.douban.com/doubanapp/dispatch?uri=/photo/2873128935/", "url": "https://movie.douban.com/photos/photo/2873128935/", "reply_limit": "A", "uri": "douban://douban.com/photo/2873128935", "likers_count": 0, "reactions_count": 0, "comments_count": 0, "position": 35}, {"read_count": 13, "image": {"large": {"url": "https://img9.doubanio.com/view/photo/l/public/p2873128933.webp", "width": 1600, "height": 1067, "size": 0}, "raw": null, "small": {"url": "https://img9.doubanio.com/view/photo/s/public/p2873128933.webp", "width": 600, "height": 400, "size": 0}, "normal": {"url": "https://img9.doubanio.com/view/photo/m/public/p2873128933.webp", "width": 600, "height": 400, "size": 0}, "is_animated": false}, "create_time": "2022-05-16 16:18:23", "collections_count": 0, "reshares_count": 0, "id": "2873128933", "author": {"loc": null, "kind": "user", "name": "\u8c46\u53cb254021938", "url": "https://www.douban.com/people/254021938/", "reg_time": "2022-02-14 16:31:00", "uri": "douban://douban.com/user/254021938", "avatar_side_icon_id": "", "avatar": "https://img9.doubanio.com/img/files/file-1609845567.png", "id": "254021938", "type": "user", "avatar_side_icon": "", "uid": "254021938"}, "is_collected": false, "subtype": "photo", "type": "photo", "owner_uri": "douban://douban.com/tv/35371695", "status": null, "reaction_type": 0, "description": "", "sharing_url": "https://www.douban.com/doubanapp/dispatch?uri=/photo/2873128933/", "url": "https://movie.douban.com/photos/photo/2873128933/", "reply_limit": "A", "uri": "douban://douban.com/photo/2873128933", "likers_count": 0, "reactions_count": 0, "comments_count": 0, "position": 36}, {"read_count": 38, "image": {"large": {"url": "https://img9.doubanio.com/view/photo/l/public/p2873020928.webp", "width": 1600, "height": 861, "size": 0}, "raw": null, "small": {"url": "https://img9.doubanio.com/view/photo/s/public/p2873020928.webp", "width": 600, "height": 323, "size": 0}, "normal": {"url": "https://img9.doubanio.com/view/photo/m/public/p2873020928.webp", "width": 600, "height": 323, "size": 0}, "is_animated": false}, "create_time": "2022-05-14 15:28:50", "collections_count": 0, "reshares_count": 0, "id": "2873020928", "author": {"loc": null, "kind": "user", "name": "\u8c46\u53cb254021938", "url": "https://www.douban.com/people/254021938/", "reg_time": "2022-02-14 16:31:00", "uri": "douban://douban.com/user/254021938", "avatar_side_icon_id": "", "avatar": "https://img9.doubanio.com/img/files/file-1609845567.png", "id": "254021938", "type": "user", "avatar_side_icon": "", "uid": "254021938"}, "is_collected": false, "subtype": "photo", "type": "photo", "owner_uri": "douban://douban.com/tv/35371695", "status": null, "reaction_type": 0, "description": "", "sharing_url": "https://www.douban.com/doubanapp/dispatch?uri=/photo/2873020928/", "url": "https://movie.douban.com/photos/photo/2873020928/", "reply_limit": "A", "uri": "douban://douban.com/photo/2873020928", "likers_count": 0, "reactions_count": 0, "comments_count": 0, "position": 37}, {"read_count": 77, "image": {"large": {"url": "https://img9.doubanio.com/view/photo/l/public/p2873020914.webp", "width": 1600, "height": 872, "size": 0}, "raw": null, "small": {"url": "https://img9.doubanio.com/view/photo/s/public/p2873020914.webp", "width": 600, "height": 327, "size": 0}, "normal": {"url": "https://img9.doubanio.com/view/photo/m/public/p2873020914.webp", "width": 600, "height": 327, "size": 0}, "is_animated": false}, "create_time": "2022-05-14 15:28:43", "collections_count": 0, "reshares_count": 0, "id": "2873020914", "author": {"loc": null, "kind": "user", "name": "\u8c46\u53cb254021938", "url": "https://www.douban.com/people/254021938/", "reg_time": "2022-02-14 16:31:00", "uri": "douban://douban.com/user/254021938", "avatar_side_icon_id": "", "avatar": "https://img9.doubanio.com/img/files/file-1609845567.png", "id": "254021938", "type": "user", "avatar_side_icon": "", "uid": "254021938"}, "is_collected": false, "subtype": "photo", "type": "photo", "owner_uri": "douban://douban.com/tv/35371695", "status": null, "reaction_type": 0, "description": "", "sharing_url": "https://www.douban.com/doubanapp/dispatch?uri=/photo/2873020914/", "url": "https://movie.douban.com/photos/photo/2873020914/", "reply_limit": "A", "uri": "douban://douban.com/photo/2873020914", "likers_count": 0, "reactions_count": 0, "comments_count": 0, "position": 38}, {"read_count": 20, "image": {"large": {"url": "https://img9.doubanio.com/view/photo/l/public/p2873020901.webp", "width": 1600, "height": 874, "size": 0}, "raw": null, "small": {"url": "https://img9.doubanio.com/view/photo/s/public/p2873020901.webp", "width": 600, "height": 327, "size": 0}, "normal": {"url": "https://img9.doubanio.com/view/photo/m/public/p2873020901.webp", "width": 600, "height": 327, "size": 0}, "is_animated": false}, "create_time": "2022-05-14 15:28:36", "collections_count": 0, "reshares_count": 0, "id": "2873020901", "author": {"loc": null, "kind": "user", "name": "\u8c46\u53cb254021938", "url": "https://www.douban.com/people/254021938/", "reg_time": "2022-02-14 16:31:00", "uri": "douban://douban.com/user/254021938", "avatar_side_icon_id": "", "avatar": "https://img9.doubanio.com/img/files/file-1609845567.png", "id": "254021938", "type": "user", "avatar_side_icon": "", "uid": "254021938"}, "is_collected": false, "subtype": "photo", "type": "photo", "owner_uri": "douban://douban.com/tv/35371695", "status": null, "reaction_type": 0, "description": "", "sharing_url": "https://www.douban.com/doubanapp/dispatch?uri=/photo/2873020901/", "url": "https://movie.douban.com/photos/photo/2873020901/", "reply_limit": "A", "uri": "douban://douban.com/photo/2873020901", "likers_count": 0, "reactions_count": 0, "comments_count": 0, "position": 39}, {"read_count": 15, "image": {"large": {"url": "https://img9.doubanio.com/view/photo/l/public/p2873020900.webp", "width": 1600, "height": 872, "size": 0}, "raw": null, "small": {"url": "https://img9.doubanio.com/view/photo/s/public/p2873020900.webp", "width": 600, "height": 327, "size": 0}, "normal": {"url": "https://img9.doubanio.com/view/photo/m/public/p2873020900.webp", "width": 600, "height": 327, "size": 0}, "is_animated": false}, "create_time": "2022-05-14 15:28:36", "collections_count": 0, "reshares_count": 0, "id": "2873020900", "author": {"loc": null, "kind": "user", "name": "\u8c46\u53cb254021938", "url": "https://www.douban.com/people/254021938/", "reg_time": "2022-02-14 16:31:00", "uri": "douban://douban.com/user/254021938", "avatar_side_icon_id": "", "avatar": "https://img9.doubanio.com/img/files/file-1609845567.png", "id": "254021938", "type": "user", "avatar_side_icon": "", "uid": "254021938"}, "is_collected": false, "subtype": "photo", "type": "photo", "owner_uri": "douban://douban.com/tv/35371695", "status": null, "reaction_type": 0, "description": "", "sharing_url": "https://www.douban.com/doubanapp/dispatch?uri=/photo/2873020900/", "url": "https://movie.douban.com/photos/photo/2873020900/", "reply_limit": "A", "uri": "douban://douban.com/photo/2873020900", "likers_count": 0, "reactions_count": 0, "comments_count": 0, "position": 40}, {"read_count": 21, "image": {"large": {"url": "https://img9.doubanio.com/view/photo/l/public/p2873020899.webp", "width": 1600, "height": 861, "size": 0}, "raw": null, "small": {"url": "https://img9.doubanio.com/view/photo/s/public/p2873020899.webp", "width": 600, "height": 323, "size": 0}, "normal": {"url": "https://img9.doubanio.com/view/photo/m/public/p2873020899.webp", "width": 600, "height": 323, "size": 0}, "is_animated": false}, "create_time": "2022-05-14 15:28:36", "collections_count": 0, "reshares_count": 0, "id": "2873020899", "author": {"loc": null, "kind": "user", "name": "\u8c46\u53cb254021938", "url": "https://www.douban.com/people/254021938/", "reg_time": "2022-02-14 16:31:00", "uri": "douban://douban.com/user/254021938", "avatar_side_icon_id": "", "avatar": "https://img9.doubanio.com/img/files/file-1609845567.png", "id": "254021938", "type": "user", "avatar_side_icon": "", "uid": "254021938"}, "is_collected": false, "subtype": "photo", "type": "photo", "owner_uri": "douban://douban.com/tv/35371695", "status": null, "reaction_type": 0, "description": "", "sharing_url": "https://www.douban.com/doubanapp/dispatch?uri=/photo/2873020899/", "url": "https://movie.douban.com/photos/photo/2873020899/", "reply_limit": "A", "uri": "douban://douban.com/photo/2873020899", "likers_count": 0, "reactions_count": 0, "comments_count": 1, "position": 41}, {"read_count": 10, "image": {"large": {"url": "https://img9.doubanio.com/view/photo/l/public/p2873020898.webp", "width": 1600, "height": 861, "size": 0}, "raw": null, "small": {"url": "https://img9.doubanio.com/view/photo/s/public/p2873020898.webp", "width": 600, "height": 323, "size": 0}, "normal": {"url": "https://img9.doubanio.com/view/photo/m/public/p2873020898.webp", "width": 600, "height": 323, "size": 0}, "is_animated": false}, "create_time": "2022-05-14 15:28:36", "collections_count": 0, "reshares_count": 0, "id": "2873020898", "author": {"loc": null, "kind": "user", "name": "\u8c46\u53cb254021938", "url": "https://www.douban.com/people/254021938/", "reg_time": "2022-02-14 16:31:00", "uri": "douban://douban.com/user/254021938", "avatar_side_icon_id": "", "avatar": "https://img9.doubanio.com/img/files/file-1609845567.png", "id": "254021938", "type": "user", "avatar_side_icon": "", "uid": "254021938"}, "is_collected": false, "subtype": "photo", "type": "photo", "owner_uri": "douban://douban.com/tv/35371695", "status": null, "reaction_type": 0, "description": "", "sharing_url": "https://www.douban.com/doubanapp/dispatch?uri=/photo/2873020898/", "url": "https://movie.douban.com/photos/photo/2873020898/", "reply_limit": "A", "uri": "douban://douban.com/photo/2873020898", "likers_count": 0, "reactions_count": 0, "comments_count": 0, "position": 42}, {"read_count": 60, "image": {"large": {"url": "https://img9.doubanio.com/view/photo/l/public/p2872969086.webp", "width": 900, "height": 1600, "size": 0}, "raw": null, "small": {"url": "https://img9.doubanio.com/view/photo/s/public/p2872969086.webp", "width": 337, "height": 600, "size": 0}, "normal": {"url": "https://img9.doubanio.com/view/photo/m/public/p2872969086.webp", "width": 337, "height": 600, "size": 0}, "is_animated": false}, "create_time": "2022-05-13 15:00:39", "collections_count": 0, "reshares_count": 0, "id": "2872969086", "author": {"loc": {"id": "118267", "name": "\u957f\u6c99", "uid": "changsha"}, "kind": "user", "name": "\u98ce\u665a", "url": "https://www.douban.com/people/47848353/", "reg_time": "2010-12-03 22:17:07", "uri": "douban://douban.com/user/47848353", "avatar_side_icon_id": "", "avatar": "https://img9.doubanio.com/img/files/file-1609845567.png", "id": "47848353", "type": "user", "avatar_side_icon": "", "uid": "47848353"}, "is_collected": false, "subtype": "photo", "type": "photo", "owner_uri": "douban://douban.com/tv/35371695", "status": null, "reaction_type": 0, "description": "", "sharing_url": "https://www.douban.com/doubanapp/dispatch?uri=/photo/2872969086/", "url": "https://movie.douban.com/photos/photo/2872969086/", "reply_limit": "A", "uri": "douban://douban.com/photo/2872969086", "likers_count": 0, "reactions_count": 0, "comments_count": 0, "position": 43}, {"read_count": 37, "image": {"large": {"url": "https://img9.doubanio.com/view/photo/l/public/p2872969080.webp", "width": 1067, "height": 1600, "size": 0}, "raw": null, "small": {"url": "https://img9.doubanio.com/view/photo/s/public/p2872969080.webp", "width": 400, "height": 600, "size": 0}, "normal": {"url": "https://img9.doubanio.com/view/photo/m/public/p2872969080.webp", "width": 400, "height": 600, "size": 0}, "is_animated": false}, "create_time": "2022-05-13 15:00:33", "collections_count": 0, "reshares_count": 0, "id": "2872969080", "author": {"loc": {"id": "118267", "name": "\u957f\u6c99", "uid": "changsha"}, "kind": "user", "name": "\u98ce\u665a", "url": "https://www.douban.com/people/47848353/", "reg_time": "2010-12-03 22:17:07", "uri": "douban://douban.com/user/47848353", "avatar_side_icon_id": "", "avatar": "https://img9.doubanio.com/img/files/file-1609845567.png", "id": "47848353", "type": "user", "avatar_side_icon": "", "uid": "47848353"}, "is_collected": false, "subtype": "photo", "type": "photo", "owner_uri": "douban://douban.com/tv/35371695", "status": null, "reaction_type": 0, "description": "", "sharing_url": "https://www.douban.com/doubanapp/dispatch?uri=/photo/2872969080/", "url": "https://movie.douban.com/photos/photo/2872969080/", "reply_limit": "A", "uri": "douban://douban.com/photo/2872969080", "likers_count": 0, "reactions_count": 0, "comments_count": 0, "position": 44}], "w": 17, "total": 92, "start": 0, "movie_info": {"id": "35371695", "title": "\u51ed\u680f\u4e00\u7247\u98ce\u4e91\u8d77", "original_title": "", "year": "2022", "is_tv": true, "rating": null, "poster": "https://img9.doubanio.com/view/photo/m_ratio_poster/public/p2872956902.webp"}}