{"stats": [0.006157635467980296, 0.038177339901477834, 0.18472906403940886, 0.4039408866995074, 0.3669950738916256], "doing_count": 140, "wish_count": 2454, "wish_friends": {"total": 0, "users": []}, "type_ranks": [], "following": null, "done_count": 1135, "movie_info": {"id": "26247838", "title": "\u68a6\u6ee8\u57ce", "original_title": "Moonbeam City", "year": "2015", "is_tv": true, "rating": {"count": 1020, "max": 10, "star_count": 4.0, "value": 8.2}, "poster": "https://img9.doubanio.com/view/photo/m_ratio_poster/public/p2565504152.webp"}}