{"stats": [0.011764705882352941, 0.054901960784313725, 0.3352941176470588, 0.4176470588235294, 0.1803921568627451], "doing_count": 70, "wish_count": 267, "wish_friends": {"total": 0, "users": []}, "type_ranks": [], "following": null, "done_count": 779, "movie_info": {"id": "26342208", "title": "\u559c\u5f53\u7237", "original_title": "Grandfathered", "year": "2015", "is_tv": true, "rating": {"count": 703, "max": 10, "star_count": 3.5, "value": 7.4}, "poster": "https://img9.doubanio.com/view/photo/m_ratio_poster/public/p2257889667.webp"}}