{"stats": [0.004288777698355968, 0.02215868477483917, 0.09077912794853467, 0.39313795568263044, 0.4896354538956397], "doing_count": 0, "wish_count": 119422, "wish_friends": {"total": 0, "users": []}, "type_ranks": [{"type": "\u5267\u60c5\u7247", "rank": 0.82}], "following": null, "done_count": 12515, "movie_info": {"id": "27305997", "title": "\u6912\u9ebb\u5802\u4f1a", "original_title": "", "year": "2021", "is_tv": false, "rating": {"count": 11020, "max": 10, "star_count": 4.5, "value": 8.7}, "poster": "https://img1.doubanio.com/view/photo/m_ratio_poster/public/p2666413657.webp"}}