{"stats": [0.029411764705882353, 0.17647058823529413, 0.39705882352941174, 0.27941176470588236, 0.11764705882352941], "doing_count": 26, "wish_count": 24, "wish_friends": {"total": 0, "users": []}, "type_ranks": [], "following": null, "done_count": 83, "movie_info": {"id": "36112213", "title": "\u7231\u60c5\u76f2\u9009 \u7b2c\u56db\u5b63", "original_title": "Love Is Blind Season 4", "year": "2023", "is_tv": true, "rating": {"count": 82, "max": 10, "star_count": 3.5, "value": 6.6}, "poster": "https://img2.doubanio.com/view/photo/m_ratio_poster/public/p2889722993.webp"}}