{"recommendations": [{"rating": {"count": 0, "max": 10, "star_count": 0.0, "value": 0}, "alg_json": "{\"recall\":\"cf_TUUT\",\"name\":\"no_stype\",\"stype\":\"None\"}", "sharing_url": "https://movie.douban.com/subject/35633610/", "title": "\u65e0\u6240\u754f\u60e7", "url": "https://movie.douban.com/subject/35633610/", "pic": {"large": "https://img1.doubanio.com/view/photo/m_ratio_poster/public/p2880616797.webp", "normal": "https://img1.doubanio.com/view/photo/s_ratio_poster/public/p2880616797.webp"}, "uri": "douban://douban.com/tv/35633610", "interest": null, "type": "tv", "id": "35633610"}, {"rating": {"count": 0, "max": 10, "star_count": 0.0, "value": 0}, "alg_json": "{\"recall\":\"cf_TUUT\",\"name\":\"no_stype\",\"stype\":\"None\"}", "sharing_url": "https://movie.douban.com/subject/35723952/", "title": "\u5982\u679c\u8fd8\u6709\u65f6\u95f4", "url": "https://movie.douban.com/subject/35723952/", "pic": {"large": "https://img1.doubanio.com/view/photo/m_ratio_poster/public/p2874946948.webp", "normal": "https://img1.doubanio.com/view/photo/s_ratio_poster/public/p2874946948.webp"}, "uri": "douban://douban.com/tv/35723952", "interest": null, "type": "tv", "id": "35723952"}, {"rating": {"count": 0, "max": 10, "star_count": 0.0, "value": 0}, "alg_json": "{\"recall\":\"cf_TUUT\",\"name\":\"no_stype\",\"stype\":\"None\"}", "sharing_url": "https://movie.douban.com/subject/35587662/", "title": "\u88c5\u8154\u542f\u793a\u5f55", "url": "https://movie.douban.com/subject/35587662/", "pic": {"large": "https://img9.doubanio.com/view/photo/m_ratio_poster/public/p2883890276.webp", "normal": "https://img9.doubanio.com/view/photo/s_ratio_poster/public/p2883890276.webp"}, "uri": "douban://douban.com/tv/35587662", "interest": null, "type": "tv", "id": "35587662"}, {"rating": {"count": 0, "max": 10, "star_count": 0.0, "value": 0}, "alg_json": "{\"recall\":\"cf_TUUT\",\"name\":\"no_stype\",\"stype\":\"None\"}", "sharing_url": "https://movie.douban.com/subject/36094754/", "title": "\u9010\u6708", "url": "https://movie.douban.com/subject/36094754/", "pic": {"large": "https://img9.doubanio.com/view/photo/m_ratio_poster/public/p2891833515.webp", "normal": "https://img9.doubanio.com/view/photo/s_ratio_poster/public/p2891833515.webp"}, "uri": "douban://douban.com/tv/36094754", "interest": null, "type": "tv", "id": "36094754"}, {"rating": {"count": 0, "max": 10, "star_count": 0.0, "value": 0}, "alg_json": "{\"recall\":\"cf_TUUT\",\"name\":\"no_stype\",\"stype\":\"None\"}", "sharing_url": "https://movie.douban.com/subject/36117468/", "title": "\u82b1\u6837\u5c11\u5e74\u5c11\u5973", "url": "https://movie.douban.com/subject/36117468/", "pic": {"large": "https://img1.doubanio.com/view/photo/m_ratio_poster/public/p2881651740.webp", "normal": "https://img1.doubanio.com/view/photo/s_ratio_poster/public/p2881651740.webp"}, "uri": "douban://douban.com/tv/36117468", "interest": null, "type": "tv", "id": "36117468"}, {"rating": {"count": 0, "max": 10, "star_count": 0.0, "value": 0}, "alg_json": "{\"recall\":\"cf_TUUT\",\"name\":\"no_stype\",\"stype\":\"None\"}", "sharing_url": "https://movie.douban.com/subject/35691837/", "title": "\u5c0f\u57ce\u6545\u4e8b\u591a", "url": "https://movie.douban.com/subject/35691837/", "pic": {"large": "https://img9.doubanio.com/view/photo/m_ratio_poster/public/p2772976066.webp", "normal": "https://img9.doubanio.com/view/photo/s_ratio_poster/public/p2772976066.webp"}, "uri": "douban://douban.com/tv/35691837", "interest": null, "type": "tv", "id": "35691837"}, {"rating": {"count": 0, "max": 10, "star_count": 0.0, "value": 0}, "alg_json": "{\"recall\":\"cf_TUUT\",\"name\":\"no_stype\",\"stype\":\"None\"}", "sharing_url": "https://movie.douban.com/subject/35929218/", "title": "\u5954\u8dd1\u5427\uff0c\u6025\u6551\u533b\u751f", "url": "https://movie.douban.com/subject/35929218/", "pic": {"large": "https://img1.doubanio.com/view/photo/m_ratio_poster/public/p2882145330.webp", "normal": "https://img1.doubanio.com/view/photo/s_ratio_poster/public/p2882145330.webp"}, "uri": "douban://douban.com/tv/35929218", "interest": null, "type": "tv", "id": "35929218"}, {"rating": {"count": 0, "max": 10, "star_count": 0.0, "value": 0}, "alg_json": "{\"recall\":\"cf_TUUT\",\"name\":\"no_stype\",\"stype\":\"None\"}", "sharing_url": "https://movie.douban.com/subject/26744054/", "title": "\u6885\u82b1\u7ea2\u6843", "url": "https://movie.douban.com/subject/26744054/", "pic": {"large": "https://img1.doubanio.com/view/photo/m_ratio_poster/public/p2882792637.webp", "normal": "https://img1.doubanio.com/view/photo/s_ratio_poster/public/p2882792637.webp"}, "uri": "douban://douban.com/tv/26744054", "interest": null, "type": "tv", "id": "26744054"}, {"rating": {"count": 0, "max": 10, "star_count": 0.0, "value": 0}, "alg_json": "{\"recall\":\"cf_TUUT\",\"name\":\"no_stype\",\"stype\":\"None\"}", "sharing_url": "https://movie.douban.com/subject/35483390/", "title": "\u5c11\u5e74\u5df4\u6bd4\u4f26", "url": "https://movie.douban.com/subject/35483390/", "pic": {"large": "https://img1.doubanio.com/view/photo/m_ratio_poster/public/p2882792010.webp", "normal": "https://img1.doubanio.com/view/photo/s_ratio_poster/public/p2882792010.webp"}, "uri": "douban://douban.com/tv/35483390", "interest": null, "type": "tv", "id": "35483390"}, {"rating": {"count": 0, "max": 10, "star_count": 0.0, "value": 0}, "alg_json": "{\"recall\":\"cf_TUUT\",\"name\":\"no_stype\",\"stype\":\"None\"}", "sharing_url": "https://movie.douban.com/subject/35688417/", "title": "\u65f6\u5dee\u4e00\u4e07\u516c\u91cc", "url": "https://movie.douban.com/subject/35688417/", "pic": {"large": "https://img1.doubanio.com/view/photo/m_ratio_poster/public/p2766748707.webp", "normal": "https://img1.doubanio.com/view/photo/s_ratio_poster/public/p2766748707.webp"}, "uri": "douban://douban.com/tv/35688417", "interest": null, "type": "tv", "id": "35688417"}, {"rating": {"count": 0, "max": 10, "star_count": 0.0, "value": 0}, "alg_json": "{\"recall\":\"cf_TUUT\",\"name\":\"no_stype\",\"stype\":\"None\"}", "sharing_url": "https://movie.douban.com/subject/35653132/", "title": "\u6551\u63f4\u533b\u751f", "url": "https://movie.douban.com/subject/35653132/", "pic": {"large": "https://img1.doubanio.com/view/photo/m_ratio_poster/public/p2717498187.webp", "normal": "https://img1.doubanio.com/view/photo/s_ratio_poster/public/p2717498187.webp"}, "uri": "douban://douban.com/tv/35653132", "interest": null, "type": "tv", "id": "35653132"}, {"rating": {"count": 0, "max": 10, "star_count": 0.0, "value": 0}, "alg_json": "{\"recall\":\"cf_TUUT\",\"name\":\"no_stype\",\"stype\":\"None\"}", "sharing_url": "https://movie.douban.com/subject/35890456/", "title": "\u4eb2\u7231\u7684\u9690\u5c45\u5148\u751f", "url": "https://movie.douban.com/subject/35890456/", "pic": {"large": "https://img9.doubanio.com/view/photo/m_ratio_poster/public/p2890613764.webp", "normal": "https://img9.doubanio.com/view/photo/s_ratio_poster/public/p2890613764.webp"}, "uri": "douban://douban.com/tv/35890456", "interest": null, "type": "tv", "id": "35890456"}, {"rating": {"count": 0, "max": 10, "star_count": 0.0, "value": 0}, "alg_json": "{\"recall\":\"cf_TUUT\",\"name\":\"no_stype\",\"stype\":\"None\"}", "sharing_url": "https://movie.douban.com/subject/35370850/", "title": "\u4eca\u5929\u7684\u5979\u4eec", "url": "https://movie.douban.com/subject/35370850/", "pic": {"large": "https://img9.doubanio.com/view/photo/m_ratio_poster/public/p2882734695.webp", "normal": "https://img9.doubanio.com/view/photo/s_ratio_poster/public/p2882734695.webp"}, "uri": "douban://douban.com/tv/35370850", "interest": null, "type": "tv", "id": "35370850"}, {"rating": {"count": 0, "max": 10, "star_count": 0.0, "value": 0}, "alg_json": "{\"recall\":\"cf_TUUT\",\"name\":\"no_stype\",\"stype\":\"None\"}", "sharing_url": "https://movie.douban.com/subject/35597519/", "title": "\u624b\u672f\u76f4\u64ad\u95f4", "url": "https://movie.douban.com/subject/35597519/", "pic": {"large": "https://img9.doubanio.com/view/photo/m_ratio_poster/public/p2885021216.webp", "normal": "https://img9.doubanio.com/view/photo/s_ratio_poster/public/p2885021216.webp"}, "uri": "douban://douban.com/tv/35597519", "interest": null, "type": "tv", "id": "35597519"}, {"rating": {"count": 0, "max": 10, "star_count": 0.0, "value": 0}, "alg_json": "{\"recall\":\"cf_TUUT\",\"name\":\"no_stype\",\"stype\":\"None\"}", "sharing_url": "https://movie.douban.com/subject/35653131/", "title": "\u6211\u548c\u5a5a\u59fb\u7684\u6218\u6597", "url": "https://movie.douban.com/subject/35653131/", "pic": {"large": "https://img2.doubanio.com/view/photo/m_ratio_poster/public/p2893467953.webp", "normal": "https://img2.doubanio.com/view/photo/s_ratio_poster/public/p2893467953.webp"}, "uri": "douban://douban.com/tv/35653131", "interest": null, "type": "tv", "id": "35653131"}, {"rating": {"count": 0, "max": 10, "star_count": 0.0, "value": 0}, "alg_json": "{\"recall\":\"cf_TUUT\",\"name\":\"no_stype\",\"stype\":\"None\"}", "sharing_url": "https://movie.douban.com/subject/35650750/", "title": "\u6700\u9065\u8fdc\u7684\u8ddd\u79bb", "url": "https://movie.douban.com/subject/35650750/", "pic": {"large": "https://img9.doubanio.com/view/photo/m_ratio_poster/public/p2882790195.webp", "normal": "https://img9.doubanio.com/view/photo/s_ratio_poster/public/p2882790195.webp"}, "uri": "douban://douban.com/tv/35650750", "interest": null, "type": "tv", "id": "35650750"}, {"rating": {"count": 0, "max": 10, "star_count": 0.0, "value": 0}, "alg_json": "{\"recall\":\"cf_TUUT\",\"name\":\"no_stype\",\"stype\":\"None\"}", "sharing_url": "https://movie.douban.com/subject/35370758/", "title": "\u4e0a\u6709\u8001\u4e0b\u6709\u5c0f", "url": "https://movie.douban.com/subject/35370758/", "pic": {"large": "https://img1.doubanio.com/view/photo/m_ratio_poster/public/p2870322158.webp", "normal": "https://img1.doubanio.com/view/photo/s_ratio_poster/public/p2870322158.webp"}, "uri": "douban://douban.com/tv/35370758", "interest": null, "type": "tv", "id": "35370758"}, {"rating": {"count": 0, "max": 10, "star_count": 0.0, "value": 0}, "alg_json": "{\"recall\":\"cf_TUUT\",\"name\":\"no_stype\",\"stype\":\"None\"}", "sharing_url": "https://movie.douban.com/subject/36250595/", "title": "\u5339\u592b\u53cb\u6cfd", "url": "https://movie.douban.com/subject/36250595/", "pic": {"large": "https://qnmob3.doubanio.com/f/frodo/568eb8fac54d39fe599b0de8c3f2aee1dbc43cf0/pics/subject/tv_large.jpg?imageView2/2/q/80/w/600/h/3000/format/webp", "normal": "https://qnmob3.doubanio.com/f/frodo/9585cef1614d973b58dfd90d84394397922c67bd/pics/subject/tv_normal.png?imageView2/2/q/80/w/200/h/300/format/webp"}, "uri": "douban://douban.com/tv/36250595", "interest": null, "type": "tv", "id": "36250595"}, {"rating": {"count": 0, "max": 10, "star_count": 0.0, "value": 0}, "alg_json": "{\"recall\":\"cf_TUUT\",\"name\":\"no_stype\",\"stype\":\"None\"}", "sharing_url": "https://movie.douban.com/subject/35490184/", "title": "\u597d\u4e8b\u6210\u53cc", "url": "https://movie.douban.com/subject/35490184/", "pic": {"large": "https://img1.doubanio.com/view/photo/m_ratio_poster/public/p2893494578.webp", "normal": "https://img1.doubanio.com/view/photo/s_ratio_poster/public/p2893494578.webp"}, "uri": "douban://douban.com/tv/35490184", "interest": null, "type": "tv", "id": "35490184"}, {"rating": {"count": 0, "max": 10, "star_count": 0.0, "value": 0}, "alg_json": "{\"recall\":\"cf_TUUT\",\"name\":\"no_stype\",\"stype\":\"None\"}", "sharing_url": "https://movie.douban.com/subject/35653133/", "title": "\u597d\u56e2\u5706", "url": "https://movie.douban.com/subject/35653133/", "pic": {"large": "https://img9.doubanio.com/view/photo/m_ratio_poster/public/p2893468036.webp", "normal": "https://img9.doubanio.com/view/photo/s_ratio_poster/public/p2893468036.webp"}, "uri": "douban://douban.com/tv/35653133", "interest": null, "type": "tv", "id": "35653133"}], "movie_info": {"id": "35173643", "title": "\u4e00\u8def\u671d\u9633", "original_title": "", "year": "2023", "is_tv": true, "rating": {"count": 0, "max": 10, "star_count": 0.0, "value": 0}, "poster": "https://img9.doubanio.com/view/photo/m_ratio_poster/public/p2896721936.webp"}}